Workbook

Sheet SOUTH
A2: REPUBLIC OF THE PHILIPPINES
A3: PROVINCIAL GOVERNMENT OF PALAWAN
A4: PROVICIAL ENGINEEING OFFICE
A5: CAPITOL COMPLEX, PUERTO PRINCESA CITY
A7: PROVINCIAL ROAD NETWORK AND ITS STATUS / CONDITION
A8: PRIORITY OF THE SCHEDULE OF REHAB FROM JULY 2025 - DECEMBER 2025
A9: SOUTH MUNICIPALITY OF PALAWAN
A11: NO. | B11: ROAD ID | C11: ROAD NAME | D11: 2024LENGTH (KM) | E11: LENGTH (KM) | F11: SURFACE TYPE (KM) | J11: ROAD CONDITION | K11: TOTAL KM OF PROVINCIAL ROAD NEED TO CONDUCT VEGETATION CONTROL(KM) | L11: TOTAL KM OF PROVINCIAL ROAD NEED TO REHAB(KM) | M11: with concreting | N11: NOTE | O11: KILOMETER POST
F12: CONCRETE | G12: ASPHALT | H12: EARTH | I12: GRAVEL
B13: MUNICIPALITY OF ABORLAN
A14: 1 | B14: 1 | C14: Sagpangan Road | D14: 3.47 | E14: ='[1]road inventory 2018'!C11 -> 5.5 | F14: 0 | G14: 0 | H14: 0 | I14: =D14-F14 -> 3.47 | J14: Good | K14: =SUM(F14:I14) -> 3.47 | L14: =SUM(G14:J14) -> 3.47 | M14: **exchange with Mailigan - Sagpangan | N14: km sta.66+400 | Q14: 23
A15: 2 | B15: 93 | C15: Iraan - Baraki Road | D15: 3.97 | E15: ='[1]road inventory 2018'!C15 -> 3.9 | F15: 3.69 | G15: 0 | H15: 0 | I15: =D15-F15 -> 0.28 | J15: Fair | K15: =SUM(F15:I15) -> 3.97 | L15: =SUM(G15:J15) -> 0.28 | N15: km sta.64+900 | O15: ok | Q15: 14
A16: 3 | B16: 4 | C16: Iraan - Tubig Road | D16: 2.77 | E16: ='[1]road inventory 2018'!C14 -> 2.7 | F16: 0.19 | G16: 0 | H16: 0 | I16: =D16-F16 -> 2.58 | J16: Fair | K16: =SUM(F16:I16) -> 2.77 | L16: =SUM(G16:J16) -> 2.58 | N16: km sta.64+900 | Q16: 13
A17: 4 | B17: 13 | C17: New Bantayan - Apis Road | D17: 1.75 | E17: ='[1]road inventory 2018'!C24 -> 1.7 | F17: 0 | G17: 0 | H17: 0 | I17: =D17-F17 -> 1.75 | J17: Poor | K17: =SUM(F17:I17) -> 1.75 | L17: =SUM(G17:J17) -> 1.75 | N17: km sta.69+200 | O17: ok | Q17: 7
A18: 5 | B18: 220 | C18: Tagbariri - Magsaysay Road | D18: 3 | E18: ='[1]road inventory 2018'!C26 -> 2.3 | F18: 0.325 | G18: 0 | H18: 0 | I18: =D18-F18 -> 2.675 | J18: Poor | K18: =SUM(F18:I18) -> 3 | L18: =SUM(G18:J18) -> 2.675 | N18: km sta.71+150 | O18: ok | Q18: 6
A19: 6 | B19: 12 | C19: Tagbariri Road | D19: 1.65 | E19: ='[1]road inventory 2018'!C25 -> 1.6 | F19: 0.86 | G19: 0 | H19: 0 | I19: =D19-F19 -> 0.79 | J19: Poor | K19: =SUM(F19:I19) -> 1.65 | L19: =SUM(G19:J19) -> 0.79 | N19: km sta.69+100 | O19: ok | Q19: 8
A20: 7 | B20: 16 | C20: Tigman - Caburian Road | D20: 1.028 | E20: ='[1]road inventory 2018'!C29 -> 1 | F20: 0 | G20: 0 | H20: 0 | I20: =D20-F20 -> 1.028 | J20: Fair | K20: =SUM(F20:I20) -> 1.028 | L20: =SUM(G20:J20) -> 1.028 | N20: km sta.78+150 | O20: ok | Q20: 5
A21: 8 | B21: 15 | C21: Tigman - Rizal Road | D21: 3.2 | E21: 3.2 | F21: 0 | G21: 0 | H21: 0 | I21: =D21-F21 -> 3.2 | J21: Poor | K21: =SUM(F21:I21) -> 3.2 | L21: =SUM(G21:J21) -> 3.2 | N21: km sta.77+400 | O21: NOT EXISTING | Q21: 4
A22: 9 | B22: 221 | C22: Hi-way Jct. Plaridel-Tigman-Caburian Rd | D22: 4.07 | E22: ='[1]road inventory 2018'!C32 -> 5.2 | F22: 1.56 | G22: 0 | H22: 0 | I22: =D22-F22 -> 2.51 | J22: Fair | K22: =SUM(F22:I22) -> 4.07 | L22: =SUM(G22:J22) -> 2.51 | N22: km sta.76+500 | O22: ok | Q22: 3
A23: 10 | B23: 10 | C23: Plaridel - Apis Cabigaan Road | D23: 13.9 | E23: ='[1]road inventory 2018'!C22 -> 13.6 | F23: 12.19 | G23: 0 | H23: 0 | I23: =D23-F23 -> 1.71 | J23: Good | K23: =SUM(F23:I23) -> 13.9 | L23: =SUM(G23:J23) -> 1.71 | N23: km sta.75+650 | Q23: 19
A24: 11 | B24: 218 | C24: Isaub - Sagpangan Road | D24: 4.77 | E24: ='[1]road inventory 2018'!C16 -> 5.8 | F24: 0 | G24: 0 | H24: 0 | I24: =D24-F24 -> 4.77 | J24: Fair | K24: =SUM(F24:I24) -> 4.77 | L24: =SUM(G24:J24) -> 4.77 | N24: km sta.58+000 | O24: ok | Q24: 21 | R24: SOUTH | S24: TOTAL MAINLAND
A25: 12 | B25: 2 | C25: Isaub - Marikit -Tubig Road | D25: 0.87 | E25: ='[1]road inventory 2018'!C12 -> 0.8 | F25: 0.43 | G25: 0 | H25: 0 | I25: =D25-F25 -> 0.44 | J25: Fair | K25: =SUM(F25:I25) -> 0.87 | L25: =SUM(G25:J25) -> 0.44 | N25: km sta.58+000 | Q25: 15
A26: 13 | B26: 5 | C26: PNAC Road | D26: 4.09 | E26: ='[1]road inventory 2018'!C17 -> 2.8 | F26: 3.537 | G26: 0 | H26: 0 | I26: =D26-F26 -> 0.553 | J26: Fair | K26: =SUM(F26:I26) -> 4.09 | L26: =SUM(G26:J26) -> 0.553 | M26: **exchange with San Juan Road | N26: km sta.64+900 | Q26: 12 | R26: =E38+#REF!+E59+E97+E132+E145+E152+E168 -> #REF! | S26: =R26+#REF! -> #REF!
A27: 14 | B27: 20 | C27: Aporawan-Daan-Cabigaan Road | D27: 7.668 | E27: ='[1]road inventory 2018'!C33 -> 7.6 | F27: 6.73 | G27: 0 | H27: 0 | I27: =D27-F27 -> 0.938 | J27: Good | K27: =SUM(F27:I27) -> 7.668 | L27: =SUM(G27:J27) -> 0.938
A28: 15 | B28: 219 | C28: Junction - Isaub Road | D28: 0.68 | E28: ='[1]road inventory 2018'!C10 -> 0.65 | F28: 0.68 | G28: 0 | H28: 0 | I28: =D28-F28 -> 0 | J28: Fair | K28: =SUM(F28:I28) -> 0.68 | L28: =SUM(G28:J28) -> 0 | N28: km sta.57+800 | O28: ok | Q28: 20
A29: 16 | B29: 3 | C29: Mailigan - Sagpangan Road | D29: 5.5 | E29: ='[1]road inventory 2018'!C13 -> 4.9 | F29: 5.5 | G29: 0 | H29: 0 | I29: =D29-F29 -> 0 | J29: Fair | K29: =SUM(F29:I29) -> 5.5 | L29: =SUM(G29:J29) -> 0 | M29: **exchange with Sagpangan Road | N29: km sta.62+400 | Q29: 22
A30: 17 | B30: 6 | C30: San Juan Road | D30: 2.67 | E30: ='[1]road inventory 2018'!C18 -> 3.9 | F30: 2.67 | G30: 0 | H30: 0 | I30: =D30-F30 -> 0 | J30: Good | K30: =SUM(F30:I30) -> 2.67 | L30: =SUM(G30:J30) -> 0 | M30: **exchange with PNAC | N30: km sta.66+400 | Q30: 11 | S30: =S26+#REF! -> #REF!
A31: 18 | B31: 7 | C31: Aborlan - River Landing | D31: 1.19 | E31: ='[1]road inventory 2018'!C19 -> 1.1 | F31: 1.19 | G31: 0 | H31: 0 | I31: =D31-F31 -> 0 | J31: Fair | K31: =SUM(F31:I31) -> 1.19 | L31: =SUM(G31:J31) -> 0 | N31: km sta.67+100 | O31: ok | Q31: 9
A32: 19 | B32: 8 | C32: Aborlan Poblacion Road | D32: 0.7 | E32: ='[1]road inventory 2018'!C20 -> 0.6 | F32: 0.7 | G32: 0 | H32: 0 | I32: =D32-F32 -> 0 | J32: Fair | K32: =SUM(F32:I32) -> 0.7 | L32: =SUM(G32:J32) -> 0 | N32: km sta.66+950 | O32: ok | Q32: 10
A33: 20 | B33: 9 | C33: Magbabadil - Cabigaan Road | D33: 9.1 | E33: ='[1]road inventory 2018'!C21 -> 9 | F33: 9.1 | G33: 0 | H33: 0 | I33: =D33-F33 -> 0 | J33: Good | K33: =SUM(F33:I33) -> 9.1 | L33: =SUM(G33:J33) -> 0 | N33: km sta.66+800 | P33: 8.646 | Q33: 18
A34: 21 | B34: 11 | C34: Tagpait Feeder Road | D34: 2.25 | E34: ='[1]road inventory 2018'!C23 -> 2.2 | F34: 2.25 | G34: 0 | H34: 0 | I34: =D34-F34 -> 0 | J34: Fair | K34: =SUM(F34:I34) -> 2.25 | L34: =SUM(G34:J34) -> 0 | N34: km sta.69+000 | O34: ok | Q34: 16
A35: 22 | B35: 14 | C35: Junction - Tigman Road | D35: 4.04 | E35: ='[1]road inventory 2018'!C27 -> 4 | F35: 4.04 | G35: 0 | H35: 0 | I35: =D35-F35 -> 0 | J35: Fair | K35: =SUM(F35:I35) -> 4.04 | L35: =SUM(G35:J35) -> 0 | N35: km sta.75+650 | O35: ok | Q35: 2
A36: 23 | B36: 17 | C36: Magbabadil - Baraki Road | D36: 4 | E36: ='[1]road inventory 2018'!C30 -> 4 | F36: 4 | G36: 0 | H36: 0 | I36: =D36-F36 -> 0 | J36: Good | K36: =SUM(F36:I36) -> 4 | L36: =SUM(G36:J36) -> 0 | N36: km sta.73+400 | O36: ok | P36: 1.422 | Q36: 17
A37: 24 | B37: 18 | C37: Tigman - Rizal - Dumangueña Road | D37: 10.58 | E37: ='[1]road inventory 2018'!C31 -> 10.5 | F37: 10.58 | G37: 0 | H37: 0 | I37: =D37-F37 -> 0 | J37: Fair | K37: =SUM(F37:I37) -> 10.58 | L37: =SUM(G37:J37) -> 0 | N37: km sta.77+400 | O37: cmgp 2019, 2kms | P37: ok | Q37: 1
C38: SUB-TOTAL | D38: =SUM(D14:D37) -> 96.916 | E38: =SUM(E28:E37) -> 40.85 | F38: =SUM(F14:F37) -> 70.222 | G38: =SUM(G14:G37) -> 0 | H38: =SUM(H14:H37) -> 0 | I38: =SUM(I14:I37) -> 26.694 | K38: =SUM(K14:K37) -> 96.916 | L38: =SUM(L14:L37) -> 26.694
B40: PROVINCIAL ROAD REHABILATION | D40: TOTAL LENGTH(KM) | F40: THICKNESS OF AGGREGATES NEEDED(M) | G40: WIDTH OF EMBANKMENT(M) | H40: APPROXIAMATE VOLUME NEEDED TO EMBANK THE AND CONDUCT REHAB
A41: 1 | B41: RIVER QUARRY/MOUNTAIN QUARRY | D41: =L38 -> 26.694 | F41: 0.1 | G41: 7 | H41: =D41*F41*1000*G41 -> 18685.8 | I41: CU.M | M41: =H41 -> 18685.8
B43: MUNICIPALITY OF BATARAZA
A44: 1 | B44: 80 | C44: Sandoval-Igang -Igang -Sarong Road | D44: 15.714 | E44: ='[1]road inventory 2018'!C154 -> 15.7 | F44: 2.57 | G44: 0 | H44: 0 | I44: =D44-F44 -> 13.144 | J44: Fair | K44: =SUM(F44:I44) -> 15.714 | L44: =SUM(G44:J44) -> 13.144 | N44: km sta.238+500 | O44: CARRIAGEWAY OKAY | P44: ok
A45: 2 | B45: 83 | C45: Sandoval Barak - Barakan Road | D45: 4.264 | E45: ='[1]road inventory 2018'!C157 -> 4.2 | F45: =0.328+0.091+0.13+0.039 -> 0.588 | G45: 0 | H45: 0 | I45: =D45-F45 -> 3.676 | J45: Fair | K45: =SUM(F45:I45) -> 4.264 | L45: =SUM(G45:J45) -> 3.676 | N45: km sta.238+500 | O45: CARRIAGEWAY OKAY | P45: ok
A46: 3 | B46: 81 | C46: Ocayan Road | D46: 3.9 | E46: ='[1]road inventory 2018'!C155 -> 3.8 | F46: 0.23 | G46: 0 | H46: 0 | I46: =D46-F46 -> 3.67 | J46: Poor | K46: =SUM(F46:I46) -> 3.9 | L46: =SUM(G46:J46) -> 3.67 | N46: km sta.243+580 | O46: CARRIAGEWAY OKAY | P46: ok
A47: 4 | B47: 88 | C47: Ocayan Bukid-Bukid Road | D47: 3.25 | E47: ='[1]road inventory 2018'!C162 -> 3.2 | F47: 0 | G47: 0 | H47: 0 | I47: =D47-F47 -> 3.25 | J47: Bad | K47: =SUM(F47:I47) -> 3.25 | L47: =SUM(G47:J47) -> 3.25 | N47: km sta.247+390 | O47: CARRIAGEWAY OKAY | P47: OK
A48: 5 | B48: 86 | C48: Culandanum - Tarusan Road | D48: 2.64 | E48: ='[1]road inventory 2018'!C160 -> 2.5 | F48: 0 | G48: 0 | H48: 2.5 | I48: =D48-F48-H48 -> 0.14 | J48: Bad | K48: =SUM(F48:I48) -> 2.64 | L48: =SUM(G48:J48) -> 2.64 | N48: km sta.242+770 | O48: CARRIAGEWAY OKAY | P48: ok
A49: 6 | B49: 85 | C49: San Juan - Sarong Road | D49: 2.851 | E49: ='[1]road inventory 2018'!C159 -> 2.8 | F49: 0 | G49: 0 | H49: 0 | I49: =D49-F49 -> 2.851 | J49: Fair | K49: =SUM(F49:I49) -> 2.851 | L49: =SUM(G49:J49) -> 2.851 | N49: km sta.242+020 | O49: CARRIAGEWAY OKAY | P49: OK
A50: 7 | B50: 82 | C50: Taratak Sea Road | D50: 5.42 | E50: ='[1]road inventory 2018'!C156 -> 5.4 | F50: =3.12 -> 3.12 | G50: 0 | H50: 0.404 | I50: =D50-F50-H50 -> 1.896 | J50: Good | K50: =SUM(F50:I50) -> 5.42 | L50: =SUM(G50:J50) -> 2.3 | N50: km sta.256+200 | O50: CARRIAGEWAY OKAY
A51: 8 | B51: 87 | C51: Brooke’s Pt.- Bataraza Friendship Fd. Rd | D51: 0.608 | E51: 0.5 | F51: 0 | G51: 0 | H51: 0 | I51: =D51-F51 -> 0.608 | J51: Fair | K51: =SUM(F51:I51) -> 0.608 | L51: =SUM(G51:J51) -> 0.608 | N51: km sta.211+270 | O51: CARRIAGEWAY OKAY | P51: ok
A52: 9 | B52: 84 | C52: Brooke’s Pt.- Bataraza Friendship Sea Rd | D52: 1.114 | E52: 1.1 | F52: 0.86 | G52: 0 | H52: 0 | I52: =D52-F52 -> 0.254 | J52: Fair | K52: =SUM(F52:I52) -> 1.114 | L52: =SUM(G52:J52) -> 0.254 | N52: km sta.211+270 | O52: CARRIAGEWAY OKAY | P52: ok
A53: 10 | B53: 95 | C53: a. Inogbong Sea Road | D53: 2.025 | E53: 2 | F53: 1.018 | G53: 0 | H53: 0 | I53: =D53-F53 -> 1.007 | J53: Fair | K53: =SUM(F53:I53) -> 2.025 | L53: =SUM(G53:J53) -> 1.007 | N53: km sta.215+100 | O53: CARRIAGEWAY OKAY | P53: ok
A54: 11 | C54: b. Inogbong Feeder Road | D54: 1.07 | E54: 1 | F54: 0.29 | G54: 0 | H54: 0 | I54: =D54-F54 -> 0.78 | J54: Poor | K54: =SUM(F54:I54) -> 1.07 | L54: =SUM(G54:J54) -> 0.78 | N54: km sta.215+100 | O54: CARRIAGEWAY OKAY | P54: ok
A55: 12 | B55: 94 | C55: Marangas Sea Road | D55: 0.634 | E55: ='[1]road inventory 2018'!C151 -> 0.6 | F55: 0 | G55: 0 | H55: 0 | I55: =D55-F55 -> 0.634 | J55: Fair | K55: =SUM(F55:I55) -> 0.634 | L55: =SUM(G55:J55) -> 0.634 | N55: km sta.217+260 | O55: CARRIAGEWAY OKAY
A56: 13 | B56: 78 | C56: Marangas Feeder Road | D56: 3.91 | E56: ='[1]road inventory 2018'!C152 -> 3.8 | F56: 0.708 | G56: 0 | H56: 0 | I56: =D56-F56 -> 3.202 | J56: Fair | K56: =SUM(F56:I56) -> 3.91 | L56: =SUM(G56:J56) -> 3.202 | N56: km sta.218+400 | O56: CARRIAGEWAY OKAY | P56: ok
A57: 14 | B57: 79 | C57: Iniam - Bono-bono Road | D57: 1.943 | E57: ='[1]road inventory 2018'!C153 -> 1.9 | F57: 0.12 | G57: 0 | H57: 0 | I57: =D57-F57 -> 1.823 | J57: Poor | K57: =SUM(F57:I57) -> 1.943 | L57: =SUM(G57:J57) -> 1.823 | N57: km sta.221+800 | O57: CARRIAGEWAY OKAY | P57: ok
A58: 15 | B58: 77 | C58: Bataraza Poblacion Road | D58: 0.7 | E58: ='[1]road inventory 2018'!C150 -> 0.7 | F58: 0.7 | G58: 0 | H58: 0 | I58: =D58-F58 -> 0 | J58: Good | K58: =SUM(F58:I58) -> 0.7 | L58: =SUM(G58:J58) -> 0 | N58: km sta.216+720 | O58: CARRIAGEWAY OKAY | P58: ok
C59: SUB-TOTAL | D59: =SUM(D44:D58) -> 50.043 | E59: =SUM(E53:E58) -> 10 | F59: =SUM(F44:F58) -> 10.204 | G59: =SUM(G44:G58) -> 0 | H59: =SUM(H44:H58) -> 2.904 | I59: =SUM(I44:I58) -> 36.935 | K59: =SUM(K44:K58) -> 50.043 | L59: =SUM(L44:L58) -> 39.839
B61: PROVINCIAL ROAD REHABILATION | D61: TOTAL LENGTH(KM) | F61: THICKNESS OF AGGREGATES NEEDED(M) | G61: WIDTH OF EMBANKMENT(M) | H61: APPROXIAMATE VOLUME NEEDED TO EMBANK THE AND CONDUCT REHAB
A62: 1 | B62: RIVER QUARRY/MOUNTAIN QUARRY | D62: =L59 -> 39.839 | F62: 0.1 | G62: 7 | H62: =D62*F62*1000*G62 -> 27887.3 | I62: CU.M | M62: =H62 -> 27887.3
B64: MUNICIPALITY OF BROOKE'S POINT
A65: 1 | B65: 48 | C65: Maasin Airport Road | D65: 2.229 | E65: =D65 -> 2.229 | F65: 0 | G65: 0 | H65: 0 | I65: =D65-F65 -> 2.229 | J65: Poor | K65: =SUM(F65:I65) -> 2.229 | L65: =SUM(G65:J65) -> 2.229 | N65: km sta.113+100 | O65: CARRIAGEWAY OKAY
A66: 2 | B66: 50 | C66: Maasin Rancho Road | D66: 7.73 | E66: =D66 -> 7.73 | F66: 1.6 | G66: 0 | H66: 0 | I66: =D66-F66 -> 6.13 | J66: Bad | K66: =SUM(F66:I66) -> 7.73 | L66: =SUM(G66:J66) -> 6.13 | N66: km sta.174+800- | O66: CARRIAGEWAY OKAY
A67: 3 | B67: 51 | C67: Ipilan Feeder Road | D67: 2.951 | E67: =D67 -> 2.951 | F67: 0 | G67: 0 | H67: 0 | I67: =D67-F67 -> 2.951 | J67: Fair | K67: =SUM(F67:I67) -> 2.951 | L67: =SUM(G67:J67) -> 2.951 | N67: km sta.182+050 | O67: CARRIAGEWAY OKAY
A68: 4 | B68: 52 | C68: Ipilan Rizal Road | D68: 6.667 | E68: =D68 -> 6.667 | F68: 0 | G68: 0 | H68: 0 | I68: =D68-F68 -> 6.667 | J68: Fair | K68: =SUM(F68:I68) -> 6.667 | L68: =SUM(G68:J68) -> 6.667 | N68: km sta.184+300 | O68: CARRIAGEWAY OKAY
A69: 5 | B69: 53 | C69: Ipilan Linao Road | D69: 6.507 | E69: =D69 -> 6.507 | F69: 5.665 | G69: 0 | H69: 0 | I69: =D69-F69 -> 0.842 | J69: Good | K69: =SUM(F69:I69) -> 6.507 | L69: =SUM(G69:J69) -> 0.842 | N69: km sta.180+150 | O69: CARRIAGEWAY OKAY
A70: 6 | B70: 54 | C70: Ipilan Sea Road | D70: 1.7 | E70: 1.6 | F70: 1.178 | G70: 0 | H70: 0 | I70: =D70-F70 -> 0.522 | J70: Good | K70: =SUM(F70:I70) -> 1.7 | L70: =SUM(G70:J70) -> 0.522 | N70: km sta.180+700 | O70: CARRIAGEWAY OKAY
A71: 7 | B71: 103 | C71: Barong-Barong Feeder Road | D71: 1.263 | E71: =D71 -> 1.263 | F71: 0.254 | G71: 0 | H71: 0 | I71: =D71-F71 -> 1.009 | J71: Fair | K71: =SUM(F71:I71) -> 1.263 | L71: =SUM(G71:J71) -> 1.009 | N71: km sta.182+700 | O71: CARRIAGEWAY OKAY
A72: 8 | B72: 55 | C72: Barong-Barong Danadio Road | D72: 4.202 | E72: =D72 -> 4.202 | F72: 0 | G72: 0 | H72: 0 | I72: =D72-F72 -> 4.202 | J72: Fair | K72: =SUM(F72:I72) -> 4.202 | L72: =SUM(G72:J72) -> 4.202 | N72: km sta.183+250 | O72: CARRIAGEWAY OKAY
A73: 9 | B73: 57 | C73: Tagusao Feeder Road | D73: 1.3 | E73: 1.3 | F73: 0.305 | G73: 0 | H73: 0 | I73: =D73-F73 -> 0.995 | J73: Poor | K73: =SUM(F73:I73) -> 1.3 | L73: =SUM(G73:J73) -> 0.995 | N73: km sta.183+500 | O73: CARRIAGEWAY OKAY
A74: 10 | B74: 58 | C74: Pintasan Sea Road | D74: 0.535 | E74: 0.3 | F74: 0 | G74: 0 | H74: 0 | I74: =D74-F74 -> 0.535 | J74: Fair | K74: =SUM(F74:I74) -> 0.535 | L74: =SUM(G74:J74) -> 0.535 | N74: km sta.185+500 | O74: CARRIAGEWAY OKAY
A75: 11 | B75: 59 | C75: Pintasan Feeder Road | D75: 0.824 | E75: 0.8 | F75: 0 | G75: 0 | H75: 0 | I75: =D75-F75 -> 0.824 | J75: Fair | K75: =SUM(F75:I75) -> 0.824 | L75: =SUM(G75:J75) -> 0.824 | N75: km sta.185+500 | O75: CARRIAGEWAY OKAY
A76: 12 | B76: 56 | C76: Ipilan - Mainit Road | D76: 5.718 | E76: =D76 -> 5.718 | F76: 1.852 | G76: 0 | H76: 0 | I76: =D76-F76 -> 3.866 | J76: Fair | K76: =SUM(F76:I76) -> 5.718 | L76: =SUM(G76:J76) -> 3.866 | N76: km sta.182+050 | O76: CARRIAGEWAY OKAY
A77: 13 | B77: 60 | C77: Junction Mainit Road | D77: 9.217 | E77: 9.2 | F77: 8.765 | G77: 0 | H77: 0 | I77: =D77-F77 -> 0.452 | J77: Good | K77: =SUM(F77:I77) -> 9.217 | L77: =SUM(G77:J77) -> 0.452 | N77: km sta.189+95 | O77: CARRIAGEWAY OKAY
A78: 14 | B78: 61 | C78: Mati Feder Road | D78: 4.52 | E78: 4.5 | F78: 1.618 | G78: 0 | H78: 0 | I78: =D78-F78 -> 2.902 | J78: Fair | K78: =SUM(F78:I78) -> 4.52 | L78: =SUM(G78:J78) -> 2.902 | N78: km sta.192+850 | O78: CARRIAGEWAY OKAY
A79: 15 | B79: 62 | C79: Tigaplan Feeder Road | D79: 2.102 | E79: 2 | F79: 0 | G79: 0 | H79: 0 | I79: =D79-F79 -> 2.102 | J79: Fair | K79: =SUM(F79:I79) -> 2.102 | L79: =SUM(G79:J79) -> 2.102 | N79: km sta.186+600 | O79: CARRIAGEWAY OKAY
A80: 16 | B80: 63 | C80: Suring - Lada Road | D80: 3.046 | E80: 0 | F80: 1.161 | G80: 0 | H80: 0 | I80: =D80-F80 -> 1.885 | J80: Fair | K80: =SUM(F80:I80) -> 3.046 | L80: =SUM(G80:J80) -> 1.885 | N80: km sta.187+450 | O80: CARRIAGEWAY OKAY
A81: 17 | B81: 98 | C81: Calasaguen Feeder Road | D81: 5.112 | E81: =D81 -> 5.112 | F81: 4.937 | G81: 0 | H81: 0 | I81: =D81-F81 -> 0.175 | J81: Good | K81: =SUM(F81:I81) -> 5.112 | L81: =SUM(G81:J81) -> 0.175 | N81: km sta.168+75 | O81: CARRIAGEWAY OKAY
A82: 18 | B82: 96 | C82: Tub - Tub - Amas Road | D82: 5.844 | E82: 5.7 | F82: 3.044 | G82: 0 | H82: 0 | I82: =D82-F82 -> 2.8 | J82: Good | K82: =SUM(F82:I82) -> 5.844 | L82: =SUM(G82:J82) -> 2.8 | N82: km sta.193+950 | O82: CARRIAGEWAY OKAY
A83: 19 | B83: 65 | C83: Oring - Oring Road | D83: 1.619 | E83: =D83 -> 1.619 | F83: 0 | G83: 0 | H83: 0 | I83: =D83-F83 -> 1.619 | J83: Fair | K83: =SUM(F83:I83) -> 1.619 | L83: =SUM(G83:J83) -> 1.619 | N83: km sta.195+500 | O83: CARRIAGEWAY OKAY
A84: 20 | B84: 66 | C84: Amas Feeder Road | D84: 3.888 | E84: =D84 -> 3.888 | F84: 0 | G84: 0 | H84: 0 | I84: =D84-F84 -> 3.888 | J84: Poor | K84: =SUM(F84:I84) -> 3.888 | L84: =SUM(G84:J84) -> 3.888 | N84: km sta.195+700 | O84: CARRIAGEWAY OKAY
A85: 21 | B85: 67 | C85: Tagpirara Sea Road | D85: 2.083 | E85: 1.9 | F85: 0.5 | G85: 0 | H85: 0 | I85: =D85-F85 -> 1.583 | J85: Poor | K85: =SUM(F85:I85) -> 2.083 | L85: =SUM(G85:J85) -> 1.583 | N85: km sta.198+800 | O85: CARRIAGEWAY OKAY
A86: 22 | B86: 68 | C86: Tagpirara Feeder Road | D86: 1.658 | E86: 1.6 | F86: 0.221 | G86: 0 | H86: 0 | I86: =D86-F86 -> 1.437 | J86: Poor | K86: =SUM(F86:I86) -> 1.658 | L86: =SUM(G86:J86) -> 1.437 | N86: km sta.198+800 | O86: CARRIAGEWAY OKAY
A87: 23 | B87: 69 | C87: Saraza Feeder Road | D87: 1.687 | E87: 1.6 | F87: 0 | G87: 0 | H87: 0 | I87: =D87-F87 -> 1.687 | J87: Poor | K87: =SUM(F87:I87) -> 1.687 | L87: =SUM(G87:J87) -> 1.687 | N87: km sta.201+200 | O87: CARRIAGEWAY OKAY
A88: 24 | B88: 70 | C88: Samariniana Feeder Road | D88: 2.4 | E88: 2.6 | F88: 0.787 | G88: 0 | H88: 0 | I88: =D88-F88 -> 1.613 | J88: Poor | K88: =SUM(F88:I88) -> 2.4 | L88: =SUM(G88:J88) -> 1.613 | N88: km sta.203+050 | O88: CARRIAGEWAY OKAY
A89: 25 | B89: 71 | C89: Saraza - Tagbalogo | D89: 2.727 | E89: 2.7 | F89: 0.124 | G89: 0 | H89: 0 | I89: =D89-F89 -> 2.603 | J89: Fair | K89: =SUM(F89:I89) -> 2.727 | L89: =SUM(G89:J89) -> 2.603 | N89: km sta.201+900 | O89: CARRIAGEWAY OKAY
A90: 26 | B90: 72 | C90: Salogon Feeder Road | D90: 2 | E90: 1.7 | F90: 1.99 | G90: 0 | H90: 0 | I90: =D90-F90 -> 0.01 | J90: Fair | K90: =SUM(F90:I90) -> 2 | L90: =SUM(G90:J90) -> 0.01 | N90: km sta.207+450 | O90: CARRIAGEWAY OKAY
A91: 27 | B91: 73 | C91: Malis - Pansur - Rabuk Road | D91: 5.732 | E91: 5.5 | F91: 0.018 | G91: 0 | H91: 0 | I91: =D91-F91 -> 5.714 | J91: Poor | K91: =SUM(F91:I91) -> 5.732 | L91: =SUM(G91:J91) -> 5.714 | N91: km sta.210+050 | O91: CARRIAGEWAY OKAY
A92: 28 | B92: 74 | C92: Malis Feeder Road | D92: 0.584 | E92: 0.5 | F92: 0 | G92: 0 | H92: 0 | I92: =D92-F92 -> 0.584 | J92: Poor | K92: =SUM(F92:I92) -> 0.584 | L92: =SUM(G92:J92) -> 0.584 | N92: km sta.210+050 | O92: CARRIAGEWAY OKAY
A93: 29 | B93: 75 | C93: Mambalot - Abuan Road | D93: 2.1 | E93: 2.1 | F93: 0 | G93: 0 | H93: 0 | I93: =D93-F93 -> 2.1 | J93: Poor | K93: =SUM(F93:I93) -> 2.1 | L93: =SUM(G93:J93) -> 2.1 | N93: km sta.176+600 | O93: CARRIAGEWAY OKAY
A94: 30 | B94: 76 | C94: Mainit-PSU Road | D94: 0.302 | E94: 0.2 | F94: 0.302 | G94: 0 | H94: 0 | I94: =D94-F94 -> 0 | J94: Fair | K94: =SUM(F94:I94) -> 0.302 | L94: =SUM(G94:J94) -> 0 | N94: km sta.192+850 | O94: CARRIAGEWAY OKAY
A95: 31 | B95: 97 | C95: Aribungos Feeder Road | D95: 8.56 | E95: =D95 -> 8.56 | F95: 8.56 | G95: 0 | H95: 0 | I95: =D95-F95 -> 0 | J95: Good | K95: =SUM(F95:I95) -> 8.56 | L95: =SUM(G95:J95) -> 0 | N95: km sta.186+100 | O95: CARRIAGEWAY OKAY
A96: 32 | B96: 64 | C96: Calasaguen Abubakar Road | D96: 3.8 | E96: =D96 -> 3.8 | F96: 3.8 | G96: 0 | H96: 0 | I96: =E96-F96 -> 0 | J96: Good | K96: =SUM(F96:I96) -> 3.8 | L96: =SUM(G96:J96) -> 0 | N96: km sta.170+750 | O96: CARRIAGEWAY OKAY
C97: SUB-TOTAL | D97: =SUM(D65:D96) -> 110.607 | E97: =SUM(E65:E94) -> 93.686 | F97: =SUM(F65:F96) -> 46.681 | G97: =SUM(G65:G96) -> 0 | H97: =SUM(H65:H96) -> 0 | I97: =SUM(I65:I96) -> 63.926 | K97: =SUM(K65:K96) -> 110.607 | L97: =SUM(L65:L96) -> 63.926
B99: PROVINCIAL ROAD REHABILATION | D99: TOTAL LENGTH(KM) | F99: THICKNESS OF AGGREGATES NEEDED(M) | G99: WIDTH OF EMBANKMENT(M) | H99: APPROXIAMATE VOLUME NEEDED TO EMBANK THE AND CONDUCT REHAB
A100: 1 | B100: RIVER QUARRY/MOUNTAIN QUARRY | D100: =L97 -> 63.926 | F100: 0.1 | G100: 7 | H100: =D100*F100*1000*G100 -> 44748.2 | I100: CU.M | M100: =H100 -> 44748.2
B102: MUNICIPALITY OF NARRA
A103: 1 | B103: 43 | C103: Aramaywan Parangue Road | D103: 13.24 | E103: ='[1]road inventory 2018'!C65 -> 12.7 | F103: 0.16 | G103: 0 | H103: 0 | I103: =D103-F103 -> 13.08 | J103: Bad | K103: =SUM(F103:I103) -> 13.24 | L103: =SUM(G103:J103) -> 13.08 | N103: km sta.120+750 | O103: CARRIAGEWAY OKAY | Q103: ok
A104: 2 | B104: 21 | C104: Sandoval Feeder Road | D104: 3.16 | E104: ='[1]road inventory 2018'!C41 -> 4.3 | F104: 0 | G104: 0 | H104: 0 | I104: =D104-F104 -> 3.16 | J104: Good | K104: =SUM(F104:I104) -> 3.16 | L104: =SUM(G104:J104) -> 3.16 | M104: **excahne with sandoval bagong sikat road (gravel ) | N104: km sta.79+500 | O104: CARRIAGEWAY OKAY | P104: 4.3 | Q104: ok
A105: 3 | B105: 104 | C105: Sandoval - Bagong Sikat Road | D105: 4.35 | E105: ='[1]road inventory 2018'!C67 -> 3.1 | F105: 4.14 | G105: 0 | H105: 0 | I105: =D105-F105 -> 0.21 | J105: Poor | K105: =SUM(F105:I105) -> 4.35 | L105: =SUM(G105:J105) -> 0.21 | M105: **replace with sandoval feeder road (concreted na dapat) | N105: km sta.81+500 | O105: CARRIAGEWAY OKAY | R105: ok
A106: 4 | B106: 22 | C106: Apo-Aporawan Section Road | D106: 4.033 | E106: ='[1]road inventory 2018'!C42 -> 3.9 | F106: 0 | G106: 0 | H106: 0 | I106: =D106-F106 -> 4.033 | J106: Poor | K106: =SUM(F106:I106) -> 4.033 | L106: =SUM(G106:J106) -> 4.033 | N106: km sta.80+770 | O106: CARRIAGEWAY OKAY | P106: ilipat sa aborlan | Q106: OK
A107: 5 | B107: 23 | C107: Malatgao - Babanitan Road | D107: 4.45 | E107: ='[1]road inventory 2018'!C43 -> 4.3 | F107: 2.93 | G107: 0 | H107: 0 | I107: =D107-F107 -> 1.52 | J107: Fair | K107: =SUM(F107:I107) -> 4.45 | L107: =SUM(G107:J107) -> 1.52 | N107: km sta.83+580 | O107: CARRIAGEWAY OKAY | Q107: OK
A108: 6 | B108: 25 | C108: Taritien Sea Road | D108: 1.769 | E108: ='[1]road inventory 2018'!C45 -> 1.7 | F108: 0 | G108: 0 | H108: 0 | I108: =D108-F108 -> 1.769 | J108: Fair | K108: =SUM(F108:I108) -> 1.769 | L108: =SUM(G108:J108) -> 1.769 | N108: km sta.85+500 | O108: CARRIAGEWAY OKAY | Q108: ok
A109: 7 | B109: 26 | C109: Taritien Section Road | D109: 6.02 | E109: ='[1]road inventory 2018'!C46 -> 5.9 | F109: 3.91 | G109: 0 | H109: 0 | I109: =D109-F109 -> 2.11 | J109: Good | K109: =SUM(F109:I109) -> 6.02 | L109: =SUM(G109:J109) -> 2.11 | N109: km sta.85+500 | O109: CARRIAGEWAY OKAY | P109: 1.85 | Q109: ok
...

Sheet  road inventory 2024
B2: LIST OF PROVINCIAL ROAD NETWORK
B6: ROAD ID | C6: ROAD NAME | D6: LENGTH (KM) | E6: LENGTH (KM) | F6: SURFACE TYPE (KM) | J6: ROAD CONDITION
F7: CONCRETE | G7: ASPHALT | H7: EARTH | I7: GRAVEL
B8: MUNICIPALITY OF ABORLAN
A9: 1 | B9: 219 | C9: Junction - Isaub Road | D9: 0.68 | E9: ='[1]road inventory 2018'!C10 -> 0.65 | F9: 0.68 | G9: 0 | H9: 0 | I9: =D9-F9-G9-H9 -> 0 | J9: Fair
A10: 2 | B10: 1 | C10: Sagpangan Road | D10: 3.47 | E10: ='[1]road inventory 2018'!C11 -> 5.5 | F10: 0 | G10: 0 | H10: 0 | I10: =D10-F10-G10-H10 -> 3.47 | J10: Good
A11: 3 | B11: 2 | C11: Isaub - Marikit -Tubig Road | D11: 0.87 | E11: ='[1]road inventory 2018'!C12 -> 0.8 | F11: 0.43 | G11: 0 | H11: 0 | I11: =D11-F11-G11-H11 -> 0.44 | J11: Fair
A12: 4 | B12: 3 | C12: Mailigan - Sagpangan Road | D12: 5.5 | E12: ='[1]road inventory 2018'!C13 -> 4.9 | F12: 5.5 | G12: 0 | H12: 0 | I12: =D12-F12-G12-H12 -> 0 | J12: Fair
A13: 5 | B13: 4 | C13: Iraan - Tubig Road | D13: 2.77 | E13: ='[1]road inventory 2018'!C14 -> 2.7 | F13: 0.19 | G13: 0 | H13: 0 | I13: =D13-F13-G13-H13 -> 2.58 | J13: Fair
A14: 6 | B14: 93 | C14: Iraan - Baraki Road | D14: 3.97 | E14: ='[1]road inventory 2018'!C15 -> 3.9 | F14: 3.69 | G14: 0 | H14: 0 | I14: =D14-F14-G14-H14 -> 0.28 | J14: Fair
A15: 7 | B15: 218 | C15: Isaub - Sagpangan Road | D15: 4.77 | E15: ='[1]road inventory 2018'!C16 -> 5.8 | F15: 0 | G15: 0 | H15: 0 | I15: =D15-F15-G15-H15 -> 4.77 | J15: Fair
A16: 8 | B16: 5 | C16: PNAC Road | D16: 4.09 | E16: ='[1]road inventory 2018'!C17 -> 2.8 | F16: 3.537 | G16: 0 | H16: 0 | I16: =D16-F16-G16-H16 -> 0.553 | J16: Fair
A17: 9 | B17: 6 | C17: San Juan Road | D17: 2.67 | E17: ='[1]road inventory 2018'!C18 -> 3.9 | F17: 2.67 | G17: 0 | H17: 0 | I17: =D17-F17-G17-H17 -> 0 | J17: Good
A18: 10 | B18: 7 | C18: Aborlan - River Landing | D18: 1.19 | E18: ='[1]road inventory 2018'!C19 -> 1.1 | F18: 1.19 | G18: 0 | H18: 0 | I18: =D18-F18-G18-H18 -> 0 | J18: Fair
A19: 11 | B19: 8 | C19: Aborlan Poblacion Road | D19: 0.7 | E19: ='[1]road inventory 2018'!C20 -> 0.6 | F19: 0.7 | G19: 0 | H19: 0 | I19: =D19-F19-G19-H19 -> 0 | J19: Fair
A20: 12 | B20: 9 | C20: Magbabadil - Cabigaan Road | D20: 9.1 | E20: ='[1]road inventory 2018'!C21 -> 9 | F20: 9.1 | G20: 0 | H20: 0 | I20: =D20-F20-G20-H20 -> 0 | J20: Good
... A26: 18 | B26: 14 | C26: Junction - Tigman Road | D26: 4.04 | E26: ='[1]road inventory 2018'!C27 -> 4 | F26: 4.04 | G26: 0 | H26: 0 | I26: =D26-F26-G26-H26 -> 0 | J26: Fair
A27: 19 | B27: 15 | C27: Tigman - Rizal Road | D27: 3.2 | E27: 3.2 | F27: 0 | G27: 0 | H27: 0 | I27: =D27-F27-G27-H27 -> 3.2 | J27: Poor
A28: 20 | B28: 16 | C28: Tigman - Caburian Road | D28: 1.028 | E28: ='[1]road inventory 2018'!C29 -> 1 | F28: 0 | G28: 0 | H28: 0 | I28: =D28-F28-G28-H28 -> 1.028 | J28: Fair
A29: 21 | B29: 17 | C29: Magbabadil - Baraki Road | D29: 4 | E29: ='[1]road inventory 2018'!C30 -> 4 | F29: 4 | G29: 0 | H29: 0 | I29: =D29-F29-G29-H29 -> 0 | J29: Good
A30: 22 | B30: 18 | C30: Tigman - Rizal - Dumangueña Road | D30: 10.58 | E30: ='[1]road inventory 2018'!C31 -> 10.5 | F30: 10.58 | G30: 0 | H30: 0 | I30: =D30-F30-G30-H30 -> 0 | J30: Fair
A31: 23 | B31: 221 | C31: Hi-way Jct. Plaridel-Tigman-Caburian Rd | D31: 4.07 | E31: ='[1]road inventory 2018'!C32 -> 5.2 | F31: 1.56 | G31: 0 | H31: 0 | I31: =D31-F31-G31-H31 -> 2.51 | J31: Fair
A32: 24 | B32: 20 | C32: Aporawan-Daan-Cabigaan Road | D32: 7.668 | E32: ='[1]road inventory 2018'!C33 -> 7.6 | F32: =6.73+0.938 -> 7.668 | G32: 0 | H32: 0 | I32: =D32-F32-G32-H32 -> 0 | J32: Good
C33: SUB-TOTAL | D33: =SUM(D9:D32) -> 96.916 | E33: =SUM(E9:E32) -> 98.55 | F33: =SUM(F9:F32) -> 72.16 | G33: =SUM(G9:G32) -> 0 | H33: =SUM(H9:H32) -> 0 | I33: =SUM(I9:I32) -> 24.756
H34: =H33+I33 -> 24.756
B35: MUNICIPALITY OF BALABAC
A36: 1 | B36: 91 | C36: Balabac-Catagupan Road | D36: 10.809 | E36: ='[1]road inventory 2018'!C169 -> 12.9 | F36: 10.311 | G36: 0 | H36: 0 | I36: =D36-F36-G36-H36 -> 0.498 | J36: Fair
A37: 2 | B37: 92 | C37: Catagupan - Agutayan Road | D37: 8.067 | E37: ='[1]road inventory 2018'!C170 -> 5.6 | F37: 8.067 | G37: 0 | H37: 0 | I37: =D37-F37-G37-H37 -> 0 | J37: Fair
C38: SUB-TOTAL | D38: =SUM(D36:D37) -> 18.876 | E38: =SUM(E36:E37) -> 18.5 | F38: =SUM(F36:F37) -> 18.378 | G38: =SUM(G36:G37) -> 0 | H38: =SUM(H36:H37) -> 0 | I38: =SUM(I36:I37) -> 0.498
H39: =H38+I38 -> 0.498
B40: MUNICIPALITY OF BATARAZA
A41: 1 | B41: 95 | C41: a. Inogbong Sea Road | D41: 2.025 | E41: 2 | F41: 1.018 | G41: 0 | H41: 0 | I41: =D41-F41-G41-H41 -> 1.007 | J41: Fair
A42: 2 | C42: b. Inogbong Feeder Road | D42: 1.07 | E42: 1 | F42: 0.29 | G42: 0 | H42: 0 | I42: =D42-F42-G42-H42 -> 0.78 | J42: Poor
A43: 3 | B43: 77 | C43: Bataraza Poblacion Road | D43: 0.7 | E43: ='[1]road inventory 2018'!C150 -> 0.7 | F43: 0.7 | G43: 0 | H43: 0 | I43: =D43-F43-G43-H43 -> 0 | J43: Good
A44: 4 | B44: 94 | C44: Marangas Sea Road | D44: 0.634 | E44: ='[1]road inventory 2018'!C151 -> 0.6 | F44: 0 | G44: 0 | H44: 0 | I44: =D44-F44-G44-H44 -> 0.634 | J44: Fair
A45: 5 | B45: 78 | C45: Marangas Feeder Road | D45: 3.91 | E45: ='[1]road inventory 2018'!C152 -> 3.8 | F45: 0.708 | G45: 0 | H45: 0 | I45: =D45-F45-G45-H45 -> 3.202 | J45: Fair
A46: 6 | B46: 79 | C46: Iniam - Bono-bono Road | D46: 1.943 | E46: ='[1]road inventory 2018'!C153 -> 1.9 | F46: 0.12 | G46: 0 | H46: 0 | I46: =D46-F46-G46-H46 -> 1.823 | J46: Poor
A47: 7 | B47: 80 | C47: Sandoval-Igang -Igang -Sarong Road | D47: 15.714 | E47: ='[1]road inventory 2018'!C154 -> 15.7 | F47: 2.57 | G47: 0 | H47: 0 | I47: =D47-F47-G47-H47 -> 13.144 | J47: Fair
A48: 8 | B48: 81 | C48: Ocayan Road | D48: 3.9 | E48: ='[1]road inventory 2018'!C155 -> 3.8 | F48: =0.23+3.33 -> 3.56 | G48: 0 | H48: 0 | I48: =D48-F48-G48-H48 -> 0.34 | J48: Poor
A49: 9 | B49: 82 | C49: Taratak Sea Road | D49: 5.42 | E49: ='[1]road inventory 2018'!C156 -> 5.4 | F49: =3.12 -> 3.12 | G49: 0 | H49: 0.404 | I49: =D49-F49-G49-H49 -> 1.896 | J49: Good
A50: 10 | B50: 83 | C50: Sandoval Barak - Barakan Road | D50: 4.264 | E50: ='[1]road inventory 2018'!C157 -> 4.2 | F50: =0.328+0.091+0.13+0.039 -> 0.588 | G50: 0 | H50: 0 | I50: =D50-F50-G50-H50 -> 3.676 | J50: Fair
A51: 11 | B51: 84 | C51: Brooke’s Pt.- Bataraza Friendship Sea Rd | D51: 1.114 | E51: 1.1 | F51: 0.86 | G51: 0 | H51: 0 | I51: =D51-F51-G51-H51 -> 0.254 | J51: Fair
A52: 12 | B52: 85 | C52: San Juan - Sarong Road | D52: 2.851 | E52: ='[1]road inventory 2018'!C159 -> 2.8 | F52: 0 | G52: 0 | H52: 0 | I52: =D52-F52-G52-H52 -> 2.851 | J52: Fair
A53: 13 | B53: 86 | C53: Culandanum - Tarusan Road | D53: 2.64 | E53: ='[1]road inventory 2018'!C160 -> 2.5 | F53: 0 | G53: 0 | H53: 2.5 | I53: =D53-F53-G53-H53 -> 0.14 | J53: Bad
A54: 14 | B54: 87 | C54: Brooke’s Pt.- Bataraza Friendship Fd. Rd | D54: 0.608 | E54: 0.5 | F54: 0 | G54: 0 | H54: 0 | I54: =D54-F54-G54-H54 -> 0.608 | J54: Fair
A55: 15 | B55: 88 | C55: Ocayan Bukid-Bukid Road | D55: 3.25 | E55: ='[1]road inventory 2018'!C162 -> 3.2 | F55: 0 | G55: 0 | H55: 0 | I55: =D55-F55-G55-H55 -> 3.25 | J55: Bad
C56: SUB-TOTAL | D56: =SUM(D41:D55) -> 50.043 | E56: =SUM(E41:E55) -> 49.2 | F56: =SUM(F41:F55) -> 13.534 | G56: =SUM(G41:G55) -> 0 | H56: =SUM(H41:H55) -> 2.904 | I56: =SUM(I41:I55) -> 33.605
H57: =H56+I56 -> 36.509
B58: MUNICIPALITY OF BROOKE'S POINT
A59: 1 | B59: 48 | C59: Maasin Airport Road | D59: 2.229 | E59: =D59 -> 2.229 | F59: 0 | G59: 0 | H59: 0 | I59: =D59-F59-G59-H59 -> 2.229 | J59: Poor
A60: 2 | B60: 50 | C60: Maasin Rancho Road | D60: 7.73 | E60: =D60 -> 7.73 | F60: 1.6 | G60: 0 | H60: 0 | I60: =D60-F60-G60-H60 -> 6.13 | J60: Bad
A61: 3 | B61: 51 | C61: Ipilan Feeder Road | D61: 2.951 | E61: =D61 -> 2.951 | F61: 0 | G61: 0 | H61: 0 | I61: =D61-F61-G61-H61 -> 2.951 | J61: Fair
A62: 4 | B62: 52 | C62: Ipilan Rizal Road | D62: 6.667 | E62: =D62 -> 6.667 | F62: 0 | G62: 0 | H62: 0 | I62: =D62-F62-G62-H62 -> 6.667 | J62: Fair
A63: 5 | B63: 53 | C63: Ipilan Linao Road | D63: 6.507 | E63: =D63 -> 6.507 | F63: 5.665 | G63: 0 | H63: 0 | I63: =D63-F63-G63-H63 -> 0.842 | J63: Good
A64: 6 | B64: 54 | C64: Ipilan Sea Road | D64: 1.7 | E64: 1.6 | F64: 1.178 | G64: 0 | H64: 0 | I64: =D64-F64-G64-H64 -> 0.522 | J64: Good
A65: 7 | B65: 103 | C65: Barong-Barong Feeder Road | D65: 1.263 | E65: =D65 -> 1.263 | F65: 0.254 | G65: 0 | H65: 0 | I65: =D65-F65-G65-H65 -> 1.009 | J65: Fair
A66: 8 | B66: 55 | C66: Barong-Barong Danadio Road | D66: 4.202 | E66: =D66 -> 4.202 | F66: 0 | G66: 0 | H66: 0 | I66: =D66-F66-G66-H66 -> 4.202 | J66: Fair
A67: 9 | B67: 57 | C67: Tagusao Feeder Road | D67: 1.3 | E67: 1.3 | F67: 0.305 | G67: 0 | H67: 0 | I67: =D67-F67-G67-H67 -> 0.995 | J67: Poor
A68: 10 | B68: 58 | C68: Pintasan Sea Road | D68: 0.535 | E68: 0.3 | F68: 0 | G68: 0 | H68: 0 | I68: =D68-F68-G68-H68 -> 0.535 | J68: Fair
A69: 11 | B69: 59 | C69: Pintasan Feeder Road | D69: 0.824 | E69: 0.8 | F69: 0 | G69: 0 | H69: 0 | I69: =D69-F69-G69-H69 -> 0.824 | J69: Fair
A70: 12 | B70: 97 | C70: Aribungos Feeder Road | D70: 8.56 | E70: =D70 -> 8.56 | F70: 8.56 | G70: 0 | H70: 0 | I70: =D70-F70-G70-H70 -> 0 | J70: Good
A71: 13 | B71: 56 | C71: Ipilan - Mainit Road | D71: 5.718 | E71: =D71 -> 5.718 | F71: 1.852 | G71: 0 | H71: 0 | I71: =D71-F71-G71-H71 -> 3.866 | J71: Fair
A72: 14 | B72: 60 | C72: Junction Mainit Road | D72: 9.217 | E72: 9.2 | F72: 8.765 | G72: 0 | H72: 0 | I72: =D72-F72-G72-H72 -> 0.452 | J72: Good
A73: 15 | B73: 61 | C73: Mati Feder Road | D73: 4.52 | E73: 4.5 | F73: 1.618 | G73: 0 | H73: 0 | I73: =D73-F73-G73-H73 -> 2.902 | J73: Fair
A74: 16 | B74: 62 | C74: Tigaplan Feeder Road | D74: 2.102 | E74: 2 | F74: 0 | G74: 0 | H74: 0 | I74: =D74-F74-G74-H74 -> 2.102 | J74: Fair
A75: 17 | B75: 63 | C75: Suring - Lada Road | D75: 3.046 | E75: 0 | F75: =1.161+1.885 -> 3.046 | G75: 0 | H75: 0 | I75: =D75-F75-G75-H75 -> -4.4408921e-16 | J75: Fair
A76: 18 | B76: 98 | C76: Calasaguen Feeder Road | D76: 5.112 | E76: =D76 -> 5.112 | F76: 4.937 | G76: 0 | H76: 0 | I76: =D76-F76-G76-H76 -> 0.175 | J76: Good
A77: 19 | B77: 64 | C77: Calasaguen Abubakar Road | D77: 3.8 | E77: =D77 -> 3.8 | F77: 3.8 | G77: 0 | H77: 0 | I77: =D77-F77-G77-H77 -> 0 | J77: Good
A78: 20 | B78: 96 | C78: Tub - Tub - Amas Road | D78: 5.844 | E78: 5.7 | F78: 3.044 | G78: 0 | H78: 0 | I78: =D78-F78-G78-H78 -> 2.8 | J78: Good
A79: 21 | B79: 65 | C79: Oring - Oring Road | D79: 1.619 | E79: =D79 -> 1.619 | F79: 0 | G79: 0 | H79: 0 | I79: =D79-F79-G79-H79 -> 1.619 | J79: Fair
A80: 22 | B80: 66 | C80: Amas Feeder Road | D80: 3.888 | E80: =D80 -> 3.888 | F80: 0 | G80: 0 | H80: 0 | I80: =D80-F80-G80-H80 -> 3.888 | J80: Poor
A81: 23 | B81: 67 | C81: Tagpirara Sea Road | D81: 2.083 | E81: 1.9 | F81: 0.5 | G81: 0 | H81: 0 | I81: =D81-F81-G81-H81 -> 1.583 | J81: Poor
A82: 24 | B82: 68 | C82: Tagpirara Feeder Road | D82: 1.658 | E82: 1.6 | F82: 0.221 | G82: 0 | H82: 0 | I82: =D82-F82-G82-H82 -> 1.437 | J82: Poor
A83: 25 | B83: 69 | C83: Saraza Feeder Road | D83: 1.687 | E83: 1.6 | F83: 0 | G83: 0 | H83: 0 | I83: =D83-F83-G83-H83 -> 1.687 | J83: Poor
A84: 26 | B84: 70 | C84: Samariniana Feeder Road | D84: 2.4 | E84: 2.6 | F84: 0.787 | G84: 0 | H84: 0 | I84: =D84-F84-G84-H84 -> 1.613 | J84: Poor
A85: 27 | B85: 71 | C85: Saraza - Tagbalogo | D85: 2.727 | E85: 2.7 | F85: 0.124 | G85: 0 | H85: 0 | I85: =D85-F85-G85-H85 -> 2.603 | J85: Fair
A86: 28 | B86: 72 | C86: Salogon Feeder Road | D86: 2 | E86: 1.7 | F86: 1.99 | G86: 0 | H86: 0 | I86: =D86-F86-G86-H86 -> 0.01 | J86: Fair
A87: 29 | B87: 73 | C87: Malis - Pansur - Rabuk Road | D87: 5.732 | E87: 5.5 | F87: 0.018 | G87: 0 | H87: 0 | I87: =D87-F87-G87-H87 -> 5.714 | J87: Poor
A88: 30 | B88: 74 | C88: Malis Feeder Road | D88: 0.584 | E88: 0.5 | F88: 0 | G88: 0 | H88: 0 | I88: =D88-F88-G88-H88 -> 0.584 | J88: Poor
A89: 31 | B89: 75 | C89: Mambalot - Abuan Road | D89: 2.1 | E89: 2.1 | F89: 0 | G89: 0 | H89: 0 | I89: =D89-F89-G89-H89 -> 2.1 | J89: Poor
A90: 32 | B90: 76 | C90: Mainit-PSU Road | D90: 0.302 | E90: 0.2 | F90: 0.302 | G90: 0 | H90: 0 | I90: =D90-F90-G90-H90 -> 0 | J90: Fair
C91: SUB-TOTAL | D91: =SUM(D59:D90) -> 110.607 | E91: =SUM(E59:E90) -> 106.046 | F91: =SUM(F59:F90) -> 48.566 | G91: =SUM(G59:G90) -> 0 | H91: =SUM(H59:H90) -> 0 | I91: =SUM(I59:I90) -> 62.041
H92: =H91+I91 -> 62.041
B93: MUNICIPALITY OF NARRA
A94: 1 | B94: 21 | C94: Sandoval Feeder Road | D94: 3.16 | E94: ='[1]road inventory 2018'!C41 -> 4.3 | F94: 0 | G94: 0 | H94: 0 | I94: =D94-F94-G94-H94 -> 3.16 | J94: Good
A95: 2 | B95: 22 | C95: Apo-Aporawan Section Road | D95: 4.033 | E95: ='[1]road inventory 2018'!C42 -> 3.9 | F95: 0 | G95: 0 | H95: 0 | I95: =D95-F95-G95-H95 -> 4.033 | J95: Poor
A96: 3 | B96: 23 | C96: Malatgao - Babanitan Road | D96: 4.45 | E96: ='[1]road inventory 2018'!C43 -> 4.3 | F96: 2.93 | G96: 0 | H96: 0 | I96: =D96-F96-G96-H96 -> 1.52 | J96: Fair
A97: 4 | B97: 24 | C97: Malatgao Section Road | D97: 8.36 | E97: 7.9 | F97: 8.36 | G97: 0 | H97: 0 | I97: =D97-F97-G97-H97 -> 0 | J97: Fair
A98: 5 | B98: 25 | C98: Taritien Sea Road | D98: 1.769 | E98: ='[1]road inventory 2018'!C45 -> 1.7 | F98: 0 | G98: 0 | H98: 0 | I98: =D98-F98-G98-H98 -> 1.769 | J98: Fair
A99: 6 | B99: 26 | C99: Taritien Section Road | D99: 6.02 | E99: ='[1]road inventory 2018'!C46 -> 5.9 | F99: 3.91 | G99: 0 | H99: 0 | I99: =D99-F99-G99-H99 -> 2.11 | J99: Good
A100: 7 | B100: 27 | C100: Antipuluan Sea Road | D100: 1.97 | E100: ='[1]road inventory 2018'!C47 -> 1.9 | F100: 0.3 | G100: 0 | H100: 0 | I100: =D100-F100-G100-H100 -> 1.67 | J100: Fair
A101: 8 | B101: 28 | C101: Lapu-Lapu Section Road | D101: 5.65 | E101: ='[1]road inventory 2018'!C48 -> 5.6 | F101: 2.79 | G101: 0 | H101: 0 | I101: =D101-F101-G101-H101 -> 2.86 | J101: Fair
A102: 9 | B102: 29 | C102: Narra School Road | D102: 0.88 | E102: ='[1]road inventory 2018'!C49 -> 0.8 | F102: 0.5 | G102: 0 | H102: 0 | I102: =D102-F102-G102-H102 -> 0.38 | J102: Good
A103: 10 | B103: 30 | C103: Rizal Avenue Section Road | D103: 2.15 | E103: ='[1]road inventory 2018'!C50 -> 2 | F103: 2.09 | G103: 0 | H103: 0 | I103: =D103-F103-G103-H103 -> 0.06 | J103: Fair
A104: 11 | B104: 106 | C104: Narra Panacan Road | D104: 3.283 | E104: ='[1]road inventory 2018'!C51 -> 3.2 | F104: 3.283 | G104: 0 | H104: 0 | I104: =D104-F104-G104-H104 -> 0 | J104: Good
A105: 12 | B105: 31 | C105: Ipil Road / Quirino | D105: 0.822 | E105: ='[1]road inventory 2018'!C52 -> 0.8 | F105: 0.822 | G105: 0 | H105: 0 | I105: =D105-F105-G105-H105 -> 0 | J105: Poor
A106: 13 | B106: 32 | C106: Guminubat Section Road | D106: 3 | E106: ='[1]road inventory 2018'!C53 -> 3 | F106: 0 | G106: 0 | H106: 0 | I106: =D106-F106-G106-H106 -> 3 | J106: Fair
A107: 14 | B107: 33 | C107: Malinao Feeder Road | D107: 2.52 | E107: ='[1]road inventory 2018'!C54 -> 2.4 | F107: 0.83 | G107: 0 | H107: 0 | I107: =D107-F107-G107-H107 -> 1.69 | J107: Poor
A108: 15 | B108: 34 | C108: Linamen Feeder Road | D108: 4.36 | E108: ='[1]road inventory 2018'!C55 -> 4.2 | F108: 1.06 | G108: 0 | H108: 0 | I108: =D108-F108-G108-H108 -> 3.3 | J108: Bad
A109: 16 | B109: 35 | C109: Caguisan Feeder Road | D109: 3.06 | E109: ='[1]road inventory 2018'!C56 -> 3 | F109: 2.28 | G109: 0 | H109: 0 | I109: =D109-F109-G109-H109 -> 0.78 | J109: Fair
...

Sheet UPDATED (FOR PRINTING) (2)
B1: PROVINCIAL ENGINEER'S OFFICE
B2: PROVINCIAL ROAD NETWORK AND ITS STATUS / CONDITION
B3: AS OF NOVEMBER 15, 2021
B6: MUNICIPALITY OF ABORLAN | R6: SOUTH | T6: NORTH | V6: ISLANDS
R7: =D34+D70+D87+D95+D111+D153+D175 -> 449.99 | T7: =D212+D246+D259+D283 -> 350.26 | V7: =D184+D317+D340+D370+D385+D399 -> 279.914
B8: ROAD ID | C8: ROAD NAME | D8: REVISED LENGTH (km/s.) | E8: OLD LENGTH | F8: SURFACE TYPE | K8: ROAD CONDITION | L8: KILOMETER POST | M8: REMARKS
F9: CONCRETE | G9: ASPHALT | H9: EARTH | I9: GRAVEL | J9: MIXED | Q9: TOTAL | R9: =R7+T7+V7 -> 1080.164 | T9: =R13-R9 -> 156.301 | V9: =(R9/R13)*100 -> 87.359044
A10: 1 | B10: 219 | C10: Junction - Isaub Road | D10: =SUM(F10:J10) -> 0.4 | E10: ='[1]road inventory 2018'!C10 -> 0.65 | F10: 0.25 | G10: 0 | H10: 0 | I10: 0.15 | J10: 0 | K10: FAIR | L10: km sta.57+800 | O10: =D10 -> 0.4 | Q10: New
A11: 2 | B11: 1 | C11: Sagpangan Road | D11: =SUM(F11:J11) -> 5.48 | E11: ='[1]road inventory 2018'!C11 -> 5.5 | F11: 4.88 | G11: 0 | H11: 0 | I11: 0.6 | J11: 0 | K11: GOOD | L11: km sta.66+400 | O11: =D11 -> 5.48 | Q11: Good | R11: =E34+E70+E87+E94+E111+E153+E175 -> 454.25 | T11: =E212+E231+E246+E259+E283 -> 417.85 | V11: =E184+E302+E317+E340+E370+E385+E399+D405 -> 364.365
A12: 3 | B12: 2 | C12: Isaub - Marikit -Tubig Road | D12: =+F12+G12+I12+H12 -> 0.92 | E12: ='[1]road inventory 2018'!C12 -> 0.8 | F12: 0.07 | G12: 0 | H12: 0 | I12: 0.85 | J12: 0 | K12: FAIR | L12: km sta.58+000 | O12: =D12 -> 0.92 | Q12: Fair
A13: 4 | B13: 3 | C13: Mailigan - Sagpangan Road | D13: =SUM(F13:J13) -> 4.97 | E13: ='[1]road inventory 2018'!C13 -> 4.9 | F13: 0 | G13: 0 | H13: 0 | I13: 4.97 | J13: 0 | K13: FAIR | L13: km sta.62+400 | N13: X | O13: =D13 -> 4.97 | Q13: Poor | R13: =R11+T11+V11 -> 1236.465
A14: 5 | B14: 4 | C14: Iraan - Tubig Road | D14: =+F14+G14+I14+H14 -> 2.67 | E14: ='[1]road inventory 2018'!C14 -> 2.7 | F14: 0 | G14: 0 | H14: 0 | I14: 2.67 | J14: 0 | K14: FAIR | L14: km sta.64+900 | N14: X | O14: =D14 -> 2.67 | Q14: Bad
A15: 6 | B15: 93 | C15: Iraan - Baraki Road | D15: =+F15+G15+I15+H15 -> 3.9 | E15: ='[1]road inventory 2018'!C15 -> 3.9 | F15: 3.79 | G15: 0 | H15: 0 | I15: 0.11 | J15: 0 | K15: FAIR | L15: km sta.64+900 | O15: =D15 -> 3.9 | R15: =E302+E309+E314+E326+E331+E335+E336+E338+E349+E358+E363+E365+E368+E381+E382+E383+E384 -> 175.06 | T15: =T9-R15 -> -18.759
A16: 7 | B16: 218 | C16: Isaub - Sagpangan Road | D16: =SUM(F16:J16) -> 5.61 | E16: ='[1]road inventory 2018'!C16 -> 5.8 | F16: 0 | G16: 0 | H16: 0 | I16: 5.61 | J16: 0 | K16: FAIR | L16: km sta.58+000 | O16: =D16 -> 5.61
A17: 8 | B17: 5 | C17: PNAC Road | D17: =SUM(F17:J17) -> 2.85 | E17: ='[1]road inventory 2018'!C17 -> 2.8 | F17: 2.85 | G17: 0 | H17: 0 | I17: 0 | J17: 0 | K17: FAIR | L17: km sta.64+900 | O17: =D17 -> 2.85 | R17: =E28+E47+E52+E82+T67 -> 8.47
A18: 9 | B18: 6 | C18: San Juan Road | D18: =+F18+G18+I18+H18 -> 3.96 | E18: ='[1]road inventory 2018'!C18 -> 3.9 | F18: =2.6+0.9 -> 3.5 | G18: 0 | H18: 0 | I18: 0.46 | J18: 0 | K18: GOOD | L18: km sta.66+400 | O18: =D18 -> 3.96
A19: 10 | B19: 7 | C19: Aborlan - River Landing | D19: 1.15 | E19: ='[1]road inventory 2018'!C19 -> 1.1 | F19: 1.15 | G19: 0 | H19: 0 | I19: 0 | J19: 0 | K19: FAIR | L19: km sta.67+100 | O19: =D19 -> 1.15 | Q19: GOOD TO FAIR (TOTAL LENGTH) | T19: ACTUAL
A20: 11 | B20: 8 | C20: Aborlan Poblacion Road | D20: =SUM(F20:J20) -> 0.64 | E20: ='[1]road inventory 2018'!C20 -> 0.6 | F20: 0.64 | G20: 0 | H20: 0 | I20: 0 | J20: 0 | K20: FAIR | L20: km sta.66+950 | O20: =D20 -> 0.64 | Q20: ABORLAN | R20: =D10+D11+D12+D13+D15+D16+D17+D18+D19+D20+D21+D22+D23+D24+D27+D29+D30+D31+D32 -> 81.36 | T20: =R20 -> 81.36
A21: 12 | B21: 9 | C21: Magbabadil - Cabigaan Road | D21: =+F21+G21+I21+H21 -> 9.3 | E21: ='[1]road inventory 2018'!C21 -> 9 | F21: 9.3 | G21: 0 | H21: 0 | I21: 0 | J21: 0 | K21: GOOD | L21: km sta.66+800 | O21: =D21 -> 9.3 | Q21: NARRA | R21: =D43+D44+D45+D46+D47+D48+D49+D50+D51+D52+D53++D54+D57+D58+D59+D60+D61+D62+D63+D66+D69 -> 72.35 | T21: =R21 -> 72.35
A22: 13 | B22: 10 | C22: Plaridel - Apis Cabigaan Road | D22: =SUM(F22:J22) -> 13.79 | E22: ='[1]road inventory 2018'!C22 -> 13.6 | F22: =8.47+1.31+0.34 -> 10.12 | G22: 0 | H22: 0 | I22: 3.67 | J22: 0 | K22: GOOD | L22: km sta.75+650 | O22: =D22 -> 13.79 | Q22: QUEZON | R22: =D80+D81+D82+D83+D84+D85 -> 28.02 | T22: =R22 -> 28.02
A23: 14 | B23: 11 | C23: Tagpait Feeder Road | D23: =SUM(F23:J23) -> 2.27 | E23: ='[1]road inventory 2018'!C23 -> 2.2 | F23: 1.3 | G23: 0 | H23: 0 | I23: 0.97 | J23: 0 | K23: FAIR | L23: km sta.69+000 | O23: =D23 -> 2.27 | Q23: RIZAL | R23: =D94 -> 3.28 | T23: =R23 -> 3.28
A24: 15 | B24: 13 | C24: New Bantayan - Apis Road | D24: =SUM(F24:J24) -> 1.72 | E24: ='[1]road inventory 2018'!C24 -> 1.7 | F24: 0 | G24: 0 | H24: 0 | I24: 1.72 | J24: 0 | K24: POOR | L24: km sta.69+200 | O24: =D24 -> 1.72 | Q24: ESPANOLA | R24: =D102+D104+D105+D106+D107+D108 -> 26.3 | T24: =R24 -> 26.3
A25: 16 | B25: 12 | C25: Tagbariri Road | D25: =+F25+G25+I25+H25 -> 1.62 | E25: ='[1]road inventory 2018'!C25 -> 1.6 | F25: 0 | G25: 0 | H25: 0 | I25: 1.62 | J25: 0 | K25: POOR | L25: km sta.69+100 | O25: =D25 -> 1.62 | Q25: BROOKES POINT | R25: =D119+D120+D121+D122+D123+D124+D125+D126+D127+D130+D131+D132+D133+D134+D135+D136+D137+D138+D139+D140+D143+D146+D147+D148+D149+D151+D152 -> 107.48 | T25: =R25 -> 107.48
A26: 17 | B26: 220 | C26: Tagbariri - Magsaysay Road | D26: =SUM(F26:J26) -> 2.11 | E26: ='[1]road inventory 2018'!C26 -> 2.3 | F26: 0 | G26: 0 | H26: 0 | I26: 2.11 | J26: 0 | K26: POOR | L26: km sta.71+150 | O26: =D26 -> 2.11 | Q26: BATARAZA | R26: =D161+D162+D163+D169+D171 -> 10.66 | T26: =R26 -> 10.66
A27: 18 | B27: 14 | C27: Junction - Tigman Road | D27: =SUM(F27:J27) -> 4.12 | E27: ='[1]road inventory 2018'!C27 -> 4 | F27: 4.12 | G27: 0 | H27: 0 | I27: 0 | J27: 0 | K27: FAIR | L27: km sta.75+650 | O27: =D27 -> 4.12 | Q27: BALABAC | R27: =D182+D183 -> 18.49 | T27: =R27 -> 18.49
A28: 19 | B28: 15 | C28: Tigman - Rizal Road | D28: 0 | E28: 0 | F28: 0 | G28: 0 | H28: 0 | I28: 0 | J28: 0 | K28: Poor | L28: km sta.77+400 | M28: NOT EXISTING | O28: =D28 -> 0 | Q28: ROXAS | R28: =D193+D194+D197+D199+D200+D201+D204+D203+D207+D208+D209+D210+D211 -> 108.29 | T28: =R28 -> 108.29
A29: 20 | B29: 16 | C29: Tigman - Caburian Road | D29: =SUM(F29:J29) -> 1.05 | E29: ='[1]road inventory 2018'!C29 -> 1 | F29: 0 | G29: 0 | H29: 0 | I29: 1.05 | J29: 0 | K29: FAIR | L29: km sta.78+150 | O29: =D29 -> 1.05 | Q29: SANVICENTE | R29: =D223+D224+D226+D227+D229+D230 -> 77.27 | T29: =R29 -> 77.27
A30: 21 | B30: 17 | C30: Magbabadil - Baraki Road | D30: =SUM(F30:J30) -> 4.18 | E30: ='[1]road inventory 2018'!C30 -> 4 | F30: 4.18 | G30: 0 | H30: 0 | I30: 0 | J30: 0 | K30: GOOD | L30: km sta.73+400 | O30: =D30 -> 4.18 | Q30: TAYTAY | R30: =D238+D239+D240+D241+D243+D244+D245 -> 88.47 | T30: =R30 -> 88.47
A31: 22 | B31: 18 | C31: Tigman - Rizal - Dumangueña Road | D31: =+F31+G31+I31+H31 -> 10.52 | E31: ='[1]road inventory 2018'!C31 -> 10.5 | F31: =4.2+3.15+0.2+0.88+0.6 -> 9.03 | G31: 0 | H31: 0 | I31: 1.49 | J31: 0 | K31: FAIR | L31: km sta.77+400 | O31: =D31 -> 10.52 | Q31: EL NIDO | R31: =D255+D257 -> 9.09 | T31: =R31 -> 9.09
A32: 23 | B32: 221 | C32: Hi-way Jct. Plaridel-Tigman-Caburian Rd | D32: =+F32+G32+I32+H32 -> 4.53 | E32: ='[1]road inventory 2018'!C32 -> 5.2 | F32: 1.17 | G32: 0 | H32: 0 | I32: 3.36 | J32: 0 | K32: FAIR | L32: km sta.76+500 | O32: =D32 -> 4.53 | Q32: DUMARAN | R32: =D266+D267+D268+D272+D273+D276+D277+D281+D282 -> 65.27 | T32: =R32 -> 65.27
A33: 24 | B33: 20 | C33: Aporawan-Daan-Cabigaan Road | D33: =+F33+G33+I33+H33+J33 -> 7.63 | E33: ='[1]road inventory 2018'!C33 -> 7.6 | F33: 1.9 | G33: 0 | H33: 0 | I33: 1.2 | J33: 4.53 | K33: BAD | O33: =D33 -> 7.63 | Q33: ARACELI | R33: =D292+D297+D298 -> 10.1 | T33: 0
D34: =SUM(D10:D33) -> 95.39 | E34: =SUM(E10:E33) -> 95.35 | F34: =SUM(F10:F33) -> 58.25 | G34: =G32+G31+G30+G29+G27+G26+G24+G23+G22+G21+G20+G19+G17+G16+G13+G11+G10 -> 0 | H34: =H32+H31+H30+H29+H27+H26+H24+H23+H22+H21+H20+H19+H17+H16+H13+H11+H10 -> 0 | I34: =SUM(I10:I33) -> 32.61 | J34: =J32+J31+J30+J29+J27+J26+J24+J23+J22+J21+J20+J19+J17+J16+J13+J11+J10 -> 0 | P34: =SUM(O10:O33) -> 95.39 | Q34: CUYO | R34: =D309+D310+D312+D313+D315 -> 27.062 | T34: =D310+D312+D313+D315 -> 14.362
B35: SUB-TOTAL | D35: =F35+G35+H35+I35+J35 -> 95.39 | F35: =SUM(F10:F33) -> 58.25 | G35: =SUM(G10:G33) -> 0 | H35: =SUM(H10:H33) -> 0 | I35: =SUM(I10:I33) -> 32.61 | J35: =SUM(J10:J33) -> 4.53 | Q35: MAGSAYSAY | R35: =D327+D328+D329+D330+D338+D339 -> 10.64 | T35: =D327+D328+D329+D330+D339 -> 9.84
Q36: AGUTAYA | R36: =D347+D348 -> 7.25 | T36: 0
B39: MUNICIPALITY OF NARRA | Q39: CORON | R39: =D357+D359+D360+D361+D362+D365+D366+D367+D369 -> 79.645 | T39: =D357+D359+D360+D361+D362+D366+D367+D369 -> 77.225
Q40: BUSUANGA | R40: =D379+D380+D382+D383 -> 34.028 | T40: =D379+D380 -> 13.028
B41: ROAD ID | C41: ROAD NAME | D41: LENGTH (km/s.) | F41: SURFACE TYPE | K41: ROAD CONDITION | L41: KILOMETER POST | M41: REMARKS | Q41: CULION | R41: =D392+D393+D394+D398 -> 20.704 | T41: =D392+D393+D394+D398 -> 20.704
F42: CONCRETE | G42: ASPHALT | H42: EARTH | I42: GRAVEL | J42: MIXED | Q42: CAGAYAN CILLO | R42: =D405 -> 8.741 | T42: 0
A43: 1 | B43: 21 | C43: Sandoval Feeder Road | D43: =+F43+G43+I43 -> 4.32 | E43: ='[1]road inventory 2018'!C41 -> 4.3 | F43: 4.32 | G43: 0 | H43: 0 | I43: 0 | J43: 0 | K43: GOOD | L43: km sta.79+500 | O43: =D43 -> 4.32 | Q43: =Q19 -> GOOD TO FAIR (TOTAL LENGTH) | R43: =SUM(R20:R42) -> 894.5 | S43: =D410-R43 -> 352.415 | T43: =SUM(T20:T42) -> 831.489
A44: 2 | B44: 22 | C44: Apo-Aporawan Section Road | D44: =+F44+G44+I44 -> 4.01 | E44: ='[1]road inventory 2018'!C42 -> 3.9 | F44: 0 | G44: 0 | H44: 0 | I44: 4.01 | J44: 0 | K44: POOR | L44: km sta.80+770 | O44: =D44 -> 4.01
A45: 3 | B45: 23 | C45: Malatgao - Babanitan Road | D45: =+F45+G45+I45 -> 4.42 | E45: ='[1]road inventory 2018'!C43 -> 4.3 | F45: 2.9 | G45: 0 | H45: 0 | I45: 1.52 | J45: 0 | K45: FAIR | L45: km sta.83+580 | O45: =D45 -> 4.42
A46: 4 | B46: 24 | C46: Malatgao Section Road | D46: =+F46+G46+I46 -> 8.25 | E46: ='[1]road inventory 2018'!C44 -> 7.5 | F46: 8.25 | G46: 0 | H46: 0 | I46: 0 | J46: 0 | K46: FAIR | L46: km sta.83+580 | O46: =D46 -> 8.25
A47: 5 | B47: 25 | C47: Taritien Sea Road | D47: =+F47+G47+I47 -> 0.88 | E47: ='[1]road inventory 2018'!C45 -> 1.7 | F47: 0 | G47: 0 | H47: 0 | I47: 0.88 | J47: 0 | K47: FAIR | L47: km sta.85+500 | O47: =D47 -> 0.88 | Q47: **NOTE: THE ROAD IS NOT ACCESSIBLE DUE TO POOR CONDITION OF BRIDGE.
A48: 6 | B48: 26 | C48: Taritien Section Road | D48: =+F48+G48+I48+H48 -> 6.06 | E48: ='[1]road inventory 2018'!C46 -> 5.9 | F48: =1+2.81 -> 3.81 | G48: 0 | H48: 0 | I48: 2.25 | J48: 0 | K48: GOOD | L48: km sta.85+500 | O48: =D48 -> 6.06
A49: 7 | B49: 27 | C49: Antipuluan Sea Road | D49: =+F49+G49+I49+H49 -> 1.93 | E49: ='[1]road inventory 2018'!C47 -> 1.9 | F49: 0.28 | G49: 0 | H49: 0 | I49: 1.65 | J49: 0 | K49: FAIR | L49: km sta.88+045 | O49: =D49 -> 1.93
A50: 8 | B50: 28 | C50: Lapu-Lapu Section Road | D50: =+F50+G50+I50+H50 -> 5.62 | E50: ='[1]road inventory 2018'!C48 -> 5.6 | F50: 1.55 | G50: 0 | H50: 0 | I50: 4.07 | J50: 0 | K50: POOR | L50: km sta.91+160 | O50: =D50 -> 5.62
A51: 9 | B51: 29 | C51: Narra School Road | D51: =+F51+G51+I51+H51 -> 0.86 | E51: ='[1]road inventory 2018'!C49 -> 0.8 | F51: 0.86 | G51: 0 | H51: 0 | I51: 0 | J51: 0 | K51: FAIR | L51: km sta.92+250 | O51: =D51 -> 0.86
A52: 10 | B52: 30 | C52: Rizal Avenue Section Road | D52: 0 | E52: ='[1]road inventory 2018'!C50 -> 2 | F52: 0 | G52: 0 | H52: 0 | I52: 0 | J52: 0 | K52: Good | L52: km sta.91+670 | M52: MUNICIPAL ROAD | O52: =D52 -> 0 | Q52: Municipal road
A53: 11 | B53: 106 | C53: Narra Panacan Road | D53: =+F53+G53+I53+H53 -> 3.21 | E53: ='[1]road inventory 2018'!C51 -> 3.2 | F53: 3.21 | G53: 0 | H53: 0 | I53: 0 | J53: 0 | K53: GOOD | L53: km sta.92+370 | O53: =D53 -> 3.21
A54: 12 | B54: 31 | C54: Ipil Road / Quirino | D54: =+F54+G54+I54+H54 -> 0.78 | E54: ='[1]road inventory 2018'!C52 -> 0.8 | F54: 0.78 | G54: 0 | H54: 0 | I54: 0 | J54: 0 | K54: FAIR | L54: km sta.92+700 | O54: =D54 -> 0.78
A55: 13 | B55: 32 | C55: Guminubat Section Road | D55: =+F55+G55+I55+H55 -> 3.01 | E55: ='[1]road inventory 2018'!C53 -> 3 | F55: 0 | G55: 0 | H55: 0 | I55: 3.01 | J55: 0 | K55: BAD | L55: km sta.94+650 | O55: =D55 -> 3.01
A56: 14 | B56: 33 | C56: Malinao Feeder Road | D56: =+F56+G56+I56+H56 -> 2.4 | E56: ='[1]road inventory 2018'!C54 -> 2.4 | F56: 0 | G56: 0 | H56: 0 | I56: 2.4 | J56: 0 | K56: POOR | L56: km sta.96+850 | O56: =D56 -> 2.4
A57: 15 | B57: 34 | C57: Linamen Feeder Road | D57: =+F57+G57+I57+H57 -> 4.31 | E57: ='[1]road inventory 2018'!C55 -> 4.2 | F57: 0 | G57: 0 | H57: 0 | I57: 4.31 | J57: 0 | K57: BAD | L57: km sta.100+150 | O57: =D57 -> 4.31
A58: 16 | B58: 35 | C58: Caguisan Feeder Road | D58: =+F58+G58+I58+H58 -> 2.97 | E58: ='[1]road inventory 2018'!C56 -> 3 | F58: =0.4+0.31+0.1 -> 0.81 | G58: 0 | H58: 0 | I58: =1.94+0.22 -> 2.16 | J58: 0 | K58: FAIR | L58: km sta.99+200 | O58: =D58 -> 2.97
A59: 17 | B59: 36 | C59: Batang-Batang Feeder Road | D59: =+F59+G59+I59+H59 -> 6.01 | E59: ='[1]road inventory 2018'!C57 -> 6.2 | F59: 0 | G59: 0 | H59: 0 | I59: 6.01 | J59: 0 | K59: FAIR | L59: km sta.101+950 | O59: =D59 -> 6.01
A60: 18 | B60: 37 | C60: Linamen - Batang-Batang Feeder Road | D60: =+F60+G60+I60+H60 -> 1.6 | E60: ='[1]road inventory 2018'!C58 -> 1.6 | F60: 0 | G60: 0 | H60: 0 | I60: 1.6 | J60: 0 | K60: BAD | L60: km sta.101+960 | O60: =D60 -> 1.6
A61: 19 | B61: 38 | C61: Teresa - Batang-Batang Road | D61: =+F61+G61+I61+H61 -> 3.9 | E61: ='[1]road inventory 2018'!C59 -> 4.4 | F61: 1.58 | G61: 0 | H61: 0 | I61: 2.32 | J61: 0 | K61: FAIR | L61: km sta.105+550 | O61: =D61 -> 3.9
A62: 20 | B62: 39 | C62: Teresa Feeder Road | D62: =+F62+G62+I62+H62 -> 4.94 | E62: ='[1]road inventory 2018'!C60 -> 4.9 | F62: 0.14 | G62: 0 | H62: 0 | I62: 4.8 | J62: 0 | K62: FAIR | L62: km sta.104+100 | O62: =D62 -> 4.94
A63: 21 | B63: 105 | C63: Bato-Bato Feeder Road | D63: =+F63+G63+I63+H63 -> 3.65 | E63: ='[1]road inventory 2018'!C61 -> 3.6 | F63: 0 | G63: 0 | H63: 0 | I63: 3.65 | J63: 0 | K63: FAIR | L63: km sta.105+950 | O63: =D63 -> 3.65
A64: 22 | B64: 40 | C64: Calategas Sea Road | D64: =+F64+G64+I64+H64 -> 1.55 | E64: ='[1]road inventory 2018'!C62 -> 1.5 | F64: 1.1 | G64: 0 | H64: 0 | I64: 0.45 | J64: 0 | K64: GOOD | L64: km sta.115+010 | O64: =D64 -> 1.55
A65: 23 | B65: 41 | C65: Calategas Dampsite Road | D65: =+F65+G65+I65+H65 -> 2.81 | E65: ='[1]road inventory 2018'!C63 -> 2.8 | F65: 0 | G65: 0 | H65: 0 | I65: 2.81 | J65: 0 | K65: FAIR | L65: km sta.116+100 | O65: =D65 -> 2.81
A66: 24 | B66: 42 | C66: Aramaywan Sea Road | D66: =+F66+G66+I66+H66 -> 1.5 | E66: ='[1]road inventory 2018'!C64 -> 1.5 | F66: 0.17 | G66: 0 | H66: 0 | I66: 1.33 | J66: 0 | K66: POOR | L66: km sta.120+300 | O66: =D66 -> 1.5
A67: 25 | B67: 43 | C67: Aramaywan Parangue Road | D67: =+F67+G67+I67+H67 -> 8.53 | E67: ='[1]road inventory 2018'!C65 -> 12.7 | F67: 0.16 | G67: 0 | H67: 0 | I67: 8.37 | J67: 0 | K67: BAD | L67: km sta.120+750 | O67: =D67 -> 8.53 | Q67: **NOTE: THE ROAD IS NOT ACCESSIBLE DUE TO POOR CONDITION OF CULVERT. | T67: =E67-D67 -> 4.17
A68: 26 | B68: 44 | C68: Burirao - Cabudlungan Road | D68: =+F68+G68+I68+H68 -> 5.52 | E68: ='[1]road inventory 2018'!C66 -> 5.3 | F68: 1.48 | G68: 0 | H68: 0 | I68: 4.04 | J68: 0 | K68: POOR | L68: km sta.124+800 | O68: =D68 -> 5.52
A69: 27 | B69: 104 | C69: Sandoval - Bagong Sikat Road | D69: =+F69+G69+I69+H69 -> 3.13 | E69: ='[1]road inventory 2018'!C67 -> 3.1 | F69: 0 | G69: 0 | H69: 0 | I69: 3.13 | J69: 0 | K69: FAIR | L69: km sta.81+500 | O69: =D69 -> 3.13
D70: =SUM(D43:D69) -> 96.17 | E70: =SUM(E43:E69) -> 102.1
B71: SUB-TOTAL | D71: =SUM(F71:J71) -> 96.17 | F71: =SUM(F43:F70) -> 31.4 | G71: =SUM(G43:G69) -> 0 | H71: =SUM(H43:H69) -> 0 | I71: =SUM(I43:I69) -> 64.77 | J71: =SUM(J43:J69) -> 0 | P71: =SUM(O43:O69) -> 96.17
B76: MUNICIPALITY OF QUEZON
B78: ROAD ID | C78: ROAD NAME | D78: LENGTH (km/s.) | F78: SURFACE TYPE | K78: ROAD CONDITION | L78: KILOMETER POST | M78: REMARKS
F79: CONCRETE | G79: ASPHALT | H79: EARTH | I79: GRAVEL | J79: MIXED
A80: 1 | B80: 107 | C80: Tabon - Pinaglabanan Road | D80: =+F80+G80+I80 -> 2.59 | E80: ='[1]road inventory 2018'!C73 -> 2.5 | F80: =1.01+1.03 -> 2.04 | G80: 0 | H80: 0 | I80: 0.55 | J80: 0 | K80: POOR | L80: km sta.139+300 | O80: =D80 -> 2.59
A81: 2 | B81: 102 | C81: Tabon - Tagpapasi Road | D81: =+F81+G81+I81 -> 1.33 | E81: ='[1]road inventory 2018'!C74 -> 1.3 | F81: 0.27 | G81: 0 | H81: 0 | I81: =0.043+1.02-0.003 -> 1.06 | J81: 0 | K81: POOR | L81: km sta.143+700 | O81: =D81 -> 1.33
A82: 3 | B82: 101 | C82: Magsaysay Road | D82: 0 | E82: ='[1]road inventory 2018'!C75 -> 0.6 | F82: 0 | G82: 0 | H82: 0 | I82: 0 | J82: 0 | K82: Good | L82: km sta.146+000 | M82: MUNICIPAL ROAD | O82: =D82 -> 0 | Q82: Municipal Road
A83: 4 | B83: 47 | C83: Abo-Abo - Isugod Road | D83: =+F83+G83+I83 -> 17.2 | E83: ='[1]road inventory 2018'!C76 -> 17 | F83: =1.03+0.2+0.08 -> 1.31 | G83: 0 | H83: 0 | I83: =1+1.06+0.99+1+1.07+1.11+1.03+0.97+1.05+1.01+0.28+1.14+1.13+1.01+0.98+0.97+0.09 -> 15.89 | J83: 0 | K83: BAD | L83: km sta.156+500 | O83: =D83 -> 17.2
A84: 5 | B84: 48 | C84: Maasin - Marintub Road | D84: =+F84+G84+I84 -> 2.63 | E84: ='[1]road inventory 2018'!C77 -> 2.6 | F84: 0 | G84: 0 | H84: 0 | I84: =0.5+1.05+1.08 -> 2.63 | J84: 0 | K84: POOR | L84: km sta.157+800 | O84: =D84 -> 2.63
A85: 6 | B85: 90 | C85: Malatgao Road | D85: =+F85+G85+I85 -> 4.27 | E85: ='[1]road inventory 2018'!C78 -> 4.35 | F85: 0 | G85: 0 | H85: 0 | I85: =1.02+1.04+1.1+0.95+0.16 -> 4.27 | J85: 0 | K85: POOR | L85: km sta.134+500 | O85: =D85 -> 4.27
A86: 7 | B86: 99 | C86: Panitian - Tabud Road | D86: =+F86+G86+I86 -> 14.14 | E86: ='[1]road inventory 2018'!C79 -> 14.1 | F86: =1.1+1 -> 2.1 | G86: 0 | H86: 0 | I86: =1.08+1.01+1.08+1+1.01+1.1+1.07+0.94+1.02+1.05+1.04+0.64 -> 12.04 | J86: 0 | K86: POOR | L86: km sta.151+000 | O86: =D86 -> 14.14
D87: =SUM(D80:D86) -> 42.16 | E87: =SUM(E80:E86) -> 42.45 | P87: =SUM(O80:O86) -> 42.16
B88: SUB-TOTAL | D88: =SUM(F88:J88) -> 42.16 | F88: =SUM(F80:F86) -> 5.72 | G88: =SUM(G80:G86) -> 0 | H88: =SUM(H80:H86) -> 0 | I88: =SUM(I80:I86) -> 36.44 | J88: =SUM(J80:J86) -> 0
B90: MUNICIPALITY OF RIZAL
B92: ROAD ID | C92: ROAD NAME | D92: LENGTH (km/s.) | F92: SURFACE TYPE | K92: ROAD CONDITION | L92: KILOMETER POST | M92: REMARKS
F93: CONCRETE | G93: ASPHALT | H93: EARTH | I93: GRAVEL | J93: MIXED
A94: 1 | B94: 108 | C94: Rancho - Puntabaja - Malapandeg Road | D94: =F94+G94+H94+I94+J94 -> 3.28 | E94: ='[1]road inventory 2018'!C86 -> 3.1 | F94: 0.48 | G94: 0 | H94: 0 | I94: =0.67+0.12+1.27+0.75-0.01 -> 2.8 | J94: 0 | K94: POOR | L94: km sta.198+000 | O94: =D94 -> 3.28
B95: SUB-TOTAL | D95: =SUM(D94:D94) -> 3.28 | F95: =SUM(F94:F94) -> 0.48 | G95: =SUM(G94:G94) -> 0 | H95: =SUM(H94:H94) -> 0 | I95: =SUM(I94:I94) -> 2.8 | J95: =SUM(J94:J94) -> 0 | P95: =O94 -> 3.28
B97: MUNICIPALITY OF SOFRONIO ESPAÑOLA
B99: ROAD ID | C99: ROAD NAME | D99: LENGTH (km/s.) | F99: SURFACE TYPE | K99: ROAD CONDITION | L99: KILOMETER POST | M99: REMARKS
F100: CONCRETE | G100: ASPHALT | H100: EARTH | I100: GRAVEL | J100: MIXED
A101: 1 | B101: 223 | C101: Panitian Seashore Road | D101: =+F101+G101+I101 -> 4.18 | E101: ='[1]road inventory 2018'!C93 -> 4.1 | F101: 0 | G101: 0 | H101: 0 | I101: 4.18 | J101: 0 | K101: POOR | L101: km sta.137+000 | O101: =D101 -> 4.18
A102: 2 | B102: 224 | C102: Panitian - Abokayan Road | D102: =+F102+G102+I102 -> 7.19 | E102: ='[1]road inventory 2018'!C94 -> 7.2 | F102: =2.25+0.06+0.9 -> 3.21 | G102: 0 | H102: 0 | I102: =3.19+0.79 -> 3.98 | J102: 0 | K102: POOR | L102: km sta.137+900 | O102: =D102 -> 7.19
A103: 3 | B103: 45 | C103: Labog Naltep Road | D103: =+F103+G103+I103 -> 7.44 | E103: ='[1]road inventory 2018'!C95 -> 7.9 | F103: 0.71 | G103: 0 | H103: 0 | I103: 6.73 | J103: 0 | K103: POOR | L103: km sta.143+800 | O103: =D103 -> 7.44
A104: 4 | B104: 217 | C104: Punang Plain Road | D104: =+F104+G104+I104 -> 1.14 | E104: ='[1]road inventory 2018'!C96 -> 1.1 | F104: 1.14 | G104: 0 | H104: 0 | I104: 0 | J104: 0 | K104: GOOD | L104: km sta.149+200 | O104: =D104 -> 1.14
A105: 5 | B105: 225 | C105: Iraray School Road | D105: =+F105+G105+I105 -> 0.36 | E105: ='[1]road inventory 2018'!C97 -> 0.4 | F105: 0 | G105: 0 | H105: 0 | I105: 0.36 | J105: 0 | K105: POOR | L105: km sta.155+700 | O105: =D105 -> 0.36
A106: 6 | B106: 226 | C106: Pulot Sea Road | D106: =+F106+G106+I106 -> 4.01 | E106: ='[1]road inventory 2018'!C98 -> 4.8 | F106: 0.86 | G106: 0 | H106: 0 | I106: 3.15 | J106: 0 | K106: GOOD | L106: km sta.162+800 | O106: =D106 -> 4.01
A107: 7 | B107: 116 | C107: Pulot I - Pulot III Road | D107: =+F107+G107+I107 -> 12.3 | E107: ='[1]road inventory 2018'!C99 -> 12.3 | F107: 6.67 | G107: 0 | H107: 0 | I107: 5.63 | J107: 0 | K107: FAIR | L107: km sta.162+800 | O107: =D107 -> 12.3
A108: 8 | B108: 46 | C108: Pulot Bo. High School Road | D108: =+F108+G108+I108 -> 1.3 | E108: ='[1]road inventory 2018'!C100 -> 1.3 | F108: 1.3 | G108: 0 | H108: 0 | I108: 0 | J108: 0 | K108: GOOD | L108: km sta.163+800 | O108: =D108 -> 1.3
A109: 9 | B109: 227 | C109: Caramay Bulho Road | D109: =+F109+G109+I109 -> 7.43 | E109: ='[1]road inventory 2018'!C101 -> 7.2 | F109: 0 | G109: 0 | H109: 0 | I109: 7.43 | J109: 0 | K109: POOR | L109: km sta.165+600 | O109: =D109 -> 7.43
A110: 10 | B110: 100 | C110: Pulot III-Tabud Road | D110: =+F110+G110+I110 -> 7.8 | E110: ='[1]road inventory 2018'!C102 -> 7.8 | F110: 0.3 | G110: 0 | H110: 0 | I110: 7.5 | J110: 0 | K110: BAD | L110: km sta.177+000 | O110: =D110 -> 7.8
D111: =SUM(D101:D110) -> 53.15 | E111: =SUM(E101:E110) -> 54.1
B112: SUB-TOTAL | D112: =F112+I112 -> 53.15 | F112: =SUM(F101:F110) -> 14.19 | G112: =SUM(G101:G110) -> 0 | H112: =SUM(H101:H110) -> 0 | I112: =SUM(I101:I110) -> 38.96 | J112: =SUM(J101:J110) -> 0 | P112: =SUM(O101:O110) -> 53.15
B115: MUNICIPALITY OF BROOKE'S POINT
...

Sheet GRAPH
J1: GOOD | L1: C | M1: A | N1: E | O1: G | P1: M
C2: R O A D I N V E N T O R Y
C4: CONCRETE | D4: ASPHALT | E4: EARTH | F4: GRAVEL | I4: 1 | J4: Sagpangan Road | K4: 5.48 | L4: 4.88 | M4: 0 | N4: 0 | O4: 0.6 | P4: 0 | Q4: GOOD | R4: km sta.66+400 | W4: CONCRETE | X4: ASPHALT | Y4: EARTH | Z4: GRAVEL | AA4: MIXED | AC4: GOOD TO FAIR | AD4: : | AE4: =(C5+E5+D5+F5+G5)+(C6+D6+E6+F6+G6) -> 927.6132
B5: GOOD | C5: ='SUMMARY 2021'!K45 -> 221.1882 | D5: ='SUMMARY 2021'!L45 -> 2.083 | E5: ='SUMMARY 2021'!M45 -> 3.42 | F5: ='SUMMARY 2021'!N45 -> 76.466 | H5: =SUM(C5:G5) -> 303.1572 | I5: 6 | J5: San Juan Road | K5: 3.96 | L5: 3.5 | M5: 0 | N5: 0 | O5: 0.46 | P5: 0 | Q5: GOOD | R5: km sta.66+400 | W5: =C5*15000000 -> 3.317823e+09 | X5: =D5*100000 -> 208300 | Y5: =E5*100000 -> 342000 | Z5: =F5*100000 -> 7646600 | AA5: =G5*100000 -> 0 | AC5: POOR TO BAD | AD5: : | AE5: =(C7+D7+E7+F7+G7)+(C8+D8+E8+F8+G8) -> 301.938
B6: FAIR | C6: ='SUMMARY 2021'!K46 -> 171.764 | D6: ='SUMMARY 2021'!L46 -> 0 | E6: ='SUMMARY 2021'!M46 -> 1.72 | F6: ='SUMMARY 2021'!N46 -> 450.972 | H6: =SUM(C6:G6) -> 624.456 | I6: 9 | J6: Magbabadil - Cabigaan Road | K6: 9.3 | L6: 9.3 | M6: 0 | N6: 0 | O6: 0 | P6: 0 | Q6: GOOD | R6: km sta.66+800 | W6: =C6*15000000 -> 2.57646e+09 | X6: =D6*100000 -> 0 | Y6: =E6*100000 -> 172000 | Z6: =F6*100000 -> 45097200 | AA6: =G6*100000 -> 0 | AC6: TOTAL LENGTH | AD6: : | AE6: =AE4+AE5 -> 1229.5512
B7: POOR | C7: ='SUMMARY 2021'!K47 -> 33.224 | D7: ='SUMMARY 2021'!L47 -> 2.55 | E7: ='SUMMARY 2021'!M47 -> 0 | F7: ='SUMMARY 2021'!N47 -> 149.181 | H7: =SUM(C7:G7) -> 184.955 | I7: 10 | J7: Plaridel - Apis Cabigaan Road | K7: 13.79 | L7: 10.12 | M7: 0 | N7: 0 | O7: 3.67 | P7: 0 | Q7: GOOD | R7: km sta.75+650 | W7: =C7*15000000 -> 4.9836e+08 | X7: =D7*100000 -> 255000 | Y7: =E7*100000 -> 0 | Z7: =F7*100000 -> 14918100 | AA7: =G7*100000 -> 0
B8: BAD | C8: ='SUMMARY 2021'!K48 -> 14.332 | D8: ='SUMMARY 2021'!L48 -> 6.11 | E8: ='SUMMARY 2021'!M48 -> 5.544 | F8: ='SUMMARY 2021'!N48 -> 90.997 | H8: =SUM(C8:G8) -> 116.983 | I8: 17 | J8: Magbabadil - Baraki Road | K8: 4.18 | L8: 4.18 | M8: 0 | N8: 0 | O8: 0 | P8: 0 | Q8: GOOD | R8: km sta.73+400 | W8: =C8*15000000 -> 214980000 | X8: =D8*100000 -> 611000 | Y8: =E8*100000 -> 554400 | Z8: =F8*100000 -> 9099700 | AA8: =G8*100000 -> 0
C9: =SUM(C5:C8) -> 440.5082 | D9: =SUM(D5:D8) -> 10.743 | E9: =SUM(E5:E8) -> 10.684 | F9: =SUM(F5:F8) -> 767.616 | G9: =SUM(C9:F9) -> 1229.5512 | H9: =SUM(H5:H8) -> 1229.5512 | I9: 21 | J9: Sandoval Feeder Road | K9: 4.32 | L9: 4.32 | M9: 0 | N9: 0 | O9: 0 | P9: 0 | Q9: GOOD | R9: km sta.79+500 | W9: =SUM(W5:W8) -> 6607623000 | X9: =SUM(X5:X8) -> 1074300 | Y9: =SUM(Y5:Y8) -> 1068400 | Z9: =SUM(Z5:Z8) -> 76761600 | AA9: =SUM(AA5:AA8) -> 0 | AB9: =SUM(W9:AA9) -> 6686527300
H10: =SUM(C9:G9) -> 2459.1024 | I10: 26 | J10: Taritien Section Road | K10: 6.06 | L10: 3.81 | M10: 0 | N10: 0 | O10: 2.25 | P10: 0 | Q10: GOOD | R10: km sta.85+500
I11: 30 | J11: Rizal Avenue Section Road | K11: 0 | L11: 0 | M11: 0 | N11: 0 | O11: 0 | P11: 0 | Q11: Good | R11: km sta.91+670 | S11: MUNICIPAL ROAD
I12: 106 | J12: Narra Panacan Road | K12: 3.21 | L12: 3.21 | M12: 0 | N12: 0 | O12: 0 | P12: 0 | Q12: GOOD | R12: km sta.92+370
I13: 40 | J13: Calategas Sea Road | K13: 1.55 | L13: 1.1 | M13: 0 | N13: 0 | O13: 0.45 | P13: 0 | Q13: GOOD | R13: km sta.115+010
I14: 101 | J14: Magsaysay Road | K14: 0 | L14: 0 | M14: 0 | N14: 0 | O14: 0 | P14: 0 | Q14: Good | R14: km sta.146+000 | S14: MUNICIPAL ROAD
I15: 217 | J15: Punang Plain Road | K15: 1.14 | L15: 1.14 | M15: 0 | N15: 0 | O15: 0 | P15: 0 | Q15: GOOD | R15: km sta.149+200
I16: 226 | J16: Pulot Sea Road | K16: 4.01 | L16: 0.86 | M16: 0 | N16: 0 | O16: 3.15 | P16: 0 | Q16: GOOD | R16: km sta.162+800 | V16: =(C9/$AE$6)*100 -> 35.826747 | AC16: %
I17: 46 | J17: Pulot Bo. High School Road | K17: 1.3 | L17: 1.3 | M17: 0 | N17: 0 | O17: 0 | P17: 0 | Q17: GOOD | R17: km sta.163+800 | V17: =(D9/$AE$6)*100 -> 0.87373344 | AC17: %
I18: 54 | J18: Ipilan Sea Road | K18: 1.69 | L18: 1.18 | M18: 0 | N18: 0 | O18: 0.51 | P18: 0 | Q18: GOOD | R18: km sta.180+700 | V18: =(E9/$AE$6)*100 -> 0.86893494 | AC18: %
I19: 60 | J19: Junction Mainit Road | K19: 9.2 | L19: 7.1 | M19: 0 | N19: 0 | O19: 2.1 | P19: 0 | Q19: GOOD | R19: km sta.189+95 | V19: =(F9/$AE$6)*100 -> 62.430584 | AC19: %
I20: 98 | J20: Calasaguen Feeder Road | K20: 4.98 | L20: 4.98 | M20: 0 | N20: 0 | O20: 0 | P20: 0 | Q20: GOOD | R20: km sta.168+75 | V20: =SUM(V16:V19) -> 100 | AC20: %
I21: 64 | J21: Calasaguen Abubakar Road | K21: 3.64 | L21: 3.64 | M21: 0 | N21: 0 | O21: 0 | P21: 0 | Q21: GOOD | R21: km sta.170+750 | AC21: %
I22: 77 | J22: Bataraza Poblacion Road | K22: 0.76 | L22: 0 | M22: 0 | N22: 0 | O22: 0.76 | P22: 0 | Q22: GOOD | R22: km sta.216+720
I23: 94 | J23: Marangas Sea Road | K23: 0.6 | L23: 0 | M23: 0 | N23: 0 | O23: 0.6 | P23: 0 | Q23: GOOD | R23: km sta.217+260
I24: 91 | J24: Balabac-Catagupan Road | K24: 12.89 | L24: 12.21 | M24: 0 | N24: 0 | O24: 0.68 | P24: 0 | Q24: GOOD | R24: km sta.000-sta.12+900 | AF24: STEEL TRUSS
I25: 89 | J25: Highway Junction Tinitian Road | K25: 0.63 | L25: 0.3 | M25: 0 | N25: 0 | O25: 0.33 | P25: 0 | Q25: GOOD | R25: km sta.92+700 | AF25: PNAC Road | AG25: 67+450 | AH25: 45 | AI25: Steel Truss | AJ25: Good
I26: 109 | J26: Highway Junction Caramay Road | K26: 2.5 | L26: 0.257 | M26: 0 | N26: 0 | O26: 2.243 | P26: 0 | Q26: GOOD | R26: km sta.107+900 | AF26: Tigman - Caburian Road | AG26: 78+830 | AH26: 26 | AI26: Steel Truss | AJ26: Good
I27: 115 | J27: San Jose Port Barton Road - A | K27: 10.71 | L27: 10.71 | M27: 0 | N27: 0 | O27: 0 | P27: 0 | Q27: GOOD | R27: km sta.124+600 | AF27: Tigman - Rizal - Dumangueña Road | AH27: 44 | AI27: Steel Truss | AJ27: Good
I28: 132 | J28: Highway Junction Tumarbong Road | K28: 13.5 | L28: 8.82 | M28: 0 | N28: 0 | O28: 4.68 | P28: 0 | Q28: GOOD | R28: km sta.150+400 | AF28: Balabac-Catagupan Road | AG28: 11+911 | AH28: 25 | AI28: Steel Truss | AJ28: Good
C29: B R I D G E I N V E N T O R Y | I29: 136 | J29: Canadcan - Alimanguan Road | K29: 11.31 | L29: 8.7 | M29: 0 | N29: 0 | O29: 2.61 | P29: 0 | Q29: GOOD | R29: km sta.171+800
I30: 137 | J30: Alimanguan - Kemdeng Road | K30: 12.59 | L30: 8.74 | M30: 0 | N30: 0 | O30: 3.85 | P30: 0 | Q30: GOOD | R30: km sta.183+100
D31: STEEL TRUSS | E31: BAILEY | F31: RC. GIRDER | G31: TIMBER | I31: 120 | J31: San Jose - Port Barton Road -B | K31: 10.85 | L31: 10.24 | M31: 0 | N31: 0 | O31: 0.61 | P31: 0 | Q31: GOOD | R31: km sta.135+400 | AF31: Malinao Feeder Road | AG31: Presidential Bridge | AH31: 29 | AI31: Steel Truss | AJ31: Fair
C32: GOOD | D32: =AH26+AH27+AH28+AH25 -> 140 | E32: =AH36+AH37 -> 78 | F32: =SUM(AH56:AH104) -> 919.88 | G32: 0 | I32: 126 | J32: Paglaum - Itangil Road | K32: 9.95 | L32: 9.95 | M32: 0 | N32: 0 | O32: 0 | P32: 0 | Q32: GOOD | R32: km sta.194+900
C33: FAIR | D33: =AH31 -> 29 | E33: =AH39+AH40+AH41 -> 69 | F33: =SUM(AH106:AH128) -> 507.6 | G33: =SUM(AH137:AH144) -> 143 | I33: 147 | J33: Taytay - Sta. Cruz Road | K33: 4.59 | L33: 0.2 | M33: 0 | N33: 0 | O33: 4.39 | P33: 0 | Q33: GOOD
C34: POOR | D34: =L243 -> 0 | E34: =SUM(AH43:AH49) -> 195.1 | F34: =SUM(AH131:AH133) -> 113.4 | G34: =SUM(AH147:AH155) -> 114.5 | I34: 150 | J34: New Ibajay - Lamoro Road | K34: 11.27 | L34: 5.87 | M34: 0 | N34: 0 | O34: 5.4 | P34: 0 | Q34: GOOD | R34: km sta.356+000-sta.368+300 | AF34: BAILEY
C35: BAD | D35: =L268 -> 0 | E35: =AH52+1 -> 17 | F35: =N268 -> 0 | G35: =AH157 -> 5 | I35: 127 | J35: Junction Bantal - San Jose Road | K35: 2.7 | L35: 1.29 | M35: 0 | N35: 0.9 | O35: 0.51 | P35: 0 | Q35: GOOD | R35: km sta.229+320 | V35: =SUM(D36:G36) -> 2331.48
D36: =SUM(D32:D35) -> 169 | E36: =SUM(E32:E35) -> 359.1 | F36: =SUM(F32:F35) -> 1540.88 | G36: =SUM(G32:G35) -> 262.5 | I36: 128 | J36: Junction Salogon - Danleg Road | K36: 2.3 | L36: 2.3 | M36: 0 | N36: 0 | O36: 0 | P36: 0 | Q36: GOOD | R36: km sta.230+070 | AC36: ln.m | AG36: 364+850 | AH36: 33 | AI36: Bailey | AJ36: Good
I37: 197 | J37: Jct. Cuyo- Suba-Baayad Road | K37: 4.927 | L37: 3.094 | M37: 1.833 | N37: 0 | O37: 0 | P37: 0 | Q37: GOOD | R37: km sta.26+530 | AF37: Bucana - Duli Road | AH37: 45 | AI37: Bailey | AJ37: Good
I38: 200 | J38: Cuyo Catadman Road | K38: 1.1 | L38: 1.1 | M38: 0 | N38: 0 | O38: 0 | P38: 0 | Q38: GOOD | R38: km sta.0+320
I39: 201 | J39: Lungsod Balaguen Road A | K39: 2.7 | L39: 2.7 | M39: 0 | N39: 0 | O39: 0 | P39: 0 | Q39: GOOD | R39: km sta.1+000 | AG39: Guadalupe Bridge 2 | AH39: 18 | AI39: Bailey | AJ39: Fair
I40: 202 | J40: Lungsod - Igabas - Emilod Road-A | K40: 1.37 | L40: 1.37 | M40: 0 | N40: 0 | O40: 0 | P40: 0 | Q40: GOOD | R40: km sta.1+000 | AF40: Balala - Malaking Patag Road | AG40: Malaking Patag Bridge | AH40: 30 | AI40: Bailey | AJ40: Fair
I41: 203 | J41: Maringian - Danawan Road | K41: 5.635 | L41: 2.535 | M41: 1.45 | N41: 0 | O41: 1.65 | P41: 0 | Q41: GOOD | R41: km sta.3+500 | AF41: Cabulihan Malaking Patag Road | AG41: Malaking Patag Bridge | AH41: 21 | AI41: Bailey | AJ41: Fair
I42: 228 | J42: Cuyo-Suba-San Carlos Road | K42: 9.3 | L42: 7.22 | M42: 0 | N42: 0 | O42: 2.08 | P42: 0 | Q42: GOOD | V42: =(D36/V$35)*100 -> 7.2486146
I43: 205 | J43: Cuyo Airport Road | K43: 0.37 | L43: 0.37 | M43: 0 | N43: 0 | O43: 0 | P43: 0 | Q43: GOOD | R43: km sta.8+300 | V43: =(E36/V$35)*100 -> 15.402234 | AF43: Taritien Sea Road | AG43: 86+400 | AH43: 60 | AI43: Bailey | AJ43: Poor
I44: 208 | J44: Lungsod - Balaguen Road B | K44: 2.26 | L44: 2.01 | M44: 0.25 | N44: 0 | O44: 0 | P44: 0 | Q44: GOOD | R44: km sta.2+700 | V44: =(F36/V$35)*100 -> 66.090209 | AG44: 119+025 | AH44: 15.7 | AI44: Bailey | AJ44: Poor
I45: 173 | J45: Coron Poblacion Road | K45: 1.5 | L45: 1.5 | M45: 0 | N45: 0 | O45: 0 | P45: 0 | Q45: GOOD | V45: =(G36/V$35)*100 -> 11.258943 | AH45: 24.6 | AI45: Bailey | AJ45: Poor
I46: 177 | J46: YKR Busuanga Airport Road | K46: 13.55 | L46: 13.55 | M46: 0 | N46: 0 | O46: 0 | P46: 0 | Q46: GOOD | V46: =SUM(V42:V46) -> 0 | AG46: Caruray BB II (Pag-asaz) | AH46: 24.8 | AI46: Bailey | AJ46: Poor
I47: 172 | J47: Bintuan Feeder Road | K47: 5.266 | L47: 1.02 | M47: 0 | N47: 0 | O47: 0.826 | P47: 3.42 | Q47: GOOD | AH47: 16 | AI47: Bailey | AJ47: Poor
I48: 181 | J48: Jct. Mabentangan - Balisungan Road | K48: 4.03 | L48: 4.03 | M48: 0 | N48: 0 | O48: 0 | P48: 0 | Q48: GOOD | AG48: 240+200 | AH48: 36 | AI48: Bailey | AJ48: Poor
I49: 182 | J49: YKR Airport-Decalachao-San Jose Rd. | K49: 16.57 | L49: 16.57 | M49: 0 | N49: 0 | O49: 0 | P49: 0 | Q49: GOOD | AF49: Cataban - Pularequin Road | AH49: 18 | AI49: Bailey | AJ49: Poor
I50: 184 | J50: San Nicolas - Decabobo Road | K50: 12.03 | L50: 10.01 | M50: 0 | N50: 0 | O50: 2.02 | P50: 0 | Q50: GOOD
I51: 185 | J51: New Busuanga-New Quezon rd | K51: 12.03 | L51: 10.01 | M51: 0 | N51: 0 | O51: 2.02 | P51: 0 | Q51: GOOD
I52: 192 | J52: Balala-Malaking Patag Road | K52: 9.456 | L52: 8.886 | M52: 0 | N52: 0.06 | O52: 0.05 | P52: 0.46 | Q52: GOOD | AG52: Maasin Bridge II | AH52: 16 | AI52: Bailey | AJ52: Bad
L53: =SUM(L4:L52) -> 230.182 | M53: =SUM(M4:M52) -> 3.533 | N53: =SUM(N4:N52) -> 0.96 | O53: =SUM(O4:O52) -> 48.499 | P53: =SUM(P4:P52) -> 3.88
AF54: RC GIRDER
J55: FAIR | L55: C | M55: A | N55: E | O55: G | P55: M
I56: 219 | J56: Junction - Isaub Road | K56: 0.4 | L56: 0.25 | M56: 0 | N56: 0 | O56: 0.15 | P56: 0 | Q56: FAIR | R56: km sta.57+800 | AF56: Panitian Seashore Road | AG56: Panitian Bridge | AH56: 22.3 | AI56: R.C Girder | AJ56: Good
I57: 2 | J57: Isaub - Marikit -Tubig Road | K57: 0.92 | L57: 0.07 | M57: 0 | N57: 0 | O57: 0.85 | P57: 0 | Q57: FAIR | R57: km sta.58+000 | AF57: Panitian - Abokayan Road | AH57: 26.5 | AI57: R.C Girder | AJ57: Good
I58: 3 | J58: Mailigan - Sagpangan Road | K58: 4.97 | L58: 0 | M58: 0 | N58: 0 | O58: 4.97 | P58: 0 | Q58: FAIR | R58: km sta.62+400 | AF58: Pulot Sea Road | AG58: 166+300 | AH58: 45.6 | AI58: R.C Girder | AJ58: Good
I59: 4 | J59: Iraan - Tubig Road | K59: 2.67 | L59: 0 | M59: 0 | N59: 0 | O59: 2.67 | P59: 0 | Q59: FAIR | R59: km sta.64+900 | AF59: Pulot I - Pulot III Road | AG59: 173+300 | AH59: 24.5 | AI59: R.C Girder | AJ59: Good
I60: 93 | J60: Iraan - Baraki Road | K60: 3.9 | L60: 3.79 | M60: 0 | N60: 0 | O60: 0.11 | P60: 0 | Q60: FAIR | R60: km sta.64+900 | AG60: 173+200 | AH60: 15 | AI60: R.C Girder | AJ60: Good
I61: 218 | J61: Isaub - Sagpangan Road | K61: 5.61 | L61: 0 | M61: 0 | N61: 0 | O61: 5.61 | P61: 0 | Q61: FAIR | R61: km sta.58+000 | AF61: Pulot III-Tabud Road | AH61: 24.5 | AI61: R.C Girder | AJ61: Good
I62: 5 | J62: PNAC Road | K62: 2.85 | L62: 2.85 | M62: 0 | N62: 0 | O62: 0 | P62: 0 | Q62: FAIR | R62: km sta.64+900 | AH62: 15 | AI62: R.C Girder | AJ62: Good
I63: 7 | J63: Aborlan - River Landing | K63: 1.15 | L63: 1.15 | M63: 0 | N63: 0 | O63: 0 | P63: 0 | Q63: FAIR | R63: km sta.67+100 | AF63: Saraza - Tagbalogo | AG63: 203+400 | AH63: 29 | AI63: R.C Girder | AJ63: Good
I64: 8 | J64: Aborlan Poblacion Road | K64: 0.64 | L64: 0.64 | M64: 0 | N64: 0 | O64: 0 | P64: 0 | Q64: FAIR | R64: km sta.66+950 | AF64: Sandoval Barak - Barakan Road | AG64: 215+360 | AH64: 28.8 | AI64: R.C Girder | AJ64: Good
I65: 11 | J65: Tagpait Feeder Road | K65: 2.27 | L65: 1.3 | M65: 0 | N65: 0 | O65: 0.97 | P65: 0 | Q65: FAIR | R65: km sta.69+000 | AF65: H-way Jct. Little Caramay-Caruray Rd.-B | AG65: 118+100 | AH65: 15 | AI65: R.C Girder | AJ65: Good
I66: 14 | J66: Junction - Tigman Road | K66: 4.12 | L66: 4.12 | M66: 0 | N66: 0 | O66: 0 | P66: 0 | Q66: FAIR | R66: km sta.75+650 | AG66: 121+825 | AH66: 12.6 | AI66: R.C Girder | AJ66: Good
I67: 16 | J67: Tigman - Caburian Road | K67: 1.05 | L67: 0 | M67: 0 | N67: 0 | O67: 1.05 | P67: 0 | Q67: FAIR | R67: km sta.78+150 | AG67: 123+500 | AH67: 12.3 | AI67: R.C Girder | AJ67: Good
I68: 18 | J68: Tigman - Rizal - Dumangueña Road | K68: 10.52 | L68: 9.03 | M68: 0 | N68: 0 | O68: 1.49 | P68: 0 | Q68: FAIR | R68: km sta.77+400 | AG68: 128+600 | AH68: 18.8 | AI68: R.C Girder | AJ68: Good
I69: 221 | J69: Hi-way Jct. Plaridel-Tigman-Caburian Rd | K69: 4.53 | L69: 1.17 | M69: 0 | N69: 0 | O69: 3.36 | P69: 0 | Q69: FAIR | R69: km sta.76+500 | AG69: 129+950 | AH69: 19 | AI69: R.C Girder | AJ69: Good
I70: 23 | J70: Malatgao - Babanitan Road | K70: 4.42 | L70: 2.9 | M70: 0 | N70: 0 | O70: 1.52 | P70: 0 | Q70: FAIR | R70: km sta.83+580 | AF70: Highway Jct. Tagumpay-Maliko Rd. | AG70: 119+250 | AH70: 21.6 | AI70: R.C Girder | AJ70: Good
I71: 24 | J71: Malatgao Section Road | K71: 8.25 | L71: 8.25 | M71: 0 | N71: 0 | O71: 0 | P71: 0 | Q71: FAIR | R71: km sta.83+580 | AF71: San Jose Port Barton Road - A | AG71: 125+675 | AH71: 26 | AI71: R.C Girder | AJ71: Good
I72: 25 | J72: Taritien Sea Road | K72: 0.88 | L72: 0 | M72: 0 | N72: 0 | O72: 0.88 | P72: 0 | Q72: FAIR | R72: km sta.85+500 | AF72: Abaroan - Linapaoan Road | AG72: 128+725 | AH72: 24.5 | AI72: R.C Girder | AJ72: Good
I73: 27 | J73: Antipuluan Sea Road | K73: 1.93 | L73: 0.28 | M73: 0 | N73: 0 | O73: 1.65 | P73: 0 | Q73: FAIR | R73: km sta.88+045 | AG73: 130+725 | AH73: 15 | AI73: R.C Girder | AJ73: Good
I74: 29 | J74: Narra School Road | K74: 0.86 | L74: 0.86 | M74: 0 | N74: 0 | O74: 0 | P74: 0 | Q74: FAIR | R74: km sta.92+250 | AF74: Highway Junction Tumarbong Road | AG74: 150+475 | AH74: 45 | AI74: R.C Girder | AJ74: Good
I75: 31 | J75: Ipil Road / Quirino | K75: 0.78 | L75: 0.78 | M75: 0 | N75: 0 | O75: 0 | P75: 0 | Q75: FAIR | R75: km sta.92+700 | AG75: 156+450 | AH75: 16.8 | AI75: R.C Girder | AJ75: Good
I76: 35 | J76: Caguisan Feeder Road | K76: 2.97 | L76: 0.81 | M76: 0 | N76: 0 | O76: 2.16 | P76: 0 | Q76: FAIR | R76: km sta.99+200 | AF76: Dumarao - Ilian - Ilian Road | AG76: 155+650 | AH76: 20.3 | AI76: R.C Girder | AJ76: Good
I77: 36 | J77: Batang-Batang Feeder Road | K77: 6.01 | L77: 0 | M77: 0 | N77: 0 | O77: 6.01 | P77: 0 | Q77: FAIR | R77: km sta.101+950 | AG77: 155+950 | AH77: 10 | AI77: R.C Girder | AJ77: Good
I78: 38 | J78: Teresa - Batang-Batang Road | K78: 3.9 | L78: 1.58 | M78: 0 | N78: 0 | O78: 2.32 | P78: 0 | Q78: FAIR | R78: km sta.105+550 | AF78: Tumarbong-Ilian Road | AG78: 163+950 | AH78: 18.5 | AI78: R.C Girder | AJ78: Good
I79: 39 | J79: Teresa Feeder Road | K79: 4.94 | L79: 0.14 | M79: 0 | N79: 0 | O79: 4.8 | P79: 0 | Q79: FAIR | R79: km sta.104+100 | AG79: 173+200 | AH79: 12.3 | AI79: R.C Girder | AJ79: Good
I80: 105 | J80: Bato-Bato Feeder Road | K80: 3.65 | L80: 0 | M80: 0 | N80: 0 | O80: 3.65 | P80: 0 | Q80: FAIR | R80: km sta.105+950 | AF80: Canadcan - Alimanguan Road | AG80: 117+900 | AH80: 22.5 | AI80: R.C Girder | AJ80: Good
I81: 41 | J81: Calategas Dampsite Road | K81: 2.81 | L81: 0 | M81: 0 | N81: 0 | O81: 2.81 | P81: 0 | Q81: FAIR | R81: km sta.116+100 | AF81: Alimanguan - Kemdeng Road | AG81: New Agutaya Bridge | AH81: 43 | AI81: R.C Girder | AJ81: Good
I82: 104 | J82: Sandoval - Bagong Sikat Road | K82: 3.13 | L82: 0 | M82: 0 | N82: 0 | O82: 3.13 | P82: 0 | Q82: FAIR | R82: km sta.81+500 | AF82: San Jose - Port Barton Road -B | AG82: 183+850 | AH82: 16.8 | AI82: R.C Girder | AJ82: Good
I83: 116 | J83: Pulot I - Pulot III Road | K83: 12.3 | L83: 6.67 | M83: 0 | N83: 0 | O83: 5.63 | P83: 0 | Q83: FAIR | R83: km sta.162+800 | AF83: H-way Jct. Little Caramay-Caruray Rd.-A | AH83: 15.8 | AI83: R.C Girder | AJ83: Good
I84: 50 | J84: Maasin Rancho Road | K84: 7.69 | L84: 2 | M84: 0 | N84: 0 | O84: 5.69 | P84: 0 | Q84: FAIR | R84: km sta.174+800- | AF84: Kemdeng - Carabao Breeding Road | AH84: 16.5 | AI84: R.C Girder | AJ84: Good
I85: 52 | J85: Ipilan Rizal Road | K85: 6.64 | L85: 0 | M85: 0 | N85: 0 | O85: 6.64 | P85: 0 | Q85: FAIR | R85: km sta.184+300 | AF85: Liminangcong-Cataban Road | AG85: 239+200 | AH85: 10 | AI85: R.C Girder | AJ85: Good
I86: 53 | J86: Ipilan Linao Road | K86: 6.46 | L86: 5.64 | M86: 0 | N86: 0 | O86: 0.82 | P86: 0 | Q86: FAIR | R86: km sta.180+150 | AG86: 246+200 | AH86: 18 | AI86: R.C Girder | AJ86: Good
I87: 103 | J87: Barong-Barong Feeder Road | K87: 1.24 | L87: 0.19 | M87: 0 | N87: 0 | O87: 1.05 | P87: 0 | Q87: FAIR | R87: km sta.182+700 | AG87: 252+000 | AH87: 15 | AI87: R.C Girder | AJ87: Good
I88: 57 | J88: Tagusao Feeder Road | K88: 1.36 | L88: 0.3 | M88: 0 | N88: 0 | O88: 1.06 | P88: 0 | Q88: FAIR | R88: km sta.183+500 | AF88: Paglaum - Itangil Road | AG88: Ariman-an Bridge | AH88: 11 | AI88: R.C Girder | AJ88: Good
I89: 58 | J89: Pintasan Sea Road | K89: 0.36 | L89: 0 | M89: 0 | N89: 0 | O89: 0.36 | P89: 0 | Q89: FAIR | R89: km sta.185+500 | AG89: Impatian Bridge I | AH89: 16 | AI89: R.C Girder | AJ89: Good
I90: 59 | J90: Pintasan Feeder Road | K90: 0.8 | L90: 0 | M90: 0 | N90: 0 | O90: 0.8 | P90: 0 | Q90: FAIR | R90: km sta.185+500 | AG90: Impatian Bridge II | AH90: 13 | AI90: R.C Girder | AJ90: Good
I91: 97 | J91: Aribungos Feeder Road | K91: 8.45 | L91: 8.45 | M91: 0 | N91: 0 | O91: 0 | P91: 0 | Q91: FAIR | R91: km sta.186+100 | AG91: Itangil I | AH91: 12 | AI91: R.C Girder | AJ91: Good
I92: 56 | J92: Ipilan - Mainit Road | K92: 5.72 | L92: 1.72 | M92: 0 | N92: 0 | O92: 4 | P92: 0 | Q92: FAIR | R92: km sta.182+050 | AF92: New Ibajay - Lamoro Road | AG92: 356+500 | AH92: 26 | AI92: R.C Girder | AJ92: Good
I93: 61 | J93: Mati Feder Road | K93: 4.5 | L93: 1.63 | M93: 0 | N93: 0 | O93: 2.87 | P93: 0 | Q93: FAIR | R93: km sta.192+850 | AF93: Itangil - Latongay Road | AG93: Itangil Bridge II | AH93: 15.6 | AI93: R.C Girder | AJ93: Good
I94: 62 | J94: Tigaplan Feeder Road | K94: 3.03 | L94: 0 | M94: 0 | N94: 0 | O94: 3.03 | P94: 0 | Q94: FAIR | R94: km sta.186+600 | AF94: Catama - Tanatanaen Road | AG94: Catama-Tanatanaen Bridge I | AH94: 15.4 | AI94: R.C Girder | AJ94: Good
I95: 63 | J95: Suring - Lada Road | K95: 3.04 | L95: 1.11 | M95: 0 | N95: 0 | O95: 1.93 | P95: 0 | Q95: FAIR | R95: km sta.187+450 | AF95: Latongay - Sta. Teresita Road | AG95: Ibalod Bridge | AH95: 15.4 | AI95: R.C Girder | AJ95: Good
I96: 96 | J96: Tub - Tub - Amas Road | K96: 5.73 | L96: 3.47 | M96: 0 | N96: 0 | O96: 2.26 | P96: 0 | Q96: FAIR | R96: km sta.193+950 | AG96: Tagumpay Bridge I | AH96: 22 | AI96: R.C Girder | AJ96: Good
I97: 65 | J97: Oring - Oring Road | K97: 2.7 | L97: 0 | M97: 0 | N97: 0 | O97: 2.7 | P97: 0 | Q97: FAIR | R97: km sta.195+500 | AG97: Tagumpay Bridge II | AH97: 12.48 | AI97: R.C Girder | AJ97: Good
I98: 66 | J98: Amas Feeder Road | K98: 4.2 | L98: 0 | M98: 0 | N98: 0 | O98: 4.2 | P98: 0 | Q98: FAIR | R98: km sta.195+700 | AG98: Tagumpay Bridge III | AH98: 12.7 | AI98: R.C Girder | AJ98: Good
I99: 71 | J99: Saraza - Tagbalogo | K99: 2.68 | L99: 0 | M99: 0 | N99: 0 | O99: 2.68 | P99: 0 | Q99: FAIR | R99: km sta.201+900 | AG99: Sta. Maria Bridge I | AH99: 12.7 | AI99: R.C Girder | AJ99: Good
I100: 72 | J100: Salogon Feeder Road | K100: 1.89 | L100: 0.83 | M100: 0 | N100: 0 | O100: 1.06 | P100: 0 | Q100: FAIR | R100: km sta.207+450 | AG100: Sta. Maria Bridge II | AH100: 18.7 | AI100: R.C Girder | AJ100: Good
I101: 73 | J101: Malis - Pansur - Rabuk Road | K101: 4.56 | L101: 0 | M101: 0 | N101: 0 | O101: 4.56 | P101: 0 | Q101: FAIR | R101: km sta.210+050 | AG101: Salban Bridge | AH101: 12.6 | AI101: R.C Girder | AJ101: Good
...

Sheet SUMMARY 2021
A1: PROVINCIAL ENGINEER'S OFFICE
A2: PROVINCIAL ROAD NETWORK AND ITS STATUS / CONDITION
A3: 2021
A5: SUMMARY OF ROAD SURFACE
A7: NO | B7: MUNICIPALITY | C7: NO. OF PROVINCIAL ROAD | D7: TOTAL LENGTH (KM) | E7: CONCRETE (KM) | F7: ASPHALT (KM) | G7: EARTH (KM) | H7: GRAVEL (KM)
A8: 1 | B8: Aborlan | C8: 24 | D8: =SUM(E8:H8) -> 98.55 | E8: ='inventory2022 (FINAL)'!F32 -> 56.048 | F8: ='inventory2022 (FINAL)'!G32 -> 0 | G8: ='inventory2022 (FINAL)'!H32 -> 4.53 | H8: ='inventory2022 (FINAL)'!I32 -> 37.972
A9: 2 | B9: Balabac | C9: 2 | D9: =SUM(E9:H9) -> 18.5 | E9: ='inventory2022 (FINAL)'!F37 -> 17.81 | F9: ='inventory2022 (FINAL)'!G37 -> 0 | G9: ='inventory2022 (FINAL)'!H37 -> 0 | H9: ='inventory2022 (FINAL)'!I37 -> 0.69
A10: 3 | B10: Bataraza | C10: 14 | D10: =SUM(E10:H10) -> 49.3 | E10: ='inventory2022 (FINAL)'!F54 -> 4.56 | F10: ='inventory2022 (FINAL)'!G54 -> 0 | G10: ='inventory2022 (FINAL)'!H54 -> 0 | H10: ='inventory2022 (FINAL)'!I54 -> 44.74
A11: 4 | B11: Brooke's Point | C11: 32 | D11: =SUM(E11:H11) -> 107.85 | E11: ='inventory2022 (FINAL)'!F88 -> 41.619 | F11: ='inventory2022 (FINAL)'!G88 -> 0 | G11: ='inventory2022 (FINAL)'!H88 -> 0 | H11: ='inventory2022 (FINAL)'!I88 -> 66.231
A12: 5 | B12: Narra | C12: 27 | D12: =SUM(E12:H12) -> 102.5 | E12: ='inventory2022 (FINAL)'!F118 -> 29.04 | F12: ='inventory2022 (FINAL)'!G118 -> 0 | G12: ='inventory2022 (FINAL)'!H118 -> 0 | H12: ='inventory2022 (FINAL)'!I118 -> 73.46
A13: 6 | B13: Quezon | C13: 7 | D13: =SUM(E13:H13) -> 42.45 | E13: ='inventory2022 (FINAL)'!F128 -> 5.72 | F13: ='inventory2022 (FINAL)'!G128 -> 0 | G13: ='inventory2022 (FINAL)'!H128 -> 0 | H13: ='inventory2022 (FINAL)'!I128 -> 36.73
A14: 7 | B14: Rizal | C14: 1 | D14: =SUM(E14:H14) -> 3.1 | E14: ='inventory2022 (FINAL)'!F132 -> 0.48 | F14: ='inventory2022 (FINAL)'!G132 -> 0 | G14: ='inventory2022 (FINAL)'!H132 -> 0 | H14: ='inventory2022 (FINAL)'!I132 -> 2.62
A15: 8 | B15: Sofronio Española | C15: 10 | D15: =SUM(E15:H15) -> 54.1 | E15: ='inventory2022 (FINAL)'!F145 -> 15.85 | F15: ='inventory2022 (FINAL)'!G145 -> 0 | G15: ='inventory2022 (FINAL)'!H145 -> 0 | H15: ='inventory2022 (FINAL)'!I145 -> 38.25
A16: SOUTH SUB-TOTAL | C16: =SUM(C8:C15) -> 117 | D16: =SUM(D8:D15) -> 476.35 | E16: =SUM(E8:E15) -> 171.127 | F16: =SUM(F8:F15) -> 0 | G16: =SUM(G8:G15) -> 4.53 | H16: =SUM(H8:H15) -> 300.693 | I16: =SUM(E16:H16) -> 476.35
A17: 9 | B17: Agutaya | C17: 2 | D17: =SUM(E17:H17) -> 7.25 | E17: ='inventory2022 (FINAL)'!F150 -> 3.3 | F17: ='inventory2022 (FINAL)'!G150 -> 0 | G17: ='inventory2022 (FINAL)'!H150 -> 0 | H17: ='inventory2022 (FINAL)'!I150 -> 3.95
A18: 10 | B18: Araceli | C18: 11 | D18: =SUM(E18:H18) -> 62 | E18: ='inventory2022 (FINAL)'!F164 -> 12.194 | F18: ='inventory2022 (FINAL)'!G164 -> 0 | G18: ='inventory2022 (FINAL)'!H164 -> 0 | H18: ='inventory2022 (FINAL)'!I164 -> 49.806
A19: 11 | B19: Busuanga | C19: 8 | D19: =SUM(E19:H19) -> 42.084 | E19: ='inventory2022 (FINAL)'!F175 -> 1.404 | F19: ='inventory2022 (FINAL)'!G175 -> 0 | G19: ='inventory2022 (FINAL)'!H175 -> 0 | H19: ='inventory2022 (FINAL)'!I175 -> 40.68
A20: 12 | B20: Cagayancillo | C20: 1 | D20: =SUM(E20:H20) -> 8.741 | E20: ='inventory2022 (FINAL)'!F179 -> 1.18 | F20: ='inventory2022 (FINAL)'!G179 -> 0 | G20: ='inventory2022 (FINAL)'!H179 -> 0 | H20: ='inventory2022 (FINAL)'!I179 -> 7.561
A21: 13 | B21: Coron | C21: 13 | D21: =SUM(E21:H21) -> 116.96 | E21: ='inventory2022 (FINAL)'!F195 -> 57.31 | F21: ='inventory2022 (FINAL)'!G195 -> 0 | G21: ='inventory2022 (FINAL)'!H195 -> 3.42 | H21: ='inventory2022 (FINAL)'!I195 -> 56.23
A22: 14 | B22: Culion | C22: 4 | D22: =SUM(E22:H22) -> 28.0002 | E22: ='inventory2022 (FINAL)'!F202 -> 17.1412 | F22: ='inventory2022 (FINAL)'!G202 -> 0 | G22: ='inventory2022 (FINAL)'!H202 -> 0 | H22: ='inventory2022 (FINAL)'!I202 -> 10.859
A23: 15 | B23: Cuyo | C23: 8 | D23: =SUM(E23:H23) -> 49 | E23: ='inventory2022 (FINAL)'!F213 -> 26.39 | F23: ='inventory2022 (FINAL)'!G213 -> 5.143 | G23: ='inventory2022 (FINAL)'!H213 -> 0.1 | H23: ='inventory2022 (FINAL)'!I213 -> 17.367
A24: 16 | B24: Dumaran | C24: 14 | D24: =SUM(E24:H24) -> 74.19 | E24: ='inventory2022 (FINAL)'!F230 -> 26.14 | F24: ='inventory2022 (FINAL)'!G230 -> 0 | G24: ='inventory2022 (FINAL)'!H230 -> 0 | H24: ='inventory2022 (FINAL)'!I230 -> 48.05
A25: 17 | B25: El Nido | C25: 5 | D25: =SUM(E25:H25) -> 28.124 | E25: ='inventory2022 (FINAL)'!F238 -> 13.035 | F25: ='inventory2022 (FINAL)'!G238 -> 0 | G25: ='inventory2022 (FINAL)'!H238 -> 0 | H25: ='inventory2022 (FINAL)'!I238 -> 15.089
A26: 18 | B26: Magsaysay | C26: 11 | D26: =SUM(E26:H26) -> 35.78 | E26: ='inventory2022 (FINAL)'!F252 -> 19.316 | F26: ='inventory2022 (FINAL)'!G252 -> 5.6 | G26: ='inventory2022 (FINAL)'!H252 -> 0.914 | H26: ='inventory2022 (FINAL)'!I252 -> 9.95
A27: 19 | B27: Roxas | C27: 17 | D27: =SUM(E27:H27) -> 129.171 | E27: ='inventory2022 (FINAL)'!F272 -> 37.722 | F27: ='inventory2022 (FINAL)'!G272 -> 0 | G27: ='inventory2022 (FINAL)'!H272 -> 0 | H27: ='inventory2022 (FINAL)'!I272 -> 91.449
A28: 20 | B28: San Vicente | C28: 8 | D28: =SUM(E28:H28) -> 87.301 | E28: ='inventory2022 (FINAL)'!F283 -> 35.896 | F28: ='inventory2022 (FINAL)'!G283 -> 0 | G28: ='inventory2022 (FINAL)'!H283 -> 0 | H28: ='inventory2022 (FINAL)'!I283 -> 51.405
A29: 21 | B29: Taytay | C29: 8 | D29: =SUM(E29:H29) -> 84.6 | E29: ='inventory2022 (FINAL)'!F294 -> 18.353 | F29: ='inventory2022 (FINAL)'!G294 -> 0 | G29: ='inventory2022 (FINAL)'!H294 -> 1.72 | H29: ='inventory2022 (FINAL)'!I294 -> 64.527
A30: NORTH SUB-TOTAL | C30: =SUM(C17:C29) -> 110 | D30: =SUM(D17:D29) -> 753.2012 | E30: =SUM(E17:E29) -> 269.3812 | F30: =SUM(F17:F29) -> 10.743 | G30: =SUM(G17:G29) -> 6.154 | H30: =SUM(H17:H29) -> 466.923 | I30: =SUM(E30:H30) -> 753.2012
A31: GRANT TOTAL (SOUTH & NORTH) | C31: =C16+C30 -> 227 | D31: =D16+D30 -> 1229.5512 | E31: =E16+E30 -> 440.5082 | F31: =F16+F30 -> 10.743 | G31: =G16+G30 -> 10.684 | H31: =H16+H30 -> 767.616 | I31: =I30+I16 -> 1229.5512 | J31: =SUM(E31:H31) -> 1229.5512
A33: SUMMARY OF ROAD CONDITION
A35: NO | B35: ROAD CONDITION | C35: TOTAL LENGTH (KM) | E35: SUMMARY OF GOOD TO FAIR / POOR TO BAD ROAD CONDITION | K35: aborlan | L35: balabac | M35: bataraza | N35: brookes point | O35: narra | P35: quezon | Q35: rizal | R35: sofronio española | S35: agutaya | T35: araceli | U35: busuanga | V35: cagayancillo | W35: coron | X35: culion | Y35: cuyo | Z35: dumaran | AA35: el nido | AB35: magsaysay | AC35: roxas | AD35: san vicente | AE35: taytay | AF35: total
A36: 1 | B36: Good | C36: =AF36 -> 299.65 | E36: GOOD TO FAIR | H36: =C36+C37 -> 932.335 | J36: Good | K36: =SUMIF('inventory2022 (FINAL)'!J8:J31,"Good",'inventory2022 (FINAL)'!E8:E31) -> 36 | L36: =SUMIF('inventory2022 (FINAL)'!$J$35:$J$36,"Good",'inventory2022 (FINAL)'!$E$35:$E$36) -> 12.9 | M36: =SUMIF('inventory2022 (FINAL)'!$J$40:$J$53,"Good",'inventory2022 (FINAL)'!$E$40:$E$53) -> 1.3 | N36: =SUMIF('inventory2022 (FINAL)'!$J$56:$J$87,"Good",'inventory2022 (FINAL)'!$E$56:$E$87) -> 19.5 | O36: =SUMIF('inventory2022 (FINAL)'!$J$91:$J$117,"Good",'inventory2022 (FINAL)'!$E$91:$E$117) -> 16.9 | P36: =SUMIF('inventory2022 (FINAL)'!$J$121:$J$127,"Good",'inventory2022 (FINAL)'!$E$121:$E$127) -> 0 | Q36: =SUMIF('inventory2022 (FINAL)'!$J$131,"Good",'inventory2022 (FINAL)'!$E$131) -> 0 | R36: =SUMIF('inventory2022 (FINAL)'!$J$135:$J$144,"Good",'inventory2022 (FINAL)'!$E$135:$E$144) -> 7.2 | S36: =SUMIF('inventory2022 (FINAL)'!$J$148:$J$149,"Good",'inventory2022 (FINAL)'!$E$148:$E$149) -> 0 | T36: =SUMIF('inventory2022 (FINAL)'!$J$153:$J$163,"Good",'inventory2022 (FINAL)'!$E$153:$E$163) -> 0 | U36: =SUMIF('inventory2022 (FINAL)'!$J$167:$J$174,"Good",'inventory2022 (FINAL)'!$E$167:$E$174) -> 7.6 | V36: =SUMIF('inventory2022 (FINAL)'!$J$178,"Good",'inventory2022 (FINAL)'!$E$178) -> 0 | W36: =SUMIF('inventory2022 (FINAL)'!$J$182:$J$194,"Good",'inventory2022 (FINAL)'!$E$182:$E$194) -> 53.6 | X36: =SUMIF('inventory2022 (FINAL)'!$J$198:$J$201,"Good",'inventory2022 (FINAL)'!$E$198:$E$201) -> 17 | Y36: =SUMIF('inventory2022 (FINAL)'!$J$205:$J$212,"Good",'inventory2022 (FINAL)'!$E$205:$E$212) -> 31.3 | Z36: =SUMIF('inventory2022 (FINAL)'!$J$216:$J$229,"Good",'inventory2022 (FINAL)'!$E$216:$E$229) -> 5 | AA36: =SUMIF('inventory2022 (FINAL)'!$J$233:$J$237,"Good",'inventory2022 (FINAL)'!$E$233:$E$237) -> 11 | AB36: =SUMIF('inventory2022 (FINAL)'!$J$241:$J$251,"Good",'inventory2022 (FINAL)'!$E$241:$E$251) -> 4.67 | AC36: =SUMIF('inventory2022 (FINAL)'!$J$255:$J$271,"Good",'inventory2022 (FINAL)'!$E$255:$E$271) -> 27.33 | AD36: =SUMIF('inventory2022 (FINAL)'!$J$275:$J$282,"Good",'inventory2022 (FINAL)'!$E$275:$E$282) -> 34.55 | AE36: =SUMIF('inventory2022 (FINAL)'!$J$286:$J$293,"Good",'inventory2022 (FINAL)'!$E$286:$E$293) -> 13.8 | AF36: =SUM(K36:AE36) -> 299.65
A37: 2 | B37: Fair | C37: =AF37 -> 632.685 | E37: POOR TO BAD | H37: =C38+C39 -> 311.68 | J37: Fair | K37: =SUMIF('inventory2022 (FINAL)'!J8:J31,"Fair",'inventory2022 (FINAL)'!E8:E31) -> 46.15 | L37: =SUMIF('inventory2022 (FINAL)'!$J$35:$J$36,"Fair",'inventory2022 (FINAL)'!$E$35:$E$36) -> 5.6 | M37: =SUMIF('inventory2022 (FINAL)'!$J$40:$J$53,"Fair",'inventory2022 (FINAL)'!$E$40:$E$53) -> 11.3 | N37: =SUMIF('inventory2022 (FINAL)'!$J$56:$J$87,"Fair",'inventory2022 (FINAL)'!$E$56:$E$87) -> 68.85 | O37: =SUMIF('inventory2022 (FINAL)'!$J$91:$J$117,"Fair",'inventory2022 (FINAL)'!$E$91:$E$117) -> 45.4 | P37: =SUMIF('inventory2022 (FINAL)'!$J$121:$J$127,"Fair",'inventory2022 (FINAL)'!$E$121:$E$127) -> 0 | Q37: =SUMIF('inventory2022 (FINAL)'!$J$131,"Fair",'inventory2022 (FINAL)'!$E$131) -> 0 | R37: =SUMIF('inventory2022 (FINAL)'!$J$135:$J$144,"Fair",'inventory2022 (FINAL)'!$E$135:$E$144) -> 12.3 | S37: =SUMIF('inventory2022 (FINAL)'!$J$148:$J$149,"Fair",'inventory2022 (FINAL)'!$E$148:$E$149) -> 7.25 | T37: =SUMIF('inventory2022 (FINAL)'!$J$153:$J$163,"Fair",'inventory2022 (FINAL)'!$E$153:$E$163) -> 10.1 | U37: =SUMIF('inventory2022 (FINAL)'!$J$167:$J$174,"Fair",'inventory2022 (FINAL)'!$E$167:$E$174) -> 32.904 | V37: =SUMIF('inventory2022 (FINAL)'!$J$178,"Fair",'inventory2022 (FINAL)'!$E$178) -> 8.741 | W37: =SUMIF('inventory2022 (FINAL)'!$J$182:$J$194,"Fair",'inventory2022 (FINAL)'!$E$182:$E$194) -> 63.16 | X37: =SUMIF('inventory2022 (FINAL)'!$J$198:$J$201,"Fair",'inventory2022 (FINAL)'!$E$198:$E$201) -> 11 | Y37: =SUMIF('inventory2022 (FINAL)'!$J$205:$J$212,"Fair",'inventory2022 (FINAL)'!$E$205:$E$212) -> 12.7 | Z37: =SUMIF('inventory2022 (FINAL)'!$J$216:$J$229,"Fair",'inventory2022 (FINAL)'!$E$216:$E$229) -> 61.9 | AA37: =SUMIF('inventory2022 (FINAL)'!$J$233:$J$237,"Fair",'inventory2022 (FINAL)'!$E$233:$E$237) -> 13.6 | AB37: =SUMIF('inventory2022 (FINAL)'!$J$241:$J$251,"Fair",'inventory2022 (FINAL)'!$E$241:$E$251) -> 7.96 | AC37: =SUMIF('inventory2022 (FINAL)'!$J$255:$J$271,"Fair",'inventory2022 (FINAL)'!$E$255:$E$271) -> 98.65 | AD37: =SUMIF('inventory2022 (FINAL)'!$J$275:$J$282,"Fair",'inventory2022 (FINAL)'!$E$275:$E$282) -> 47.62 | AE37: =SUMIF('inventory2022 (FINAL)'!$J$286:$J$293,"Fair",'inventory2022 (FINAL)'!$E$286:$E$293) -> 67.5 | AF37: =SUM(K37:AE37) -> 632.685
A38: 3 | B38: Poor | C38: =AF38 -> 196.92 | E38: GRAND TOTAL | H38: =SUM(H36:H37) -> 1244.015 | J38: Poor | K38: =SUMIF('inventory2022 (FINAL)'!J8:J31,"Poor",'inventory2022 (FINAL)'!E8:E31) -> 8.8 | L38: =SUMIF('inventory2022 (FINAL)'!$J$35:$J$36,"Poor",'inventory2022 (FINAL)'!$E$35:$E$36) -> 0 | M38: =SUMIF('inventory2022 (FINAL)'!$J$40:$J$53,"Poor",'inventory2022 (FINAL)'!$E$40:$E$53) -> 12.2 | N38: =SUMIF('inventory2022 (FINAL)'!$J$56:$J$87,"Poor",'inventory2022 (FINAL)'!$E$56:$E$87) -> 19.5 | O38: =SUMIF('inventory2022 (FINAL)'!$J$91:$J$117,"Poor",'inventory2022 (FINAL)'!$E$91:$E$117) -> 18.7 | P38: =SUMIF('inventory2022 (FINAL)'!$J$121:$J$127,"Poor",'inventory2022 (FINAL)'!$E$121:$E$127) -> 25.45 | Q38: =SUMIF('inventory2022 (FINAL)'!$J$131,"Poor",'inventory2022 (FINAL)'!$E$131) -> 3.1 | R38: =SUMIF('inventory2022 (FINAL)'!$J$135:$J$144,"Poor",'inventory2022 (FINAL)'!$E$135:$E$144) -> 26.8 | S38: =SUMIF('inventory2022 (FINAL)'!$J$148:$J$149,"Poor",'inventory2022 (FINAL)'!$E$148:$E$149) -> 0 | T38: =SUMIF('inventory2022 (FINAL)'!$J$153:$J$163,"Poor",'inventory2022 (FINAL)'!$E$153:$E$163) -> 48.7 | U38: =SUMIF('inventory2022 (FINAL)'!$J$167:$J$174,"Poor",'inventory2022 (FINAL)'!$E$167:$E$174) -> 0 | V38: =SUMIF('inventory2022 (FINAL)'!$J$178,"Poor",'inventory2022 (FINAL)'!$E$178) -> 0 | W38: =SUMIF('inventory2022 (FINAL)'!$J$182:$J$194,"Poor",'inventory2022 (FINAL)'!$E$182:$E$194) -> 0.2 | X38: =SUMIF('inventory2022 (FINAL)'!$J$198:$J$201,"Poor",'inventory2022 (FINAL)'!$E$198:$E$201) -> 0 | Y38: =SUMIF('inventory2022 (FINAL)'!$J$205:$J$212,"Poor",'inventory2022 (FINAL)'!$E$205:$E$212) -> 0 | Z38: =SUMIF('inventory2022 (FINAL)'!$J$216:$J$229,"Poor",'inventory2022 (FINAL)'!$E$216:$E$229) -> 12 | AA38: =SUMIF('inventory2022 (FINAL)'!$J$233:$J$237,"Poor",'inventory2022 (FINAL)'!$E$233:$E$237) -> 0 | AB38: =SUMIF('inventory2022 (FINAL)'!$J$241:$J$251,"Poor",'inventory2022 (FINAL)'!$E$241:$E$251) -> 15.97 | AC38: =SUMIF('inventory2022 (FINAL)'!$J$255:$J$271,"Poor",'inventory2022 (FINAL)'!$E$255:$E$271) -> 0 | AD38: =SUMIF('inventory2022 (FINAL)'!$J$275:$J$282,"Poor",'inventory2022 (FINAL)'!$E$275:$E$282) -> 5.5 | AE38: =SUMIF('inventory2022 (FINAL)'!$J$286:$J$293,"Poor",'inventory2022 (FINAL)'!$E$286:$E$293) -> 0 | AF38: =SUM(K38:AE38) -> 196.92
A39: 4 | B39: Bad | C39: =AF39 -> 114.76 | J39: Bad | K39: =SUMIF('inventory2022 (FINAL)'!J8:J31,"Bad",'inventory2022 (FINAL)'!E8:E31) -> 7.6 | L39: =SUMIF('inventory2022 (FINAL)'!$J$35:$J$36,"Bad",'inventory2022 (FINAL)'!$E$35:$E$36) -> 0 | M39: =SUMIF('inventory2022 (FINAL)'!$J$40:$J$53,"Bad",'inventory2022 (FINAL)'!$E$40:$E$53) -> 24.5 | N39: =SUMIF('inventory2022 (FINAL)'!$J$56:$J$87,"Bad",'inventory2022 (FINAL)'!$E$56:$E$87) -> 0 | O39: =SUMIF('inventory2022 (FINAL)'!$J$91:$J$117,"Bad",'inventory2022 (FINAL)'!$E$91:$E$117) -> 21.5 | P39: =SUMIF('inventory2022 (FINAL)'!$J$121:$J$127,"Bad",'inventory2022 (FINAL)'!$E$121:$E$127) -> 17 | Q39: =SUMIF('inventory2022 (FINAL)'!$J$131,"Bad",'inventory2022 (FINAL)'!$E$131) -> 0 | R39: =SUMIF('inventory2022 (FINAL)'!$J$135:$J$144,"Bad",'inventory2022 (FINAL)'!$E$135:$E$144) -> 7.8 | S39: =SUMIF('inventory2022 (FINAL)'!$J$148:$J$149,"Bad",'inventory2022 (FINAL)'!$E$148:$E$149) -> 0 | T39: =SUMIF('inventory2022 (FINAL)'!$J$153:$J$163,"Bad",'inventory2022 (FINAL)'!$E$153:$E$163) -> 3.2 | U39: =SUMIF('inventory2022 (FINAL)'!$J$167:$J$174,"Bad",'inventory2022 (FINAL)'!$E$167:$E$174) -> 1.58 | V39: =SUMIF('inventory2022 (FINAL)'!$J$178,"Bad",'inventory2022 (FINAL)'!$E$178) -> 0 | W39: =SUMIF('inventory2022 (FINAL)'!$J$182:$J$194,"Bad",'inventory2022 (FINAL)'!$E$182:$E$194) -> 0 | X39: =SUMIF('inventory2022 (FINAL)'!$J$198:$J$201,"Bad",'inventory2022 (FINAL)'!$E$198:$E$201) -> 0 | Y39: =SUMIF('inventory2022 (FINAL)'!$J$205:$J$212,"Bad",'inventory2022 (FINAL)'!$E$205:$E$212) -> 5 | Z39: =SUMIF('inventory2022 (FINAL)'!$J$216:$J$229,"Bad",'inventory2022 (FINAL)'!$E$216:$E$229) -> 9.7 | AA39: =SUMIF('inventory2022 (FINAL)'!$J$233:$J$237,"Bad",'inventory2022 (FINAL)'!$E$233:$E$237) -> 3 | AB39: =SUMIF('inventory2022 (FINAL)'!$J$241:$J$251,"Bad",'inventory2022 (FINAL)'!$E$241:$E$251) -> 7.18 | AC39: =SUMIF('inventory2022 (FINAL)'!$J$255:$J$271,"Bad",'inventory2022 (FINAL)'!$E$255:$E$271) -> 3.4 | AD39: =SUMIF('inventory2022 (FINAL)'!$J$275:$J$282,"Bad",'inventory2022 (FINAL)'!$E$275:$E$282) -> 0 | AE39: =SUMIF('inventory2022 (FINAL)'!$J$286:$J$293,"Bad",'inventory2022 (FINAL)'!$E$286:$E$293) -> 3.3 | AF39: =SUM(K39:AE39) -> 114.76
A40: GRAND TOTAL | C40: =SUM(C36:C39) -> 1244.015 | K40: =SUM(K36:K39) -> 98.55 | L40: =SUM(L36:L39) -> 18.5 | M40: =SUM(M36:M39) -> 49.3 | N40: =SUM(N36:N39) -> 107.85 | O40: =SUM(O36:O39) -> 102.5 | P40: =SUM(P36:P39) -> 42.45 | Q40: =SUM(Q36:Q39) -> 3.1 | R40: =SUM(R36:R39) -> 54.1 | ... AF40: =SUM(AF36:AF39) -> 1244.015
B43: Prepared by: | E43: Reviewed by:
K44: CONCRETE (KM) | L44: ASPHALT (KM) | M44: EARTH (KM) | N44: GRAVEL (KM)
J45: Good | K45: =SUMIF('inventory2022 (FINAL)'!$J$8:$J$294,"Good",'inventory2022 (FINAL)'!$F$8:$F$294) -> 221.1882 | L45: =SUMIF('inventory2022 (FINAL)'!$J$8:$J$294,"Good",'inventory2022 (FINAL)'!$G$8:$G$294) -> 2.083 | M45: =SUMIF('inventory2022 (FINAL)'!$J$8:$J$294,"Good",'inventory2022 (FINAL)'!$H$8:$H$294) -> 3.42 | N45: =SUMIF('inventory2022 (FINAL)'!$J$8:$J$294,"Good",'inventory2022 (FINAL)'!$I$8:$I$294) -> 76.466 | O45: =SUM(K45:N45) -> 303.1572
B46: CHARISMA WY A. BOLEN | E46: RANFORD T. VILLEGAS | J46: Fair | K46: =SUMIF('inventory2022 (FINAL)'!$J$8:$J$294,"Fair",'inventory2022 (FINAL)'!$F$8:$F$294) -> 171.764 | L46: =SUMIF('inventory2022 (FINAL)'!$J$8:$J$294,"Fair",'inventory2022 (FINAL)'!$G$8:$G$294) -> 0 | M46: =SUMIF('inventory2022 (FINAL)'!$J$8:$J$294,"Fair",'inventory2022 (FINAL)'!$H$8:$H$294) -> 1.72 | N46: =SUMIF('inventory2022 (FINAL)'!$J$8:$J$294,"Fair",'inventory2022 (FINAL)'!$I$8:$I$294) -> 450.972 | O46: =SUM(K46:N46) -> 624.456
B47: Engineer II | E47: Engineer III, OIC Asst. Provincial Engineer | J47: Poor | K47: =SUMIF('inventory2022 (FINAL)'!$J$8:$J$294,"Poor",'inventory2022 (FINAL)'!$F$8:$F$294) -> 33.224 | L47: =SUMIF('inventory2022 (FINAL)'!$J$8:$J$294,"Poor",'inventory2022 (FINAL)'!$G$8:$G$294) -> 2.55 | M47: =SUMIF('inventory2022 (FINAL)'!$J$8:$J$294,"Poor",'inventory2022 (FINAL)'!$H$8:$H$294) -> 0 | N47: =SUMIF('inventory2022 (FINAL)'!$J$8:$J$294,"Poor",'inventory2022 (FINAL)'!$I$8:$I$294) -> 149.181 | O47: =SUM(K47:N47) -> 184.955
J48: Bad | K48: =SUMIF('inventory2022 (FINAL)'!$J$8:$J$294,"Bad",'inventory2022 (FINAL)'!$F$8:$F$294) -> 14.332 | L48: =SUMIF('inventory2022 (FINAL)'!$J$8:$J$294,"Bad",'inventory2022 (FINAL)'!$G$8:$G$294) -> 6.11 | M48: =SUMIF('inventory2022 (FINAL)'!$J$8:$J$294,"Bad",'inventory2022 (FINAL)'!$H$8:$H$294) -> 5.544 | N48: =SUMIF('inventory2022 (FINAL)'!$J$8:$J$294,"Bad",'inventory2022 (FINAL)'!$I$8:$I$294) -> 90.997 | O48: =SUM(K48:N48) -> 116.983
O49: =SUM(O45:O48) -> 1229.5512
B50: Submitted by: | E50: Recommending Approval:
B53: ARLENE N. GAMO | E53: SAYLITO M. PURISIMA
B54: Engineer III | E54: PGDH (PEPO )/OIC (PEO)
E55: Head, Infrastructure Division
C57: Approved:
C60: JOSE CH. ALVAREZ
C61: Governor

Sheet Indicator 5
A1: Capacity Element 3: Information and resources for local road management | G1: pw: lrmpat2020
B3: Indicator 5: Annual budget for road rehabilitation
B4: Please fill up the table that follows with information on length of local core roads for the last three years
B6: For Core Roads in Gravel
B7: Year | C7: Total Length of Core Roads (a) | D7: Thickness of Road in mm | E7: Cost of rehabilitation based on thickness | F7: Ideal (Required) Budget | G7: Actual Budget for Road Rehabilitation based on Appropriation Ordinance | H7: % of Budget against Requirement
A8: 2021 | B8: Current Year | D8: 150 | E8: =IF(D8=150, 4572000, IF(D8=200, 4851000)) -> 4572000 | F8: =C8*E8 -> 0 | H8: =IF(C8="","",(G8/F8 * 100)) | K8: =OR(C8>=1,C9>=1,C10>=1) -> FALSE | L8: =IF(K8=TRUE,1,0) -> 0 | M8: =C8>=1 -> FALSE | N8: =IF(M8=TRUE,1,0) -> 0
A9: 2020 | B9: Prior Year | D9: 150 | E9: =IF(D9=150, 4572000, IF(D9=200, 4851000)) -> 4572000 | F9: =C9*E9 -> 0 | H9: =IF(C9="","",(G9/F9 * 100)) | M9: =C9>=1 -> FALSE | N9: =IF(M9=TRUE,1,0) -> 0
A10: 2019 | B10: Two Years Prior | D10: 150 | E10: =IF(D10=150, 4572000, IF(D10=200, 4851000)) -> 4572000 | F10: =C10*E10 -> 0 | H10: =IF(C10="","",(G10/F10 * 100)) | M10: =C10>=1 -> FALSE | N10: =IF(M10=TRUE,1,0) -> 0
G11: Average | H11: =IF(AND(C8="",C9="",C10=""),"",(SUM(H8:H10)/SUM(N8:N10)))
G13: Score for Gravel only | H13: =IF(L8=0,0,(IF(H11 >=100, 4, IF(H11 >=80, 3, IF(H11 >=60, 2, IF(H11 >=40, 1, 0)))))) -> 0
B15: For Core Roads in Asphalt
B16: Year | C16: Total Length of Core Roads | D16: Thickness of Road in mm | E16: Cost of rehabilitation based on thickness | F16: Ideal (Required) Budget | G16: Actual Budget for Road Rehabilitation based on Appropriation Ordinance | H16: % of Budget against Requirement
A17: 2021 | B17: Current Year | D17: 50 | E17: =IF(D17=50, 6591000) -> 6591000 | F17: =C17*E17 -> 0 | H17: =IF(C17="","",(G17/F17 * 100)) | K17: =OR(C17>=1,C18>=1,C19>=1) -> FALSE | L17: =IF(K17=TRUE,1,0) -> 0 | M17: =C17>=1 -> FALSE | N17: =IF(M17=TRUE,1,0) -> 0
A18: 2020 | B18: Prior Year | D18: 50 | E18: =IF(D18=50, 6591000) -> 6591000 | F18: =C18*E18 -> 0 | H18: =IF(C18="","",(G18/F18 * 100)) | M18: =C18>=1 -> FALSE | N18: =IF(M18=TRUE,1,0) -> 0
A19: 2019 | B19: Two Years Prior | D19: 50 | E19: =IF(D19=50, 6591000) -> 6591000 | F19: =C19*E19 -> 0 | H19: =IF(C19="","",(G19/F19 * 100)) | M19: =C19>=1 -> FALSE | N19: =IF(M19=TRUE,1,0) -> 0
G20: Average | H20: =IF(AND(C17="",C18="",C19=""),"",(SUM(H17:H19)/SUM(N17:N19)))
G22: Score for Asphalt only | H22: =IF(L17=0,0,IF(AND(C26="",C17="",C8=""),0,(IF(H20 >=100, 4, IF(H20 >=80, 3, IF(H20 >=60, 2, IF(H20 >=40, 1, 0))))))) -> 0
B24: For Core Roads in PCCP
B25: Year | C25: Total Length of Core Roads (a) | D25: Thickness of Road in mm | E25: Cost of rehabilitation based on thickness | F25: Ideal (Required) Budget | G25: Actual Budget for Road Rehabilitation based on Appropriation Ordinance | H25: % of Budget against Requirement
A26: 2021 | B26: Current Year | D26: 230 | E26: =IF(D26=150, 7487000, IF(D26=200, 9106000, IF(D26=230, 9847000))) -> 9847000 | F26: =C26*E26 -> 0 | G26: 970000000 | H26: =IF(C26="","",(G26/F26 * 100)) | K26: =OR(C26>=1,C27>=1,C28>=1) -> FALSE | L26: =IF(K26=TRUE,1,0) -> 0 | M26: =C26>=1 -> FALSE | N26: =IF(M26=TRUE,1,0) -> 0
A27: 2020 | B27: Prior Year | D27: 200 | E27: =IF(D27=150, 7487000, IF(D27=200, 9106000, IF(D27=230, 9847000))) -> 9106000 | F27: =C27*E27 -> 0 | G27: 810000000 | H27: =IF(C27="","",(G27/F27 * 100)) | M27: =C27>=1 -> FALSE | N27: =IF(M27=TRUE,1,0) -> 0
A28: 2019 | B28: Two Years Prior | D28: 150 | E28: =IF(D28=150, 7487000, IF(D28=200, 9106000, IF(D28=230, 9847000))) -> 7487000 | F28: =C28*E28 -> 0 | G28: 590000000 | H28: =IF(C28="","",(G28/F28 * 100)) | M28: =C28>=1 -> FALSE | N28: =IF(M28=TRUE,1,0) -> 0
G29: Average | H29: =IF(AND(C26="",C27="",C28=""),"",(SUM(H26:H28)/SUM(N26:N28)))
G31: Sore for PCCP only | H31: =IF(L26=0,0,(IF(H29 >=100, 4, IF(H29 >=80, 3, IF(H29 >=60, 2, IF(H29 >=40, 1, 0)))))) -> 0
B32: Average of all surfaces
B33: Surface | C33: Three-year average
B34: Gravel | C34: =IF(AND(C8="",C9="",C10=""),"",H11)
B35: Asphalt | C35: =IF(AND(C17="",C18="",C19=""),"",H20)
B36: PCCP | C36: =IF(AND(C26="",C27="",C28=""),"",H29)
B37: Average | C37: =IF(AND(C26="",C17="",C8=""),0,(SUM(C34:C36)/SUM(L8,L17,L26))) -> 0
B39: Score | C39: =IF(C37 >=100, 4, IF(C37 >=80, 3, IF(C37 >=60, 2, IF(C37 >=40, 1, 0)))) -> 0
B41: Notes/Annotations:
B53: Score is 4 if percentage is 100 or more.
B54: Score is 3 if percentage is at least 80.
B55: Score is 2 if percentage is at least 60.
B56: Score is 1 if percentage is at least 40.
B57: Score is 0 if percentage is at least 20.

Sheet inventory2019(FOR UPDATE)
A1: PROVINCIAL ENGINEER'S OFFICE
A2: PROVINCIAL ROAD NETWORK AND ITS STATUS / CONDITION
A3: 2019
A4: MUNICIPALITY OF ABORLAN
A6: ROAD ID | B6: ROAD NAME | C6: REVISED LENGTH (km/s.) | D6: OLD LENGTH | E6: SURFACE TYPE | J6: ROAD CONDITION | K6: KILOMETER POST | L6: REMARKS
E7: CONCRETE | F7: ASPHALT | G7: EARTH | H7: GRAVEL | I7: MIXED
A8: 219 | B8: Junction - Isaub Road | C8: =SUM(E8:I8) -> 0.4 | D8: ='[23]road inventory 2018'!C10 -> 0.65 | E8: 0 | F8: 0 | G8: 0 | H8: 0.4 | I8: 0 | J8: Fair | K8: km sta.57+800
A9: 1 | B9: Sagpangan Road | C9: =SUM(E9:I9) -> 5.48 | D9: ='[23]road inventory 2018'!C11 -> 5.5 | E9: 2.87 | F9: 0 | G9: 0 | H9: 2.61 | I9: 0 | J9: Fair | K9: km sta.66+400
A10: 2 | B10: Isaub - Marikit -Tubig Road | C10: =SUM(E10:I10) -> 0.92 | D10: ='[23]road inventory 2018'!C12 -> 0.8 | E10: 0.07 | F10: 0 | G10: 0 | H10: 0.85 | I10: 0 | J10: Good | K10: km sta.58+000
A11: 3 | B11: Mailigan - Sagpangan Road | C11: =SUM(E11:I11) -> 4.97 | D11: ='[23]road inventory 2018'!C13 -> 4.9 | E11: 0 | F11: 0 | G11: 0 | H11: 4.97 | I11: 0 | J11: Fair | K11: km sta.62+400
A12: 4 | B12: Iraan - Tubig Road | C12: =SUM(E12:I12) -> 2.67 | D12: ='[23]road inventory 2018'!C14 -> 2.7 | E12: 0.11 | F12: 0 | G12: 0 | H12: 2.56 | I12: 0 | J12: Poor | K12: km sta.64+900
A13: 93 | B13: Iraan - Baraki Road | C13: =SUM(E13:I13) -> 3.9 | D13: ='[23]road inventory 2018'!C15 -> 3.9 | E13: 3.9 | F13: 0 | G13: 0 | H13: 0 | I13: 0 | J13: =#REF! -> #REF! | K13: km sta.64+900
A14: 218 | B14: Isaub - Sagpangan Road | C14: =SUM(E14:I14) -> 5.61 | D14: ='[23]road inventory 2018'!C16 -> 5.8 | E14: 0 | F14: 0 | G14: 0 | H14: 5.61 | I14: 0 | J14: Fair | K14: km sta.58+000
A15: 5 | B15: PNAC Road | C15: =SUM(E15:I15) -> 2.85 | D15: ='[23]road inventory 2018'!C17 -> 2.8 | E15: 2.85 | F15: 0 | G15: 0 | H15: 0 | I15: 0 | J15: Good | K15: km sta.64+900
A16: 6 | B16: San Juan Road | C16: =SUM(E16:I16) -> 3.96 | D16: ='[23]road inventory 2018'!C18 -> 3.9 | E16: 2.7 | F16: 0 | G16: 0 | H16: 1.26 | I16: 0 | J16: Good | K16: km sta.66+400
A17: 7 | B17: Aborlan - River Landing | C17: =SUM(E17:I17) -> 1.15 | D17: ='[23]road inventory 2018'!C19 -> 1.1 | E17: 1.15 | F17: 0 | G17: 0 | H17: 0 | I17: 0 | J17: Good | K17: km sta.67+100
A18: 8 | B18: Aborlan Poblacion Road | C18: =SUM(E18:I18) -> 0.64 | D18: ='[23]road inventory 2018'!C20 -> 0.6 | E18: 0.64 | F18: 0 | G18: 0 | H18: 0 | I18: 0 | J18: Good | K18: km sta.66+950
A19: 9 | B19: Magbabadil - Cabigaan Road | C19: =SUM(E19:I19) -> 9.3 | D19: ='[23]road inventory 2018'!C21 -> 9 | E19: 9.3 | F19: 0 | G19: 0 | H19: 0 | I19: 0 | J19: Good | K19: km sta.66+800
A20: 10 | B20: Plaridel - Apis Cabigaan Road | C20: =SUM(E20:I20) -> 13.79 | D20: ='[23]road inventory 2018'!C22 -> 13.6 | E20: 8.79 | F20: 0 | G20: 0 | H20: 5 | I20: 0 | J20: =J19 -> Good | K20: km sta.75+650
A21: 11 | B21: Tagpait Feeder Road | C21: =SUM(E21:I21) -> 2.27 | D21: ='[23]road inventory 2018'!C23 -> 2.2 | E21: 0.21 | F21: 0 | G21: 0 | H21: 2.06 | I21: 0 | J21: Fair | K21: km sta.69+000
A22: 13 | B22: New Bantayan - Apis Road | C22: =SUM(E22:I22) -> 1.72 | D22: ='[23]road inventory 2018'!C24 -> 1.7 | E22: 0 | F22: 0 | G22: 0 | H22: 1.72 | I22: 0 | J22: Fair | K22: km sta.69+200
A23: 12 | B23: Tagbariri Road | C23: =SUM(E23:I23) -> 1.62 | D23: ='[23]road inventory 2018'!C25 -> 1.6 | E23: 0 | F23: 0 | G23: 0 | H23: 1.62 | I23: 0 | J23: Poor | K23: km sta.69+100
A24: 220 | B24: Tagbariri - Magsaysay Road | C24: =SUM(E24:I24) -> 2.11 | D24: ='[23]road inventory 2018'!C26 -> 2.3 | E24: 0 | F24: 0 | G24: 0 | H24: 2.11 | I24: 0 | J24: Poor | K24: km sta.71+150
A25: 14 | B25: Junction - Tigman Road | C25: =SUM(E25:I25) -> 4.12 | D25: ='[23]road inventory 2018'!C27 -> 4 | E25: 4.12 | F25: 0 | G25: 0 | H25: 0 | I25: 0 | J25: Good | K25: km sta.75+650
A26: 15 | B26: Tigman - Rizal Road | C26: =SUM(E26:I26) -> 0 | D26: ='[23]road inventory 2018'!C28 -> 3.2 | E26: 0 | F26: 0 | G26: 0 | H26: 0 | I26: 0 | J26: Poor | K26: km sta.77+400 | L26: NOT EXISTING
A27: 16 | B27: Tigman - Caburian Road | C27: =SUM(E27:I27) -> 1.05 | D27: ='[23]road inventory 2018'!C29 -> 1 | E27: 0 | F27: 0 | G27: 0 | H27: 1.05 | I27: 0 | J27: Fair | K27: km sta.78+150
A28: 17 | B28: Magbabadil - Baraki Road | C28: =SUM(E28:I28) -> 4.18 | D28: ='[23]road inventory 2018'!C30 -> 4 | E28: 4.18 | F28: 0 | G28: 0 | H28: 0 | I28: 0 | J28: Fair | K28: km sta.73+400
A29: 18 | B29: Tigman - Rizal - Dumangueña Road | C29: =SUM(E29:I29) -> 10.52 | D29: ='[23]road inventory 2018'!C31 -> 10.5 | E29: 4.54 | F29: 0 | G29: 0 | H29: 5.98 | I29: 0 | J29: Fair | K29: km sta.77+400
A30: 221 | B30: Hi-way Jct. Plaridel-Tigman-Caburian Rd | C30: =SUM(E30:I30) -> 4.53 | D30: ='[23]road inventory 2018'!C32 -> 5.2 | E30: 0 | F30: 0 | G30: 0 | H30: 4.53 | I30: 0 | J30: Fair | K30: km sta.76+500
A31: 20 | B31: Aporawan-Daan-Cabigaan Road | C31: =SUM(E31:I31) -> 7.63 | D31: ='[23]road inventory 2018'!C33 -> 7.6 | E31: 0 | F31: 0 | G31: 0 | H31: 7.63 | I31: 0 | J31: Bad
C32: =SUM(C8:C31) -> 95.39 | D32: =SUM(D8:D31) -> 98.55 | E32: =SUM(E8:E31) -> 45.43 | F32: =SUM(F8:F31) -> 0 | G32: =SUM(G8:G31) -> 0 | H32: =SUM(H8:H31) -> 49.96 | I32: =SUM(I8:I31) -> 0
A33: SUB-TOTAL | C33: =E33+F33+G33+H33+I33 -> 95.39 | E33: =SUM(E8:E31) -> 45.43 | F33: =SUM(F8:F31) -> 0 | G33: =SUM(G8:G31) -> 0 | H33: =SUM(H8:H31) -> 49.96 | I33: =SUM(I8:I31) -> 0
A35: MUNICIPALITY OF NARRA
A37: ROAD ID | B37: ROAD NAME | C37: LENGTH (km/s.) | E37: SURFACE TYPE | J37: ROAD CONDITION | K37: KILOMETER POST | L37: REMARKS
E38: CONCRETE | F38: ASPHALT | G38: EARTH | H38: GRAVEL | I38: MIXED
A39: 21 | B39: Sandoval Feeder Road | C39: =SUM(E39:I39) -> 4.32 | D39: ='[23]road inventory 2018'!C41 -> 4.3 | E39: 4.11 | F39: 0 | G39: 0 | H39: 0.21 | I39: 0 | J39: Good | K39: km sta.79+500
A40: 22 | B40: Apo-Aporawan Section Road | C40: =SUM(E40:I40) -> 4.01 | D40: ='[23]road inventory 2018'!C42 -> 3.9 | E40: 0 | F40: 0 | G40: 0 | H40: 4.01 | I40: 0 | J40: Fair | K40: km sta.80+770
A41: 23 | B41: Malatgao - Babanitan Road | C41: =SUM(E41:I41) -> 4.42 | D41: ='[23]road inventory 2018'!C43 -> 4.3 | E41: 2.9 | F41: 0 | G41: 0 | H41: 1.52 | I41: 0 | J41: Fair | K41: km sta.83+580
A42: 24 | B42: Malatgao Section Road | C42: =SUM(E42:I42) -> 8.25 | D42: ='[23]road inventory 2018'!C44 -> 7.5 | E42: 8.25 | F42: 0 | G42: 0 | H42: 0 | I42: 0 | J42: Good | K42: km sta.83+580
A43: 25 | B43: Taritien Sea Road | C43: =SUM(E43:I43) -> 0.88 | D43: ='[23]road inventory 2018'!C45 -> 1.7 | E43: 0 | F43: 0 | G43: 0 | H43: 0.88 | I43: 0 | J43: Fair | K43: km sta.85+500 | L43: NOT ACCESSIBLE
A44: 26 | B44: Taritien Section Road | C44: =SUM(E44:I44) -> 6.06 | D44: ='[23]road inventory 2018'!C46 -> 5.9 | E44: 2.85 | F44: 0 | G44: 0 | H44: 3.21 | I44: 0 | J44: Fair | K44: km sta.85+500
A45: 27 | B45: Antipuluan Sea Road | C45: =SUM(E45:I45) -> 1.93 | D45: ='[23]road inventory 2018'!C47 -> 1.9 | E45: 0.28 | F45: 0 | G45: 0 | H45: 1.65 | I45: 0 | J45: Fair | K45: km sta.88+045
A46: 28 | B46: Lapu-Lapu Section Road | C46: =SUM(E46:I46) -> 5.62 | D46: ='[23]road inventory 2018'!C48 -> 5.6 | E46: 1.54 | F46: 0 | G46: 0 | H46: 4.08 | I46: 0 | J46: Good | K46: km sta.91+160
A47: 29 | B47: Narra School Road | C47: =SUM(E47:I47) -> 0.86 | D47: ='[23]road inventory 2018'!C49 -> 0.8 | E47: 0.11 | F47: 0 | G47: 0 | H47: 0.75 | I47: 0 | J47: Fair | K47: km sta.92+250
A48: 30 | B48: Rizal Avenue Section Road | C48: =SUM(E48:I48) -> 2 | D48: ='[23]road inventory 2018'!C50 -> 2 | E48: 1.5 | F48: 0 | G48: 0 | H48: 0.5 | I48: 0 | J48: Good | K48: km sta.91+670 | L48: MUNICIPAL ROAD
A49: 106 | B49: Narra Panacan Road | C49: =SUM(E49:I49) -> 3.21 | D49: ='[23]road inventory 2018'!C51 -> 3.2 | E49: 3.21 | F49: 0 | G49: 0 | H49: 0 | I49: 0 | J49: Good | K49: km sta.92+370
A50: 31 | B50: Ipil Road / Quirino | C50: =SUM(E50:I50) -> 0.78 | D50: ='[23]road inventory 2018'!C52 -> 0.8 | E50: 0.78 | F50: 0 | G50: 0 | H50: 0 | I50: 0 | J50: Good | K50: km sta.92+700
A51: 32 | B51: Guminubat Section Road | C51: =SUM(E51:I51) -> 3.01 | D51: ='[23]road inventory 2018'!C53 -> 3 | E51: 0 | F51: 0 | G51: 0 | H51: 3.01 | I51: 0 | J51: Bad | K51: km sta.94+650
A52: 33 | B52: Malinao Feeder Road | C52: =SUM(E52:I52) -> 2.4 | D52: ='[23]road inventory 2018'!C54 -> 2.4 | E52: 0.25 | F52: 0 | G52: 0 | H52: 2.15 | I52: 0 | J52: Poor | K52: km sta.96+850
A53: 34 | B53: Linamen Feeder Road | C53: =SUM(E53:I53) -> 4.31 | D53: ='[23]road inventory 2018'!C55 -> 4.2 | E53: 0 | F53: 0 | G53: 0 | H53: 4.31 | I53: 0 | J53: Fair | K53: km sta.100+150
A54: 35 | B54: Caguisan Feeder Road | C54: =SUM(E54:I54) -> 2.97 | D54: ='[23]road inventory 2018'!C56 -> 3 | E54: 0.4 | F54: 0 | G54: 0 | H54: 2.57 | I54: 0 | J54: Fair | K54: km sta.99+200
A55: 36 | B55: Batang-Batang Feeder Road | C55: =SUM(E55:I55) -> 6.01 | D55: ='[23]road inventory 2018'!C57 -> 6.2 | E55: 0 | F55: 0 | G55: 0 | H55: 6.01 | I55: 0 | J55: Fair | K55: km sta.101+950
A56: 37 | B56: Linamen - Batang-Batang Feeder Road | C56: =SUM(E56:I56) -> 1.6 | D56: ='[23]road inventory 2018'!C58 -> 1.6 | E56: 0 | F56: 0 | G56: 0 | H56: 1.6 | I56: 0 | J56: Fair | K56: km sta.101+960
A57: 38 | B57: Teresa - Batang-Batang Road | C57: =SUM(E57:I57) -> 3.9 | D57: ='[23]road inventory 2018'!C59 -> 4.4 | E57: 0 | F57: 0 | G57: 0 | H57: 3.9 | I57: 0 | J57: Fair | K57: km sta.105+550
A58: 39 | B58: Teresa Feeder Road | C58: =SUM(E58:I58) -> 4.94 | D58: ='[23]road inventory 2018'!C60 -> 4.9 | E58: 0 | F58: 0 | G58: 0 | H58: 4.94 | I58: 0 | J58: Fair | K58: km sta.104+100
A59: 105 | B59: Bato-Bato Feeder Road | C59: =SUM(E59:I59) -> 3.65 | D59: ='[23]road inventory 2018'!C61 -> 3.6 | E59: 0 | F59: 0 | G59: 0 | H59: 3.65 | I59: 0 | J59: Fair | K59: km sta.105+950
A60: 40 | B60: Calategas Sea Road | C60: =SUM(E60:I60) -> 1.55 | D60: ='[23]road inventory 2018'!C62 -> 1.5 | E60: 1.22 | F60: 0 | G60: 0 | H60: 0.33 | I60: 0 | J60: Poor | K60: km sta.115+010
... A62: 42 | B62: Aramaywan Sea Road | C62: =SUM(E62:I62) -> 1.5 | D62: ='[23]road inventory 2018'!C64 -> 1.5 | E62: 0 | F62: 0 | G62: 0 | H62: 1.5 | I62: 0 | J62: Fair | K62: km sta.120+300
A63: 43 | B63: Aramaywan Parangue Road | C63: =SUM(E63:I63) -> 8.37 | D63: ='[23]road inventory 2018'!C65 -> 12.7 | E63: 0.16 | F63: 0 | G63: 0 | H63: 8.21 | I63: 0 | J63: Bad | K63: km sta.120+750 | L63: NOT ACCESSIBLE
A64: 44 | B64: Burirao - Cabudlungan Road | C64: =SUM(E64:I64) -> 5.52 | D64: ='[23]road inventory 2018'!C66 -> 5.3 | E64: 0 | F64: 0 | G64: 0 | H64: 5.52 | I64: 0 | J64: Bad | K64: km sta.124+800
A65: 104 | B65: Sandoval - Bagong Sikat Road | C65: =SUM(E65:I65) -> 3.13 | D65: ='[23]road inventory 2018'!C67 -> 3.1 | E65: 0 | F65: 0 | G65: 0 | H65: 3.13 | I65: 0 | J65: Fair | K65: km sta.81+500
C66: =SUM(C39:C65) -> 98.01 | D66: =SUM(D39:D65) -> 102.1 | E66: =SUM(E39:E65) -> 27.56 | F66: =SUM(F39:F65) -> 0 | G66: =SUM(G39:G65) -> 0 | H66: =SUM(H39:H65) -> 70.45 | I66: =SUM(I39:I65) -> 0
A67: SUB-TOTAL | C67: =SUM(E67:I67) -> 98.01 | E67: =SUM(E39:E65) -> 27.56 | F67: =SUM(F39:F65) -> 0 | G67: =SUM(G39:G65) -> 0 | H67: =SUM(H39:H65) -> 70.45 | I67: =SUM(I39:I65) -> 0
A68: MUNICIPALITY OF QUEZON
A70: ROAD ID | B70: ROAD NAME | C70: LENGTH (km/s.) | E70: SURFACE TYPE | J70: ROAD CONDITION | K70: KILOMETER POST | L70: REMARKS
E71: CONCRETE | F71: ASPHALT | G71: EARTH | H71: GRAVEL | I71: MIXED
A72: 107 | B72: Tabon - Pinaglabanan Road | C72: =SUM(E72:I72) -> 2.59 | D72: ='[23]road inventory 2018'!C73 -> 2.5 | E72: 1.07 | F72: 0 | G72: 0 | H72: 1.52 | I72: 0 | J72: Fair | K72: km sta.139+300
A73: 102 | B73: Tabon - Tagpapasi Road | C73: =SUM(E73:I73) -> 1.33 | D73: ='[23]road inventory 2018'!C74 -> 1.3 | E73: 0 | F73: 0 | G73: 0 | H73: 1.33 | I73: 0 | J73: Fair | K73: km sta.143+700
A74: 101 | B74: Magsaysay Road | C74: =SUM(E74:I74) -> 0 | D74: ='[23]road inventory 2018'!C75 -> 0.6 | E74: 0 | F74: 0 | G74: 0 | H74: 0 | I74: 0 | J74: Good | K74: km sta.146+000 | L74: MUNICIPAL ROAD
A75: 47 | B75: Abo-Abo - Isugod Road | C75: =SUM(E75:I75) -> 17.2 | D75: ='[23]road inventory 2018'!C76 -> 17 | E75: 0.27 | F75: 0 | G75: 0 | H75: 16.93 | I75: 0 | J75: Fair | K75: km sta.156+500
A76: 48 | B76: Maasin - Marintub Road | C76: =SUM(E76:I76) -> 2.63 | D76: ='[23]road inventory 2018'!C77 -> 2.6 | E76: 0 | F76: 0 | G76: 0 | H76: 2.63 | I76: 0 | J76: Fair | K76: km sta.157+800
A77: 90 | B77: Malatgao Road | C77: =SUM(E77:I77) -> 4.27 | D77: ='[23]road inventory 2018'!C78 -> 4.35 | E77: 0 | F77: 0 | G77: 0 | H77: 4.27 | I77: 0 | J77: Fair | K77: km sta.134+500
A78: 99 | B78: Panitian - Tabud Road | C78: =SUM(E78:I78) -> 14.14 | D78: ='[23]road inventory 2018'!C79 -> 14.1 | E78: 0 | F78: 0 | G78: 0 | H78: 14.14 | I78: 0 | J78: Poor | K78: km sta.151+000
C79: =SUM(C72:C78) -> 42.16 | D79: =SUM(D72:D78) -> 42.45 | E79: =SUM(E72:E78) -> 1.34 | F79: =SUM(F72:F78) -> 0 | G79: =SUM(G72:G78) -> 0 | H79: =SUM(H72:H78) -> 40.82
A80: SUB-TOTAL | C80: =SUM(E80:I80) -> 42.16 | E80: =SUM(E72:E78) -> 1.34 | F80: =SUM(F72:F78) -> 0 | G80: =SUM(G72:G78) -> 0 | H80: =SUM(H72:H78) -> 40.82 | I80: =SUM(I72:I78) -> 0
A82: MUNICIPALITY OF RIZAL
A84: ROAD ID | B84: ROAD NAME | C84: LENGTH (km/s.) | E84: SURFACE TYPE | J84: ROAD CONDITION | K84: KILOMETER POST | L84: REMARKS
E85: CONCRETE | F85: ASPHALT | G85: EARTH | H85: GRAVEL | I85: MIXED
A86: 108 | B86: Rancho - Puntabaja - Malapandeg Road | C86: =E86+F86+G86+H86+I86 -> 3.28 | D86: ='[23]road inventory 2018'!C86 -> 3.1 | E86: 0.48 | F86: 0 | G86: 0 | H86: 2.8 | I86: 0 | J86: Fair | K86: km sta.198+000
A87: SUB-TOTAL | C87: =SUM(C86:C86) -> 3.28 | E87: =SUM(E86:E86) -> 0.48 | F87: =SUM(F86:F86) -> 0 | G87: =SUM(G86:G86) -> 0 | H87: =SUM(H86:H86) -> 2.8 | I87: =SUM(I86:I86) -> 0
A89: MUNICIPALITY OF SOFRONIO ESPAÑOLA
A91: ROAD ID | B91: ROAD NAME | C91: LENGTH (km/s.) | E91: SURFACE TYPE | J91: ROAD CONDITION | K91: KILOMETER POST | L91: REMARKS
E92: CONCRETE | F92: ASPHALT | G92: EARTH | H92: GRAVEL | I92: MIXED
A93: 223 | B93: Panitian Seashore Road | C93: =SUM(E93:I93) -> 4.18 | D93: ='[23]road inventory 2018'!C93 -> 4.1 | E93: 0 | F93: 0 | G93: 0 | H93: 4.18 | I93: 0 | J93: Poor | K93: km sta.137+000
A94: 224 | B94: Panitian - Abokayan Road | C94: =SUM(E94:I94) -> 7.24 | D94: ='[23]road inventory 2018'!C94 -> 7.2 | E94: 1.02 | F94: 0 | G94: 0 | H94: 6.22 | I94: 0 | J94: Fair | K94: km sta.137+900
A95: 45 | B95: Labog Naltep Road | C95: =SUM(E95:I95) -> 7.44 | D95: ='[23]road inventory 2018'!C95 -> 7.9 | E95: 0.71 | F95: 0 | G95: 0 | H95: 6.73 | I95: 0 | J95: Poor | K95: km sta.143+800
A96: 217 | B96: Punang Plain Road | C96: =SUM(E96:I96) -> 1.14 | D96: ='[23]road inventory 2018'!C96 -> 1.1 | E96: 1.14 | F96: 0 | G96: 0 | H96: 0 | I96: 0 | J96: Good | K96: km sta.149+200
A97: 225 | B97: Iraray School Road | C97: =SUM(E97:I97) -> 0.36 | D97: ='[23]road inventory 2018'!C97 -> 0.4 | E97: 0 | F97: 0 | G97: 0 | H97: 0.36 | I97: 0 | J97: Good | K97: km sta.155+700
A98: 226 | B98: Pulot Sea Road | C98: =SUM(E98:I98) -> 4.01 | D98: ='[23]road inventory 2018'!C98 -> 4.8 | E98: 0.86 | F98: 0 | G98: 0 | H98: 3.15 | I98: 0 | J98: Good | K98: km sta.162+800
A99: 116 | B99: Pulot I - Pulot III Road | C99: =SUM(E99:I99) -> 12.3 | D99: ='[23]road inventory 2018'!C99 -> 12.3 | E99: 6.67 | F99: 0 | G99: 0 | H99: 5.63 | I99: 0 | J99: Fair | K99: km sta.162+800
A100: 46 | B100: Pulot Bo. High School Road | C100: =SUM(E100:I100) -> 1.3 | D100: ='[23]road inventory 2018'!C100 -> 1.3 | E100: 1.3 | F100: 0 | G100: 0 | H100: 0 | I100: 0 | J100: Good | K100: km sta.163+800
A101: 227 | B101: Caramay Bulho Road | C101: =SUM(E101:I101) -> 7.43 | D101: ='[23]road inventory 2018'!C101 -> 7.2 | E101: 0 | F101: 0 | G101: 0 | H101: 7.43 | I101: 0 | J101: Poor | K101: km sta.165+600
A102: 100 | B102: Pulot III-Tabud Road | C102: =SUM(E102:I102) -> 7.8 | D102: ='[23]road inventory 2018'!C102 -> 7.8 | E102: 0.3 | F102: 0 | G102: 0 | H102: 7.5 | I102: 0 | J102: Bad | K102: km sta.177+000
C103: =SUM(C93:C102) -> 53.2 | D103: =SUM(D93:D102) -> 54.1 | E103: =SUM(E93:E102) -> 12 | F103: =SUM(F93:F102) -> 0 | G103: =SUM(G93:G102) -> 0 | H103: =SUM(H93:H102) -> 41.2
A104: SUB-TOTAL | C104: =E104+H104 -> 53.2 | E104: =SUM(E93:E102) -> 12 | F104: =SUM(F93:F102) -> 0 | G104: =SUM(G93:G102) -> 0 | H104: =SUM(H93:H102) -> 41.2 | I104: =SUM(I93:I102) -> 0
A106: MUNICIPALITY OF BROOKE'S POINT
A108: ROAD ID | B108: ROAD NAME | C108: LENGTH (km/s.) | E108: SURFACE TYPE | J108: ROAD CONDITION | K108: KILOMETER POST | L108: REMARKS
E109: CONCRETE | F109: ASPHALT | G109: EARTH | H109: GRAVEL | I109: MIXED
A110: 48 | B110: Maasin Airport Road | C110: =SUM(E110:I110) -> 2.19 | D110: ='[23]road inventory 2018'!C109 -> 2.1 | E110: 0 | F110: 0 | G110: 0 | H110: 2.19 | I110: 0 | J110: Fair | K110: km sta.113+100
A111: 50 | B111: Maasin Rancho Road | C111: =SUM(E111:I111) -> 7.69 | D111: ='[23]road inventory 2018'!C110 -> 7.6 | E111: 1.79 | F111: 0 | G111: 0 | H111: 5.9 | I111: 0 | J111: Fair | K111: km sta.174+800-
...

Sheet GOOD TO FAIR2019
A1: PROVINCIAL ENGINEER'S OFFICE
A2: PROVINCIAL ROAD NETWORK AND ITS STATUS / CONDITION
A3: 2019
A6: MUNICIPALITY OF ABORLAN | M6: ISLANDS
M7: =C144+C239+C252+C277+C289+C300 -> 193.498
A8: ROAD ID | B8: ROAD NAME | C8: REVISED LENGTH (km/s.) | D8: OLD LENGTH | E8: SURFACE TYPE | J8: ROAD CONDITION | K8: KILOMETER POST | L8: REMARKS
E9: CONCRETE | F9: ASPHALT | G9: EARTH | H9: GRAVEL | I9: MIXED | M9: =(#REF!/#REF!)*100 -> #REF!
A10: 219 | B10: Junction - Isaub Road | C10: =SUM(E10:I10) -> 0.4 | D10: ='[23]road inventory 2018'!C10 -> 0.65 | E10: 0 | F10: 0 | G10: 0 | H10: 0.4 | I10: 0 | J10: Fair | K10: km sta.57+800
A11: 1 | B11: Sagpangan Road | C11: =SUM(E11:I11) -> 5.48 | D11: ='[23]road inventory 2018'!C11 -> 5.5 | E11: 2.87 | F11: 0 | G11: 0 | H11: 2.61 | I11: 0 | J11: Fair | K11: km sta.66+400 | M11: =D144+D227+D239+D252+D277+D289+D300+C306 -> 216.613
A12: 2 | B12: Isaub - Marikit -Tubig Road | C12: =SUM(E12:I12) -> 0.92 | D12: ='[23]road inventory 2018'!C12 -> 0.8 | E12: 0.07 | F12: 0 | G12: 0 | H12: 0.85 | I12: 0 | J12: Good | K12: km sta.58+000
A13: 3 | B13: Mailigan - Sagpangan Road | C13: =SUM(E13:I13) -> 4.97 | D13: ='[23]road inventory 2018'!C13 -> 4.9 | E13: 0 | F13: 0 | G13: 0 | H13: 4.97 | I13: 0 | J13: Fair | K13: km sta.62+400
A14: 93 | B14: Iraan - Baraki Road | C14: =SUM(E14:I14) -> 3.9 | D14: ='[23]road inventory 2018'!C15 -> 3.9 | E14: 3.9 | F14: 0 | G14: 0 | H14: 0 | I14: 0 | J14: =#REF! -> #REF! | K14: km sta.64+900
A15: 218 | B15: Isaub - Sagpangan Road | C15: =SUM(E15:I15) -> 5.61 | D15: ='[23]road inventory 2018'!C16 -> 5.8 | E15: 0 | F15: 0 | G15: 0 | H15: 5.61 | I15: 0 | J15: Fair | K15: km sta.58+000
A16: 5 | B16: PNAC Road | C16: =SUM(E16:I16) -> 2.85 | D16: ='[23]road inventory 2018'!C17 -> 2.8 | E16: 2.85 | F16: 0 | G16: 0 | H16: 0 | I16: 0 | J16: Good | K16: km sta.64+900
A17: 6 | B17: San Juan Road | C17: =SUM(E17:I17) -> 3.96 | D17: ='[23]road inventory 2018'!C18 -> 3.9 | E17: 2.7 | F17: 0 | G17: 0 | H17: 1.26 | I17: 0 | J17: Good | K17: km sta.66+400
A18: 7 | B18: Aborlan - River Landing | C18: =SUM(E18:I18) -> 1.15 | D18: ='[23]road inventory 2018'!C19 -> 1.1 | E18: 1.15 | F18: 0 | G18: 0 | H18: 0 | I18: 0 | J18: Good | K18: km sta.67+100
A19: 8 | B19: Aborlan Poblacion Road | C19: =SUM(E19:I19) -> 0.64 | D19: ='[23]road inventory 2018'!C20 -> 0.6 | E19: 0.64 | F19: 0 | G19: 0 | H19: 0 | I19: 0 | J19: Good | K19: km sta.66+950
A20: 9 | B20: Magbabadil - Cabigaan Road | C20: =SUM(E20:I20) -> 9.3 | D20: ='[23]road inventory 2018'!C21 -> 9 | E20: 9.3 | F20: 0 | G20: 0 | H20: 0 | I20: 0 | J20: Good | K20: km sta.66+800
A21: 10 | B21: Plaridel - Apis Cabigaan Road | C21: =SUM(E21:I21) -> 13.79 | D21: ='[23]road inventory 2018'!C22 -> 13.6 | E21: 8.79 | F21: 0 | G21: 0 | H21: 5 | I21: 0 | J21: =J20 -> Good | K21: km sta.75+650
A22: 11 | B22: Tagpait Feeder Road | C22: =SUM(E22:I22) -> 2.27 | D22: ='[23]road inventory 2018'!C23 -> 2.2 | E22: 0.21 | F22: 0 | G22: 0 | H22: 2.06 | I22: 0 | J22: Fair | K22: km sta.69+000
A23: 13 | B23: New Bantayan - Apis Road | C23: =SUM(E23:I23) -> 1.72 | D23: ='[23]road inventory 2018'!C24 -> 1.7 | E23: 0 | F23: 0 | G23: 0 | H23: 1.72 | I23: 0 | J23: Fair | K23: km sta.69+200
A24: 14 | B24: Junction - Tigman Road | C24: =SUM(E24:I24) -> 4.12 | D24: ='[23]road inventory 2018'!C27 -> 4 | E24: 4.12 | F24: 0 | G24: 0 | H24: 0 | I24: 0 | J24: Good | K24: km sta.75+650
A25: 16 | B25: Tigman - Caburian Road | C25: =SUM(E25:I25) -> 1.05 | D25: ='[23]road inventory 2018'!C29 -> 1 | E25: 0 | F25: 0 | G25: 0 | H25: 1.05 | I25: 0 | J25: Fair | K25: km sta.78+150
A26: 17 | B26: Magbabadil - Baraki Road | C26: =SUM(E26:I26) -> 4.18 | D26: ='[23]road inventory 2018'!C30 -> 4 | E26: 4.18 | F26: 0 | G26: 0 | H26: 0 | I26: 0 | J26: Fair | K26: km sta.73+400
A27: 18 | B27: Tigman - Rizal - Dumangueña Road | C27: =SUM(E27:I27) -> 10.52 | D27: ='[23]road inventory 2018'!C31 -> 10.5 | E27: 4.54 | F27: 0 | G27: 0 | H27: 5.98 | I27: 0 | J27: Fair | K27: km sta.77+400
A28: 221 | B28: Hi-way Jct. Plaridel-Tigman-Caburian Rd | C28: =SUM(E28:I28) -> 4.53 | D28: ='[23]road inventory 2018'!C32 -> 5.2 | E28: 0 | F28: 0 | G28: 0 | H28: 4.53 | I28: 0 | J28: Fair | K28: km sta.76+500
C29: =SUM(C10:C28) -> 81.36 | D29: =SUM(D10:D28) -> 81.15 | E29: =SUM(E10:E28) -> 45.32 | F29: =SUM(F10:F28) -> 0 | G29: =SUM(G10:G28) -> 0 | H29: =SUM(H10:H28) -> 36.04 | I29: =SUM(I10:I28) -> 0
A30: SUB-TOTAL | C30: =E30+F30+G30+H30+I30 -> 81.36 | E30: =SUM(E10:E28) -> 45.32 | F30: =SUM(F10:F28) -> 0 | G30: =SUM(G10:G28) -> 0 | H30: =SUM(H10:H28) -> 36.04 | I30: =SUM(I10:I28) -> 0
A32: MUNICIPALITY OF NARRA
A34: ROAD ID | B34: ROAD NAME | C34: LENGTH (km/s.) | E34: SURFACE TYPE | J34: ROAD CONDITION | K34: KILOMETER POST | L34: REMARKS
E35: CONCRETE | F35: ASPHALT | G35: EARTH | H35: GRAVEL | I35: MIXED
A36: 21 | B36: Sandoval Feeder Road | C36: =SUM(E36:I36) -> 4.32 | D36: ='[23]road inventory 2018'!C41 -> 4.3 | E36: 4.11 | F36: 0 | G36: 0 | H36: 0.21 | I36: 0 | J36: Good | K36: km sta.79+500
A37: 22 | B37: Apo-Aporawan Section Road | C37: =SUM(E37:I37) -> 4.01 | D37: ='[23]road inventory 2018'!C42 -> 3.9 | E37: 0 | F37: 0 | G37: 0 | H37: 4.01 | I37: 0 | J37: Fair | K37: km sta.80+770
A38: 23 | B38: Malatgao - Babanitan Road | C38: =SUM(E38:I38) -> 4.42 | D38: ='[23]road inventory 2018'!C43 -> 4.3 | E38: 2.9 | F38: 0 | G38: 0 | H38: 1.52 | I38: 0 | J38: Fair | K38: km sta.83+580
A39: 24 | B39: Malatgao Section Road | C39: =SUM(E39:I39) -> 8.25 | D39: ='[23]road inventory 2018'!C44 -> 7.5 | E39: 8.25 | F39: 0 | G39: 0 | H39: 0 | I39: 0 | J39: Good | K39: km sta.83+580
A40: 25 | B40: Taritien Sea Road | C40: =SUM(E40:I40) -> 0.88 | D40: ='[23]road inventory 2018'!C45 -> 1.7 | E40: 0 | F40: 0 | G40: 0 | H40: 0.88 | I40: 0 | J40: Fair | K40: km sta.85+500 | L40: NOT ACCESSIBLE
A41: 26 | B41: Taritien Section Road | C41: =SUM(E41:I41) -> 6.06 | D41: ='[23]road inventory 2018'!C46 -> 5.9 | E41: 2.85 | F41: 0 | G41: 0 | H41: 3.21 | I41: 0 | J41: Fair | K41: km sta.85+500
A42: 27 | B42: Antipuluan Sea Road | C42: =SUM(E42:I42) -> 1.93 | D42: ='[23]road inventory 2018'!C47 -> 1.9 | E42: 0.28 | F42: 0 | G42: 0 | H42: 1.65 | I42: 0 | J42: Fair | K42: km sta.88+045
A43: 28 | B43: Lapu-Lapu Section Road | C43: =SUM(E43:I43) -> 5.62 | D43: ='[23]road inventory 2018'!C48 -> 5.6 | E43: 1.54 | F43: 0 | G43: 0 | H43: 4.08 | I43: 0 | J43: Good | K43: km sta.91+160
A44: 29 | B44: Narra School Road | C44: =SUM(E44:I44) -> 0.86 | D44: ='[23]road inventory 2018'!C49 -> 0.8 | E44: 0.11 | F44: 0 | G44: 0 | H44: 0.75 | I44: 0 | J44: Fair | K44: km sta.92+250
A45: 30 | B45: Rizal Avenue Section Road | C45: =SUM(E45:I45) -> 2 | D45: ='[23]road inventory 2018'!C50 -> 2 | E45: 1.5 | F45: 0 | G45: 0 | H45: 0.5 | I45: 0 | J45: Good | K45: km sta.91+670 | L45: MUNICIPAL ROAD
A46: 106 | B46: Narra Panacan Road | C46: =SUM(E46:I46) -> 3.21 | D46: ='[23]road inventory 2018'!C51 -> 3.2 | E46: 3.21 | F46: 0 | G46: 0 | H46: 0 | I46: 0 | J46: Good | K46: km sta.92+370
A47: 31 | B47: Ipil Road / Quirino | C47: =SUM(E47:I47) -> 0.78 | D47: ='[23]road inventory 2018'!C52 -> 0.8 | E47: 0.78 | F47: 0 | G47: 0 | H47: 0 | I47: 0 | J47: Good | K47: km sta.92+700
A48: 34 | B48: Linamen Feeder Road | C48: =SUM(E48:I48) -> 4.31 | D48: ='[23]road inventory 2018'!C55 -> 4.2 | E48: 0 | F48: 0 | G48: 0 | H48: 4.31 | I48: 0 | J48: Fair | K48: km sta.100+150
A49: 35 | B49: Caguisan Feeder Road | C49: =SUM(E49:I49) -> 2.97 | D49: ='[23]road inventory 2018'!C56 -> 3 | E49: 0.4 | F49: 0 | G49: 0 | H49: 2.57 | I49: 0 | J49: Fair | K49: km sta.99+200
A50: 36 | B50: Batang-Batang Feeder Road | C50: =SUM(E50:I50) -> 6.01 | D50: ='[23]road inventory 2018'!C57 -> 6.2 | E50: 0 | F50: 0 | G50: 0 | H50: 6.01 | I50: 0 | J50: Fair | K50: km sta.101+950
A51: 37 | B51: Linamen - Batang-Batang Feeder Road | C51: =SUM(E51:I51) -> 1.6 | D51: ='[23]road inventory 2018'!C58 -> 1.6 | E51: 0 | F51: 0 | G51: 0 | H51: 1.6 | I51: 0 | J51: Fair | K51: km sta.101+960
A52: 38 | B52: Teresa - Batang-Batang Road | C52: =SUM(E52:I52) -> 3.9 | D52: ='[23]road inventory 2018'!C59 -> 4.4 | E52: 0 | F52: 0 | G52: 0 | H52: 3.9 | I52: 0 | J52: Fair | K52: km sta.105+550
A53: 39 | B53: Teresa Feeder Road | C53: =SUM(E53:I53) -> 4.94 | D53: ='[23]road inventory 2018'!C60 -> 4.9 | E53: 0 | F53: 0 | G53: 0 | H53: 4.94 | I53: 0 | J53: Fair | K53: km sta.104+100
A54: 105 | B54: Bato-Bato Feeder Road | C54: =SUM(E54:I54) -> 3.65 | D54: ='[23]road inventory 2018'!C61 -> 3.6 | E54: 0 | F54: 0 | G54: 0 | H54: 3.65 | I54: 0 | J54: Fair | K54: km sta.105+950
A55: 42 | B55: Aramaywan Sea Road | C55: =SUM(E55:I55) -> 1.5 | D55: ='[23]road inventory 2018'!C64 -> 1.5 | E55: 0 | F55: 0 | G55: 0 | H55: 1.5 | I55: 0 | J55: Fair | K55: km sta.120+300
A56: 104 | B56: Sandoval - Bagong Sikat Road | C56: =SUM(E56:I56) -> 3.13 | D56: ='[23]road inventory 2018'!C67 -> 3.1 | E56: 0 | F56: 0 | G56: 0 | H56: 3.13 | I56: 0 | J56: Fair | K56: km sta.81+500
C57: =SUM(C36:C56) -> 74.35 | D57: =SUM(D36:D56) -> 74.4 | E57: =SUM(E36:E56) -> 25.93 | F57: =SUM(F36:F56) -> 0 | G57: =SUM(G36:G56) -> 0 | H57: =SUM(H36:H56) -> 48.42 | I57: =SUM(I36:I56) -> 0
A58: SUB-TOTAL | C58: =SUM(E58:I58) -> 74.35 | E58: =SUM(E36:E56) -> 25.93 | F58: =SUM(F36:F56) -> 0 | G58: =SUM(G36:G56) -> 0 | H58: =SUM(H36:H56) -> 48.42 | I58: =SUM(I36:I56) -> 0
A59: MUNICIPALITY OF QUEZON
A61: ROAD ID | B61: ROAD NAME | C61: LENGTH (km/s.) | E61: SURFACE TYPE | J61: ROAD CONDITION | K61: KILOMETER POST | L61: REMARKS
E62: CONCRETE | F62: ASPHALT | G62: EARTH | H62: GRAVEL | I62: MIXED
A63: 107 | B63: Tabon - Pinaglabanan Road | C63: =SUM(E63:I63) -> 2.59 | D63: ='[23]road inventory 2018'!C73 -> 2.5 | E63: 1.07 | F63: 0 | G63: 0 | H63: 1.52 | I63: 0 | J63: Fair | K63: km sta.139+300
A64: 102 | B64: Tabon - Tagpapasi Road | C64: =SUM(E64:I64) -> 1.33 | D64: ='[23]road inventory 2018'!C74 -> 1.3 | E64: 0 | F64: 0 | G64: 0 | H64: 1.33 | I64: 0 | J64: Fair | K64: km sta.143+700
A65: 101 | B65: Magsaysay Road | C65: =SUM(E65:I65) -> 0 | D65: ='[23]road inventory 2018'!C75 -> 0.6 | E65: 0 | F65: 0 | G65: 0 | H65: 0 | I65: 0 | J65: Good | K65: km sta.146+000 | L65: MUNICIPAL ROAD
A66: 47 | B66: Abo-Abo - Isugod Road | C66: =SUM(E66:I66) -> 17.2 | D66: ='[23]road inventory 2018'!C76 -> 17 | E66: 0.27 | F66: 0 | G66: 0 | H66: 16.93 | I66: 0 | J66: Fair | K66: km sta.156+500
A67: 48 | B67: Maasin - Marintub Road | C67: =SUM(E67:I67) -> 2.63 | D67: ='[23]road inventory 2018'!C77 -> 2.6 | E67: 0 | F67: 0 | G67: 0 | H67: 2.63 | I67: 0 | J67: Fair | K67: km sta.157+800
A68: 90 | B68: Malatgao Road | C68: =SUM(E68:I68) -> 4.27 | D68: ='[23]road inventory 2018'!C78 -> 4.35 | E68: 0 | F68: 0 | G68: 0 | H68: 4.27 | I68: 0 | J68: Fair | K68: km sta.134+500
C69: =SUM(C63:C68) -> 28.02 | D69: =SUM(D63:D68) -> 28.35 | E69: =SUM(E63:E68) -> 1.34 | F69: =SUM(F63:F68) -> 0 | G69: =SUM(G63:G68) -> 0 | H69: =SUM(H63:H68) -> 26.68
A70: SUB-TOTAL | C70: =SUM(E70:I70) -> 28.02 | E70: =SUM(E63:E68) -> 1.34 | F70: =SUM(F63:F68) -> 0 | G70: =SUM(G63:G68) -> 0 | H70: =SUM(H63:H68) -> 26.68 | I70: =SUM(I63:I68) -> 0
A72: MUNICIPALITY OF RIZAL
A74: ROAD ID | B74: ROAD NAME | C74: LENGTH (km/s.) | E74: SURFACE TYPE | J74: ROAD CONDITION | K74: KILOMETER POST | L74: REMARKS
E75: CONCRETE | F75: ASPHALT | G75: EARTH | H75: GRAVEL | I75: MIXED
A76: 108 | B76: Rancho - Puntabaja - Malapandeg Road | C76: =SUM(E76:I76) -> 3.28 | D76: ='[23]road inventory 2018'!C86 -> 3.1 | E76: 0.48 | F76: 0 | G76: 0 | H76: 2.8 | I76: 0 | J76: Fair | K76: km sta.198+000
A77: SUB-TOTAL | C77: =SUM(C76:C76) -> 3.28 | E77: =SUM(E76:E76) -> 0.48 | F77: =SUM(F76:F76) -> 0 | G77: =SUM(G76:G76) -> 0 | H77: =SUM(H76:H76) -> 2.8 | I77: =SUM(I76:I76) -> 0
A79: MUNICIPALITY OF SOFRONIO ESPAÑOLA
A81: ROAD ID | B81: ROAD NAME | C81: LENGTH (km/s.) | E81: SURFACE TYPE | J81: ROAD CONDITION | K81: KILOMETER POST | L81: REMARKS
E82: CONCRETE | F82: ASPHALT | G82: EARTH | H82: GRAVEL | I82: MIXED
A83: 224 | B83: Panitian - Abokayan Road | C83: =SUM(E83:I83) -> 7.24 | D83: ='[23]road inventory 2018'!C94 -> 7.2 | E83: 1.02 | F83: 0 | G83: 0 | H83: 6.22 | I83: 0 | J83: Fair | K83: km sta.137+900
A84: 217 | B84: Punang Plain Road | C84: =SUM(E84:I84) -> 1.14 | D84: ='[23]road inventory 2018'!C96 -> 1.1 | E84: 1.14 | F84: 0 | G84: 0 | H84: 0 | I84: 0 | J84: Good | K84: km sta.149+200
A85: 225 | B85: Iraray School Road | C85: =SUM(E85:I85) -> 0.36 | D85: ='[23]road inventory 2018'!C97 -> 0.4 | E85: 0 | F85: 0 | G85: 0 | H85: 0.36 | I85: 0 | J85: Good | K85: km sta.155+700
A86: 226 | B86: Pulot Sea Road | C86: =SUM(E86:I86) -> 4.01 | D86: ='[23]road inventory 2018'!C98 -> 4.8 | E86: 0.86 | F86: 0 | G86: 0 | H86: 3.15 | I86: 0 | J86: Good | K86: km sta.162+800
A87: 116 | B87: Pulot I - Pulot III Road | C87: =SUM(E87:I87) -> 12.3 | D87: ='[23]road inventory 2018'!C99 -> 12.3 | E87: 6.67 | F87: 0 | G87: 0 | H87: 5.63 | I87: 0 | J87: Fair | K87: km sta.162+800
A88: 46 | B88: Pulot Bo. High School Road | C88: =SUM(E88:I88) -> 1.3 | D88: ='[23]road inventory 2018'!C100 -> 1.3 | E88: 1.3 | F88: 0 | G88: 0 | H88: 0 | I88: 0 | J88: Good | K88: km sta.163+800
C89: =SUM(C83:C88) -> 26.35 | D89: =SUM(D83:D88) -> 27.1 | E89: =SUM(E83:E88) -> 10.99 | F89: =SUM(F83:F88) -> 0 | G89: =SUM(G83:G88) -> 0 | H89: =SUM(H83:H88) -> 15.36
A90: SUB-TOTAL | C90: =E90+H90 -> 26.35 | E90: =SUM(E83:E88) -> 10.99 | F90: =SUM(F83:F88) -> 0 | G90: =SUM(G83:G88) -> 0 | H90: =SUM(H83:H88) -> 15.36 | I90: =SUM(I83:I88) -> 0
A92: MUNICIPALITY OF BROOKE'S POINT
A94: ROAD ID | B94: ROAD NAME | C94: LENGTH (km/s.) | E94: SURFACE TYPE | J94: ROAD CONDITION | K94: KILOMETER POST | L94: REMARKS
E95: CONCRETE | F95: ASPHALT | G95: EARTH | H95: GRAVEL | I95: MIXED
A96: 48 | B96: Maasin Airport Road | C96: =SUM(E96:I96) -> 2.19 | D96: ='[23]road inventory 2018'!C109 -> 2.1 | E96: 0 | F96: 0 | G96: 0 | H96: 2.19 | I96: 0 | J96: Fair | K96: km sta.113+100
A97: 50 | B97: Maasin Rancho Road | C97: =SUM(E97:I97) -> 7.69 | D97: ='[23]road inventory 2018'!C110 -> 7.6 | E97: 1.79 | F97: 0 | G97: 0 | H97: 5.9 | I97: 0 | J97: Fair | K97: km sta.174+800-
A98: 51 | B98: Ipilan Feeder Road | C98: =SUM(E98:I98) -> 3.96 | D98: ='[23]road inventory 2018'!C111 -> 3 | E98: 0 | F98: 0 | G98: 0 | H98: 3.96 | I98: 0 | J98: Fair | K98: km sta.182+050
A99: 52 | B99: Ipilan Rizal Road | C99: =SUM(E99:I99) -> 6.64 | D99: ='[23]road inventory 2018'!C112 -> 6.5 | E99: 0 | F99: 0 | G99: 0 | H99: 6.64 | I99: 0 | J99: Fair | K99: km sta.184+300
A100: 53 | B100: Ipilan Linao Road | C100: =SUM(E100:I100) -> 6.46 | D100: ='[23]road inventory 2018'!C113 -> 6.4 | E100: 5.64 | F100: 0 | G100: 0 | H100: 0.82 | I100: 0 | J100: Fair | K100: km sta.180+150
A101: 54 | B101: Ipilan Sea Road | C101: =SUM(E101:I101) -> 1.69 | D101: ='[23]road inventory 2018'!C114 -> 1.6 | E101: 1.18 | F101: 0 | G101: 0 | H101: 0.51 | I101: 0 | J101: Good | K101: km sta.180+700
A102: 103 | B102: Barong-Barong Feeder Road | C102: =SUM(E102:I102) -> 1.27 | D102: ='[23]road inventory 2018'!C115 -> 1.2 | E102: 0.19 | F102: 0 | G102: 0 | H102: 1.08 | I102: 0 | J102: Good | K102: km sta.182+700
A103: 55 | B103: Barong-Barong Danadio Road | C103: =SUM(E103:I103) -> 4.18 | D103: ='[23]road inventory 2018'!C116 -> 4.1 | E103: 0 | F103: 0 | G103: 0 | H103: 4.18 | I103: 0 | J103: Fair | K103: km sta.183+250
A104: 57 | B104: Tagusao Feeder Road | C104: =SUM(E104:I104) -> 1.36 | D104: ='[23]road inventory 2018'!C117 -> 1.3 | E104: 0.3 | F104: 0 | G104: 0 | H104: 1.06 | I104: 0 | J104: Fair | K104: km sta.183+500
A105: 97 | B105: Aribungos Feeder Road | C105: =SUM(E105:I105) -> 8.45 | D105: ='[23]road inventory 2018'!C120 -> 8.3 | E105: 8.45 | F105: 0 | G105: 0 | H105: 0 | I105: 0 | J105: Good | K105: km sta.186+100
A106: 56 | B106: Ipilan - Mainit Road | C106: =SUM(E106:I106) -> 5.72 | D106: ='[23]road inventory 2018'!C121 -> 5.7 | E106: 1.73 | F106: 0 | G106: 0 | H106: 3.99 | I106: 0 | J106: Fair | K106: km sta.182+050
A107: 60 | B107: Junction Mainit Road | C107: =SUM(E107:I107) -> 9.2 | D107: ='[23]road inventory 2018'!C122 -> 9.2 | E107: 7.1 | F107: 0 | G107: 0 | H107: 2.1 | I107: 0 | J107: Good | K107: km sta.189+95
A108: 61 | B108: Mati Feder Road | C108: =SUM(E108:I108) -> 4.5 | D108: ='[23]road inventory 2018'!C123 -> 4.5 | E108: 1.63 | F108: 0 | G108: 0 | H108: 2.87 | I108: 0 | J108: Good | K108: km sta.192+850
A109: 62 | B109: Tigaplan Feeder Road | C109: =SUM(E109:I109) -> 3.03 | D109: ='[23]road inventory 2018'!C124 -> 2 | E109: 0 | F109: 0 | G109: 0 | H109: 3.03 | I109: 0 | J109: Fair | K109: km sta.186+600
A110: 63 | B110: Suring - Lada Road | C110: =SUM(E110:I110) -> 3.04 | D110: ='[23]road inventory 2018'!C125 -> 3 | E110: 0.11 | F110: 0 | G110: 0 | H110: 2.93 | I110: 0 | J110: Fair | K110: km sta.187+450
A111: 98 | B111: Calasaguen Feeder Road | C111: =SUM(E111:I111) -> 5.18 | D111: ='[23]road inventory 2018'!C126 -> 5.1 | E111: 5.08 | F111: 0 | G111: 0 | H111: 0.1 | I111: 0 | J111: Fair | K111: km sta.168+75
...

Sheet inventory2020(FOR UPDATE)
A1: PROVINCIAL ENGINEER'S OFFICE
A2: PROVINCIAL ROAD NETWORK AND ITS STATUS / CONDITION
A3: 2020
A6: MUNICIPALITY OF ABORLAN | O6: SOUTH | Q6: NORTH | S6: ISLANDS
O7: =C34+C68+C81+C89+C105+C144+C165 -> 449.95 | Q7: =C199+C229+C241+C262 -> 326.497 | S7: =C174+C295+C313+C342+C358+C369 -> 286.852
A8: ROAD ID | B8: ROAD NAME | C8: REVISED LENGTH (km/s.) | D8: OLD LENGTH | E8: SURFACE TYPE | J8: ROAD CONDITION | K8: KILOMETER POST | L8: REMARKS
E9: CONCRETE | F9: ASPHALT | G9: EARTH | H9: GRAVEL | I9: MIXED | N9: TOTAL | O9: =O7+Q7+S7 -> 1063.299 | Q9: =O13-O9 -> 176.366 | S9: =(O9/O13)*100 -> 85.773092
A10: 219 | B10: Junction - Isaub Road | C10: =SUM(E10:I10) -> 0.4 | D10: ='[23]road inventory 2018'!C10 -> 0.65 | E10: 0 | F10: 0 | G10: 0 | H10: 0.4 | I10: 0 | J10: Fair | K10: km sta.57+800 | N10: New
A11: 1 | B11: Sagpangan Road | C11: =SUM(E11:I11) -> 5.48 | D11: ='[23]road inventory 2018'!C11 -> 5.5 | E11: 2.87 | F11: 0 | G11: 0 | H11: 2.61 | I11: 0 | J11: Fair | K11: km sta.66+400 | N11: Good | O11: =D34+D68+D81+D88+D105+D144+D165 -> 457.45 | Q11: =D199+D214+D229+D241+D262 -> 417.85 | S11: =D174+D280+D295+D313+D342+D358+D369+C375 -> 364.365
A12: 2 | B12: Isaub - Marikit -Tubig Road | C12: =SUM(E12:I12) -> 0.92 | D12: ='[23]road inventory 2018'!C12 -> 0.8 | E12: 0.07 | F12: 0 | G12: 0 | H12: 0.85 | I12: 0 | J12: Good | K12: km sta.58+000 | N12: Fair
A13: 3 | B13: Mailigan - Sagpangan Road | C13: =SUM(E13:I13) -> 4.97 | D13: ='[23]road inventory 2018'!C13 -> 4.9 | E13: 0 | F13: 0 | G13: 0 | H13: 4.97 | I13: 0 | J13: Fair | K13: km sta.62+400 | N13: Poor | O13: =O11+Q11+S11 -> 1239.665
A14: 4 | B14: Iraan - Tubig Road | C14: =SUM(E14:I14) -> 2.67 | D14: ='[23]road inventory 2018'!C14 -> 2.7 | E14: 0.11 | F14: 0 | G14: 0 | H14: 2.56 | I14: 0 | J14: Poor | K14: km sta.64+900 | N14: Bad
A15: 93 | B15: Iraan - Baraki Road | C15: =SUM(E15:I15) -> 3.9 | D15: ='[23]road inventory 2018'!C15 -> 3.9 | E15: 3.9 | F15: 0 | G15: 0 | H15: 0 | I15: 0 | J15: =N11 -> Good | K15: km sta.64+900 | O15: =D280+D287+D292+D302+D307+D308+D309+D311+D322+D330+D335+D337+D340+D353+D354+D355+D356 -> 175.06 | Q15: =Q9-O15 -> 1.306
A16: 218 | B16: Isaub - Sagpangan Road | C16: =SUM(E16:I16) -> 5.61 | D16: ='[23]road inventory 2018'!C16 -> 5.8 | E16: 0 | F16: 0 | G16: 0 | H16: 5.61 | I16: 0 | J16: Fair | K16: km sta.58+000
A17: 5 | B17: PNAC Road | C17: =SUM(E17:I17) -> 2.85 | D17: ='[23]road inventory 2018'!C17 -> 2.8 | E17: 2.85 | F17: 0 | G17: 0 | H17: 0 | I17: 0 | J17: Good | K17: km sta.64+900 | O17: =D28+D45+D50+D76+Q65 -> 11.83
A18: 6 | B18: San Juan Road | C18: =SUM(E18:I18) -> 3.96 | D18: ='[23]road inventory 2018'!C18 -> 3.9 | E18: 2.7 | F18: 0 | G18: 0 | H18: 1.26 | I18: 0 | J18: Good | K18: km sta.66+400
A19: 7 | B19: Aborlan - River Landing | C19: =SUM(E19:I19) -> 1.15 | D19: ='[23]road inventory 2018'!C19 -> 1.1 | E19: 1.15 | F19: 0 | G19: 0 | H19: 0 | I19: 0 | J19: Good | K19: km sta.67+100 | N19: GOOD TO FAIR (TOTAL LENGTH) | Q19: ACTUAL
A20: 8 | B20: Aborlan Poblacion Road | C20: =SUM(E20:I20) -> 0.64 | D20: ='[23]road inventory 2018'!C20 -> 0.6 | E20: 0.64 | F20: 0 | G20: 0 | H20: 0 | I20: 0 | J20: Good | K20: km sta.66+950 | N20: ABORLAN | O20: =C10+C11+C12+C13+C15+C16+C17+C18+C19+C20+C21+C22+C23+C24+C27+C29+C30+C31+C32 -> 81.36 | Q20: =O20 -> 81.36
A21: 9 | B21: Magbabadil - Cabigaan Road | C21: =SUM(E21:I21) -> 9.3 | D21: ='[23]road inventory 2018'!C21 -> 9 | E21: 9.3 | F21: 0 | G21: 0 | H21: 0 | I21: 0 | J21: Good | K21: km sta.66+800 | N21: NARRA | O21: =C41+C42+C43+C44+C45+C46+C47+C48+C49+C50+C51++C52+C55+C56+C57+C58+C59+C60+C61+C64+C67 -> 74.35 | Q21: =O21 -> 74.35
A22: 10 | B22: Plaridel - Apis Cabigaan Road | C22: =SUM(E22:I22) -> 13.79 | D22: ='[23]road inventory 2018'!C22 -> 13.6 | E22: 8.79 | F22: 0 | G22: 0 | H22: 5 | I22: 0 | J22: =J21 -> Good | K22: km sta.75+650 | N22: QUEZON | O22: =C74+C75+C76+C77+C78+C79 -> 28.02 | Q22: =O22 -> 28.02
A23: 11 | B23: Tagpait Feeder Road | C23: =SUM(E23:I23) -> 2.27 | D23: ='[23]road inventory 2018'!C23 -> 2.2 | E23: 0.21 | F23: 0 | G23: 0 | H23: 2.06 | I23: 0 | J23: Fair | K23: km sta.69+000 | N23: RIZAL | O23: =C88 -> 3.28 | Q23: =O23 -> 3.28
A24: 13 | B24: New Bantayan - Apis Road | C24: =SUM(E24:I24) -> 1.72 | D24: ='[23]road inventory 2018'!C24 -> 1.7 | E24: 0 | F24: 0 | G24: 0 | H24: 1.72 | I24: 0 | J24: Fair | K24: km sta.69+200 | N24: ESPANOLA | O24: =C96+C98+C99+C100+C101+C102 -> 26.35 | Q24: =O24 -> 26.35
A25: 12 | B25: Tagbariri Road | C25: =SUM(E25:I25) -> 1.62 | D25: ='[23]road inventory 2018'!C25 -> 1.6 | E25: 0 | F25: 0 | G25: 0 | H25: 1.62 | I25: 0 | J25: Poor | K25: km sta.69+100 | N25: BROOKES POINT | O25: =C112+C113+C114+C115+C116+C117+C118+C119+C120+C123+C124+C125+C126+C127+C128+C129+C130+C131+C132+C133+C136+C137+C138+C139+C140+C142+C143 -> 107.36 | Q25: =O25 -> 107.36
A26: 220 | B26: Tagbariri - Magsaysay Road | C26: =SUM(E26:I26) -> 2.11 | D26: ='[23]road inventory 2018'!C26 -> 2.3 | E26: 0 | F26: 0 | G26: 0 | H26: 2.11 | I26: 0 | J26: Poor | K26: km sta.71+150 | N26: BATARAZA | O26: =C151+C152+C153+C159+C161 -> 10.66 | Q26: =O26 -> 10.66
A27: 14 | B27: Junction - Tigman Road | C27: =SUM(E27:I27) -> 4.12 | D27: ='[23]road inventory 2018'!C27 -> 4 | E27: 4.12 | F27: 0 | G27: 0 | H27: 0 | I27: 0 | J27: Good | K27: km sta.75+650 | N27: BALABAC | O27: =C172+C173 -> 18.67 | Q27: =O27 -> 18.67
A28: 15 | B28: Tigman - Rizal Road | C28: =SUM(E28:I28) -> 0 | D28: ='[23]road inventory 2018'!C28 -> 3.2 | E28: 0 | F28: 0 | G28: 0 | H28: 0 | I28: 0 | J28: Poor | K28: km sta.77+400 | L28: NOT EXISTING | N28: ROXAS | O28: =C182+C183+C186+C188+C189+C190+C193+C192+C194+C195+C196+C197+C198 -> 108.29 | Q28: =O28 -> 108.29
A29: 16 | B29: Tigman - Caburian Road | C29: =SUM(E29:I29) -> 1.05 | D29: ='[23]road inventory 2018'!C29 -> 1 | E29: 0 | F29: 0 | G29: 0 | H29: 1.05 | I29: 0 | J29: Fair | K29: km sta.78+150 | N29: SANVICENTE | O29: =C206+C207+C209+C210+C212+C213 -> 71.4 | Q29: =O29 -> 71.4
A30: 17 | B30: Magbabadil - Baraki Road | C30: =SUM(E30:I30) -> 4.18 | D30: ='[23]road inventory 2018'!C30 -> 4 | E30: 4.18 | F30: 0 | G30: 0 | H30: 0 | I30: 0 | J30: Fair | K30: km sta.73+400 | N30: TAYTAY | O30: =C221+C222+C223+C224+C226+C227+C228 -> 88.617 | Q30: =O30 -> 88.617
A31: 18 | B31: Tigman - Rizal - Dumangueña Road | C31: =SUM(E31:I31) -> 10.52 | D31: ='[23]road inventory 2018'!C31 -> 10.5 | E31: 4.54 | F31: 0 | G31: 0 | H31: 5.98 | I31: 0 | J31: Fair | K31: km sta.77+400 | N31: EL NIDO | O31: =C237+C239 -> 9 | Q31: =O31 -> 9
A32: 221 | B32: Hi-way Jct. Plaridel-Tigman-Caburian Rd | C32: =SUM(E32:I32) -> 4.53 | D32: ='[23]road inventory 2018'!C32 -> 5.2 | E32: 0 | F32: 0 | G32: 0 | H32: 4.53 | I32: 0 | J32: Fair | K32: km sta.76+500 | N32: DUMARAN | O32: =C248+C249+C250+C251+C252+C255+C256+C260+C261 -> 55.5 | Q32: =O32 -> 55.5
A33: 20 | B33: Aporawan-Daan-Cabigaan Road | C33: =SUM(E33:I33) -> 7.63 | D33: ='[23]road inventory 2018'!C33 -> 7.6 | E33: 0 | F33: 0 | G33: 0 | H33: 7.63 | I33: 0 | J33: Bad | N33: ARACELI | O33: =C270+C275+C276 -> 10.1 | Q33: 0
C34: =SUM(C10:C33) -> 95.39 | D34: =SUM(D10:D33) -> 98.55 | E34: =SUM(E10:E33) -> 45.43 | F34: =SUM(F10:F33) -> 0 | G34: =SUM(G10:G33) -> 0 | H34: =SUM(H10:H33) -> 49.96 | I34: =SUM(I10:I33) -> 0 | N34: CUYO | O34: =C287+C288+C290+C291+C293 -> 27.7 | Q34: =C288+C290+C291+C293 -> 15.01
A35: SUB-TOTAL | C35: =E35+F35+G35+H35+I35 -> 95.39 | E35: =SUM(E10:E33) -> 45.43 | F35: =SUM(F10:F33) -> 0 | G35: =SUM(G10:G33) -> 0 | H35: =SUM(H10:H33) -> 49.96 | I35: =SUM(I10:I33) -> 0 | N35: MAGSAYSAY | O35: =C303+C304+C305+C306+C311+C312 -> 8.82 | Q35: =C303+C304+C305+C306+C312 -> 8.02
N36: AGUTAYA | O36: =C320+C321 -> 7.25 | Q36: 0
A37: MUNICIPALITY OF NARRA | N37: CORON | O37: =C329+C331+C332+C333+C334+C337+C338+C339+C341 -> 79.6 | Q37: =C329+C331+C332+C333+C334+C338+C339+C341 -> 77.18
N38: BUSUANGA | O38: =C351+C352+C354+C355 -> 34.028 | Q38: =C351+C352 -> 13.028
A39: ROAD ID | B39: ROAD NAME | C39: LENGTH (km/s.) | E39: SURFACE TYPE | J39: ROAD CONDITION | K39: KILOMETER POST | L39: REMARKS | N39: CULION | O39: =C364+C365+C366+C367 -> 24.68 | Q39: =C364+C365+C366+C367 -> 24.68
E40: CONCRETE | F40: ASPHALT | G40: EARTH | H40: GRAVEL | I40: MIXED | N40: CAGAYAN CILLO | O40: =C375 -> 8.741 | Q40: 0
A41: 21 | B41: Sandoval Feeder Road | C41: =SUM(E41:I41) -> 4.32 | D41: ='[23]road inventory 2018'!C41 -> 4.3 | E41: 4.11 | F41: 0 | G41: 0 | H41: 0.21 | I41: 0 | J41: Good | K41: km sta.79+500 | N41: =N19 -> GOOD TO FAIR (TOTAL LENGTH) | O41: =SUM(O20:O40) -> 883.776 | P41: =C380-O41 -> 340.404 | Q41: =SUM(Q20:Q40) -> 820.775
A42: 22 | B42: Apo-Aporawan Section Road | C42: =SUM(E42:I42) -> 4.01 | D42: ='[23]road inventory 2018'!C42 -> 3.9 | E42: 0 | F42: 0 | G42: 0 | H42: 4.01 | I42: 0 | J42: Fair | K42: km sta.80+770
A43: 23 | B43: Malatgao - Babanitan Road | C43: =SUM(E43:I43) -> 4.42 | D43: ='[23]road inventory 2018'!C43 -> 4.3 | E43: 2.9 | F43: 0 | G43: 0 | H43: 1.52 | I43: 0 | J43: Fair | K43: km sta.83+580
A44: 24 | B44: Malatgao Section Road | C44: =SUM(E44:I44) -> 8.25 | D44: ='[23]road inventory 2018'!C44 -> 7.5 | E44: 8.25 | F44: 0 | G44: 0 | H44: 0 | I44: 0 | J44: Good | K44: km sta.83+580
A45: 25 | B45: Taritien Sea Road | C45: =SUM(E45:I45) -> 0.88 | D45: ='[23]road inventory 2018'!C45 -> 1.7 | E45: 0 | F45: 0 | G45: 0 | H45: 0.88 | I45: 0 | J45: Fair | K45: km sta.85+500 | L45: NOT ACCESSIBLE | N45: **NOTE: THE ROAD IS NOT ACCESSIBLE DUE TO POOR CONDITION OF BRIDGE.
A46: 26 | B46: Taritien Section Road | C46: =SUM(E46:I46) -> 6.06 | D46: ='[23]road inventory 2018'!C46 -> 5.9 | E46: 2.85 | F46: 0 | G46: 0 | H46: 3.21 | I46: 0 | J46: Fair | K46: km sta.85+500
A47: 27 | B47: Antipuluan Sea Road | C47: =SUM(E47:I47) -> 1.93 | D47: ='[23]road inventory 2018'!C47 -> 1.9 | E47: 0.28 | F47: 0 | G47: 0 | H47: 1.65 | I47: 0 | J47: Fair | K47: km sta.88+045
A48: 28 | B48: Lapu-Lapu Section Road | C48: =SUM(E48:I48) -> 5.62 | D48: ='[23]road inventory 2018'!C48 -> 5.6 | E48: 1.54 | F48: 0 | G48: 0 | H48: 4.08 | I48: 0 | J48: Good | K48: km sta.91+160
A49: 29 | B49: Narra School Road | C49: =SUM(E49:I49) -> 0.86 | D49: ='[23]road inventory 2018'!C49 -> 0.8 | E49: 0.11 | F49: 0 | G49: 0 | H49: 0.75 | I49: 0 | J49: Fair | K49: km sta.92+250
A50: 30 | B50: Rizal Avenue Section Road | C50: =SUM(E50:I50) -> 2 | D50: ='[23]road inventory 2018'!C50 -> 2 | E50: 1.5 | F50: 0 | G50: 0 | H50: 0.5 | I50: 0 | J50: Good | K50: km sta.91+670 | L50: MUNICIPAL ROAD | N50: Municipal road
A51: 106 | B51: Narra Panacan Road | C51: =SUM(E51:I51) -> 3.21 | D51: ='[23]road inventory 2018'!C51 -> 3.2 | E51: 3.21 | F51: 0 | G51: 0 | H51: 0 | I51: 0 | J51: Good | K51: km sta.92+370
A52: 31 | B52: Ipil Road / Quirino | C52: =SUM(E52:I52) -> 0.78 | D52: ='[23]road inventory 2018'!C52 -> 0.8 | E52: 0.78 | F52: 0 | G52: 0 | H52: 0 | I52: 0 | J52: Good | K52: km sta.92+700
A53: 32 | B53: Guminubat Section Road | C53: =SUM(E53:I53) -> 3.01 | D53: ='[23]road inventory 2018'!C53 -> 3 | E53: 0 | F53: 0 | G53: 0 | H53: 3.01 | I53: 0 | J53: Bad | K53: km sta.94+650
A54: 33 | B54: Malinao Feeder Road | C54: =SUM(E54:I54) -> 2.4 | D54: ='[23]road inventory 2018'!C54 -> 2.4 | E54: 0.25 | F54: 0 | G54: 0 | H54: 2.15 | I54: 0 | J54: Poor | K54: km sta.96+850
A55: 34 | B55: Linamen Feeder Road | C55: =SUM(E55:I55) -> 4.31 | D55: ='[23]road inventory 2018'!C55 -> 4.2 | E55: 0 | F55: 0 | G55: 0 | H55: 4.31 | I55: 0 | J55: Fair | K55: km sta.100+150
A56: 35 | B56: Caguisan Feeder Road | C56: =SUM(E56:I56) -> 2.97 | D56: ='[23]road inventory 2018'!C56 -> 3 | E56: 0.4 | F56: 0 | G56: 0 | H56: 2.57 | I56: 0 | J56: Fair | K56: km sta.99+200
A57: 36 | B57: Batang-Batang Feeder Road | C57: =SUM(E57:I57) -> 6.01 | D57: ='[23]road inventory 2018'!C57 -> 6.2 | E57: 0 | F57: 0 | G57: 0 | H57: 6.01 | I57: 0 | J57: Fair | K57: km sta.101+950
A58: 37 | B58: Linamen - Batang-Batang Feeder Road | C58: =SUM(E58:I58) -> 1.6 | D58: ='[23]road inventory 2018'!C58 -> 1.6 | E58: 0 | F58: 0 | G58: 0 | H58: 1.6 | I58: 0 | J58: Fair | K58: km sta.101+960
A59: 38 | B59: Teresa - Batang-Batang Road | C59: =SUM(E59:I59) -> 3.9 | D59: ='[23]road inventory 2018'!C59 -> 4.4 | E59: 1.504 | F59: 0 | G59: 0 | H59: 2.396 | I59: 0 | J59: Fair | K59: km sta.105+550
A60: 39 | B60: Teresa Feeder Road | C60: =SUM(E60:I60) -> 4.94 | D60: ='[23]road inventory 2018'!C60 -> 4.9 | E60: 0 | F60: 0 | G60: 0 | H60: 4.94 | I60: 0 | J60: Fair | K60: km sta.104+100
A61: 105 | B61: Bato-Bato Feeder Road | C61: =SUM(E61:I61) -> 3.65 | D61: ='[23]road inventory 2018'!C61 -> 3.6 | E61: 0 | F61: 0 | G61: 0 | H61: 3.65 | I61: 0 | J61: Fair | K61: km sta.105+950
A62: 40 | B62: Calategas Sea Road | C62: =SUM(E62:I62) -> 1.55 | D62: ='[23]road inventory 2018'!C62 -> 1.5 | E62: 1.22 | F62: 0 | G62: 0 | H62: 0.33 | I62: 0 | J62: Poor | K62: km sta.115+010
... A64: 42 | B64: Aramaywan Sea Road | C64: =SUM(E64:I64) -> 1.5 | D64: ='[23]road inventory 2018'!C64 -> 1.5 | E64: 0 | F64: 0 | G64: 0 | H64: 1.5 | I64: 0 | J64: Fair | K64: km sta.120+300
A65: 43 | B65: Aramaywan Parangue Road | C65: =SUM(E65:I65) -> 8.37 | D65: ='[23]road inventory 2018'!C65 -> 12.7 | E65: 0.16 | F65: 0 | G65: 0 | H65: 8.21 | I65: 0 | J65: Bad | K65: km sta.120+750 | L65: NOT ACCESSIBLE | N65: **NOTE: THE ROAD IS NOT ACCESSIBLE DUE TO POOR CONDITION OF CULVERT. | Q65: =D65-C65 -> 4.33
A66: 44 | B66: Burirao - Cabudlungan Road | C66: =SUM(E66:I66) -> 5.52 | D66: ='[23]road inventory 2018'!C66 -> 5.3 | E66: 0 | F66: 0 | G66: 0 | H66: 5.52 | I66: 0 | J66: Bad | K66: km sta.124+800
A67: 104 | B67: Sandoval - Bagong Sikat Road | C67: =SUM(E67:I67) -> 3.13 | D67: ='[23]road inventory 2018'!C67 -> 3.1 | E67: 0 | F67: 0 | G67: 0 | H67: 3.13 | I67: 0 | J67: Fair | K67: km sta.81+500
C68: =SUM(C41:C67) -> 98.01 | D68: =SUM(D41:D67) -> 102.1 | E68: =SUM(E41:E67) -> 29.064 | F68: =SUM(F41:F67) -> 0 | G68: =SUM(G41:G67) -> 0 | H68: =SUM(H41:H67) -> 68.946 | I68: =SUM(I41:I67) -> 0
A69: SUB-TOTAL | C69: =SUM(E69:I69) -> 98.01 | E69: =SUM(E41:E67) -> 29.064 | F69: =SUM(F41:F67) -> 0 | G69: =SUM(G41:G67) -> 0 | H69: =SUM(H41:H67) -> 68.946 | I69: =SUM(I41:I67) -> 0
A70: MUNICIPALITY OF QUEZON
A72: ROAD ID | B72: ROAD NAME | C72: LENGTH (km/s.) | E72: SURFACE TYPE | J72: ROAD CONDITION | K72: KILOMETER POST | L72: REMARKS
E73: CONCRETE | F73: ASPHALT | G73: EARTH | H73: GRAVEL | I73: MIXED
A74: 107 | B74: Tabon - Pinaglabanan Road | C74: =SUM(E74:I74) -> 2.59 | D74: ='[23]road inventory 2018'!C73 -> 2.5 | E74: 1.07 | F74: 0 | G74: 0 | H74: 1.52 | I74: 0 | J74: Fair | K74: km sta.139+300
A75: 102 | B75: Tabon - Tagpapasi Road | C75: =SUM(E75:I75) -> 1.33 | D75: ='[23]road inventory 2018'!C74 -> 1.3 | E75: 0 | F75: 0 | G75: 0 | H75: 1.33 | I75: 0 | J75: Fair | K75: km sta.143+700
A76: 101 | B76: Magsaysay Road | C76: =SUM(E76:I76) -> 0 | D76: ='[23]road inventory 2018'!C75 -> 0.6 | E76: 0 | F76: 0 | G76: 0 | H76: 0 | I76: 0 | J76: Good | K76: km sta.146+000 | L76: MUNICIPAL ROAD | N76: Municipal Road
A77: 47 | B77: Abo-Abo - Isugod Road | C77: =SUM(E77:I77) -> 17.2 | D77: ='[23]road inventory 2018'!C76 -> 17 | E77: 0.27 | F77: 0 | G77: 0 | H77: 16.93 | I77: 0 | J77: Fair | K77: km sta.156+500
A78: 48 | B78: Maasin - Marintub Road | C78: =SUM(E78:I78) -> 2.63 | D78: ='[23]road inventory 2018'!C77 -> 2.6 | E78: 0 | F78: 0 | G78: 0 | H78: 2.63 | I78: 0 | J78: Fair | K78: km sta.157+800
A79: 90 | B79: Malatgao Road | C79: =SUM(E79:I79) -> 4.27 | D79: ='[23]road inventory 2018'!C78 -> 4.35 | E79: 0 | F79: 0 | G79: 0 | H79: 4.27 | I79: 0 | J79: Fair | K79: km sta.134+500
A80: 99 | B80: Panitian - Tabud Road | C80: =SUM(E80:I80) -> 14.14 | D80: ='[23]road inventory 2018'!C79 -> 14.1 | E80: 2.1 | F80: 0 | G80: 0 | H80: 12.04 | I80: 0 | J80: Fair | K80: km sta.151+000
C81: =SUM(C74:C80) -> 42.16 | D81: =SUM(D74:D80) -> 42.45 | E81: =SUM(E74:E80) -> 3.44 | F81: =SUM(F74:F80) -> 0 | G81: =SUM(G74:G80) -> 0 | H81: =SUM(H74:H80) -> 38.72
A82: SUB-TOTAL | C82: =SUM(E82:I82) -> 42.16 | E82: =SUM(E74:E80) -> 3.44 | F82: =SUM(F74:F80) -> 0 | G82: =SUM(G74:G80) -> 0 | H82: =SUM(H74:H80) -> 38.72 | I82: =SUM(I74:I80) -> 0
A84: MUNICIPALITY OF RIZAL
A86: ROAD ID | B86: ROAD NAME | C86: LENGTH (km/s.) | E86: SURFACE TYPE | J86: ROAD CONDITION | K86: KILOMETER POST | L86: REMARKS
E87: CONCRETE | F87: ASPHALT | G87: EARTH | H87: GRAVEL | I87: MIXED
A88: 108 | B88: Rancho - Puntabaja - Malapandeg Road | C88: =E88+F88+G88+H88+I88 -> 3.28 | D88: ='[23]road inventory 2018'!C86 -> 3.1 | E88: 0.48 | F88: 0 | G88: 0 | H88: 2.8 | I88: 0 | J88: Fair | K88: km sta.198+000
A89: SUB-TOTAL | C89: =SUM(C88:C88) -> 3.28 | E89: =SUM(E88:E88) -> 0.48 | F89: =SUM(F88:F88) -> 0 | G89: =SUM(G88:G88) -> 0 | H89: =SUM(H88:H88) -> 2.8 | I89: =SUM(I88:I88) -> 0
A91: MUNICIPALITY OF SOFRONIO ESPAÑOLA
A93: ROAD ID | B93: ROAD NAME | C93: LENGTH (km/s.) | E93: SURFACE TYPE | J93: ROAD CONDITION | K93: KILOMETER POST | L93: REMARKS
E94: CONCRETE | F94: ASPHALT | G94: EARTH | H94: GRAVEL | I94: MIXED
A95: 223 | B95: Panitian Seashore Road | C95: =SUM(E95:I95) -> 4.18 | D95: ='[23]road inventory 2018'!C93 -> 4.1 | E95: 0 | F95: 0 | G95: 0 | H95: 4.18 | I95: 0 | J95: Poor | K95: km sta.137+000
A96: 224 | B96: Panitian - Abokayan Road | C96: =SUM(E96:I96) -> 7.24 | D96: ='[23]road inventory 2018'!C94 -> 7.2 | E96: 1.98 | F96: 0 | G96: 0 | H96: 5.26 | I96: 0 | J96: Fair | K96: km sta.137+900
A97: 45 | B97: Labog Naltep Road | C97: =SUM(E97:I97) -> 7.44 | D97: ='[23]road inventory 2018'!C95 -> 7.9 | E97: 0.71 | F97: 0 | G97: 0 | H97: 6.73 | I97: 0 | J97: Poor | K97: km sta.143+800
A98: 217 | B98: Punang Plain Road | C98: =SUM(E98:I98) -> 1.14 | D98: ='[23]road inventory 2018'!C96 -> 1.1 | E98: 1.14 | F98: 0 | G98: 0 | H98: 0 | I98: 0 | J98: Good | K98: km sta.149+200
A99: 225 | B99: Iraray School Road | C99: =SUM(E99:I99) -> 0.36 | D99: ='[23]road inventory 2018'!C97 -> 0.4 | E99: 0 | F99: 0 | G99: 0 | H99: 0.36 | I99: 0 | J99: Good | K99: km sta.155+700
A100: 226 | B100: Pulot Sea Road | C100: =SUM(E100:I100) -> 4.01 | D100: ='[23]road inventory 2018'!C98 -> 4.8 | E100: 0.86 | F100: 0 | G100: 0 | H100: 3.15 | I100: 0 | J100: Good | K100: km sta.162+800
A101: 116 | B101: Pulot I - Pulot III Road | C101: =SUM(E101:I101) -> 12.3 | D101: ='[23]road inventory 2018'!C99 -> 12.3 | E101: 6.67 | F101: 0 | G101: 0 | H101: 5.63 | I101: 0 | J101: Fair | K101: km sta.162+800
A102: 46 | B102: Pulot Bo. High School Road | C102: =SUM(E102:I102) -> 1.3 | D102: ='[23]road inventory 2018'!C100 -> 1.3 | E102: 1.3 | F102: 0 | G102: 0 | H102: 0 | I102: 0 | J102: Good | K102: km sta.163+800
A103: 227 | B103: Caramay Bulho Road | C103: =SUM(E103:I103) -> 7.43 | D103: ='[23]road inventory 2018'!C101 -> 7.2 | E103: 0 | F103: 0 | G103: 0 | H103: 7.43 | I103: 0 | J103: Poor | K103: km sta.165+600
A104: 100 | B104: Pulot III-Tabud Road | C104: =SUM(E104:I104) -> 7.8 | D104: ='[23]road inventory 2018'!C102 -> 7.8 | E104: 2 | F104: 0 | G104: 5.8 | H104: 0 | I104: 0 | J104: Fair | K104: km sta.177+000
C105: =SUM(C95:C104) -> 53.2 | D105: =SUM(D95:D104) -> 54.1 | E105: =SUM(E95:E104) -> 14.66 | F105: =SUM(F95:F104) -> 0 | G105: =SUM(G95:G104) -> 5.8 | H105: =SUM(H95:H104) -> 32.74
A106: SUB-TOTAL | C106: =SUM(E106:I106) -> 53.2 | E106: =SUM(E95:E104) -> 14.66 | F106: =SUM(F95:F104) -> 0 | G106: =SUM(G95:G104) -> 5.8 | H106: =SUM(H95:H104) -> 32.74 | I106: =SUM(I95:I104) -> 0
A108: MUNICIPALITY OF BROOKE'S POINT
A110: ROAD ID | B110: ROAD NAME | C110: LENGTH (km/s.) | E110: SURFACE TYPE | J110: ROAD CONDITION | K110: KILOMETER POST | L110: REMARKS
...

Sheet GOOD TO FAIR2020
A1: PROVINCIAL ENGINEER'S OFFICE
A2: PROVINCIAL ROAD NETWORK AND ITS STATUS / CONDITION
A3: 2020
A6: MUNICIPALITY OF ABORLAN | O6: SOUTH | Q6: NORTH | S6: ISLANDS
O7: =C29+C57+C70+C78+C91+C125+C137 -> 353.32 | Q7: =C167+C194+C203+C220 -> 268.417 | S7: =C146+C243+C256+C281+C293+C304 -> 198.798
A8: ROAD ID | B8: ROAD NAME | C8: REVISED LENGTH (km/s.) | D8: OLD LENGTH | E8: SURFACE TYPE | J8: ROAD CONDITION | K8: KILOMETER POST | L8: REMARKS
E9: CONCRETE | F9: ASPHALT | G9: EARTH | H9: GRAVEL | I9: MIXED | N9: TOTAL | O9: =O7+Q7+S7 -> 820.535 | Q9: =O13-O9 -> 91.978 | S9: =(O9/O13)*100 -> 89.920363
A10: 219 | B10: Junction - Isaub Road | C10: =SUM(E10:I10) -> 0.4 | D10: ='[23]road inventory 2018'!C10 -> 0.65 | E10: 0 | F10: 0 | G10: 0 | H10: 0.4 | I10: 0 | J10: Fair | K10: km sta.57+800 | N10: New
A11: 1 | B11: Sagpangan Road | C11: =SUM(E11:I11) -> 5.48 | D11: ='[23]road inventory 2018'!C11 -> 5.5 | E11: 2.87 | F11: 0 | G11: 0 | H11: 2.61 | I11: 0 | J11: Fair | K11: km sta.66+400 | N11: Good | O11: =D29+D57+D70+D77+D91+D125+D137 -> 350.05 | Q11: =D167+D180+D194+D203+D220 -> 340.55 | S11: =D146+D230+D243+D256+D281+D293+D304+C310 -> 221.913
A12: 2 | B12: Isaub - Marikit -Tubig Road | C12: =SUM(E12:I12) -> 0.92 | D12: ='[23]road inventory 2018'!C12 -> 0.8 | E12: 0.07 | F12: 0 | G12: 0 | H12: 0.85 | I12: 0 | J12: Good | K12: km sta.58+000 | N12: Fair
A13: 3 | B13: Mailigan - Sagpangan Road | C13: =SUM(E13:I13) -> 4.97 | D13: ='[23]road inventory 2018'!C13 -> 4.9 | E13: 0 | F13: 0 | G13: 0 | H13: 4.97 | I13: 0 | J13: Fair | K13: km sta.62+400 | N13: Poor | O13: =O11+Q11+S11 -> 912.513
A14: 93 | B14: Iraan - Baraki Road | C14: =SUM(E14:I14) -> 3.9 | D14: ='[23]road inventory 2018'!C15 -> 3.9 | E14: 3.9 | F14: 0 | G14: 0 | H14: 0 | I14: 0 | J14: =N11 -> Good | K14: km sta.64+900 | O14: =D230+D237+D241+#REF!+#REF!+#REF!+#REF!+D254+D265+#REF!+#REF!+D277+#REF!+#REF!+D290+D291+#REF! -> #REF! | Q14: =Q9-O14 -> #REF!
A15: 218 | B15: Isaub - Sagpangan Road | C15: =SUM(E15:I15) -> 5.61 | D15: ='[23]road inventory 2018'!C16 -> 5.8 | E15: 0 | F15: 0 | G15: 0 | H15: 5.61 | I15: 0 | J15: Fair | K15: km sta.58+000
A16: 5 | B16: PNAC Road | C16: =SUM(E16:I16) -> 2.85 | D16: ='[23]road inventory 2018'!C17 -> 2.8 | E16: 2.85 | F16: 0 | G16: 0 | H16: 0 | I16: 0 | J16: Good | K16: km sta.64+900 | O16: =#REF!+D40+D45+D65+#REF! -> #REF!
A17: 6 | B17: San Juan Road | C17: =SUM(E17:I17) -> 3.96 | D17: ='[23]road inventory 2018'!C18 -> 3.9 | E17: 2.7 | F17: 0 | G17: 0 | H17: 1.26 | I17: 0 | J17: Good | K17: km sta.66+400
A18: 7 | B18: Aborlan - River Landing | C18: =SUM(E18:I18) -> 1.15 | D18: ='[23]road inventory 2018'!C19 -> 1.1 | E18: 1.15 | F18: 0 | G18: 0 | H18: 0 | I18: 0 | J18: Good | K18: km sta.67+100 | N18: GOOD TO FAIR (TOTAL LENGTH) | Q18: ACTUAL
A19: 8 | B19: Aborlan Poblacion Road | C19: =SUM(E19:I19) -> 0.64 | D19: ='[23]road inventory 2018'!C20 -> 0.6 | E19: 0.64 | F19: 0 | G19: 0 | H19: 0 | I19: 0 | J19: Good | K19: km sta.66+950 | N19: ABORLAN | O19: =C10+C11+C12+C13+C14+C15+C16+C17+C18+C19+C20+C21+C22+C23+C24+C25+C26+C27+C28 -> 81.36 | Q19: =O19 -> 81.36
A20: 9 | B20: Magbabadil - Cabigaan Road | C20: =SUM(E20:I20) -> 9.3 | D20: ='[23]road inventory 2018'!C21 -> 9 | E20: 9.3 | F20: 0 | G20: 0 | H20: 0 | I20: 0 | J20: Good | K20: km sta.66+800 | N20: NARRA | O20: =C36+C37+C38+C39+C40+C41+C42+C43+C44+C45+C46++C47+C48+C49+C50+C51+C52+C53+C54+C55+C56 -> 74.35 | Q20: =O20 -> 74.35
A21: 10 | B21: Plaridel - Apis Cabigaan Road | C21: =SUM(E21:I21) -> 13.79 | D21: ='[23]road inventory 2018'!C22 -> 13.6 | E21: 8.79 | F21: 0 | G21: 0 | H21: 5 | I21: 0 | J21: =J20 -> Good | K21: km sta.75+650 | N21: QUEZON | O21: =C63+C64+C65+C66+C67+C68 -> 28.02 | Q21: =O21 -> 28.02
A22: 11 | B22: Tagpait Feeder Road | C22: =SUM(E22:I22) -> 2.27 | D22: ='[23]road inventory 2018'!C23 -> 2.2 | E22: 0.21 | F22: 0 | G22: 0 | H22: 2.06 | I22: 0 | J22: Fair | K22: km sta.69+000 | N22: RIZAL | O22: =C77 -> 3.28 | Q22: =O22 -> 3.28
A23: 13 | B23: New Bantayan - Apis Road | C23: =SUM(E23:I23) -> 1.72 | D23: ='[23]road inventory 2018'!C24 -> 1.7 | E23: 0 | F23: 0 | G23: 0 | H23: 1.72 | I23: 0 | J23: Fair | K23: km sta.69+200 | N23: ESPANOLA | O23: =C84+C85+C86+C87+C88+C89 -> 26.35 | Q23: =O23 -> 26.35
A24: 14 | B24: Junction - Tigman Road | C24: =SUM(E24:I24) -> 4.12 | D24: ='[23]road inventory 2018'!C27 -> 4 | E24: 4.12 | F24: 0 | G24: 0 | H24: 0 | I24: 0 | J24: Good | K24: km sta.75+650 | N24: BALABAC | O24: =C144+C145 -> 18.67 | Q24: =O24 -> 18.67
A25: 16 | B25: Tigman - Caburian Road | C25: =SUM(E25:I25) -> 1.05 | D25: ='[23]road inventory 2018'!C29 -> 1 | E25: 0 | F25: 0 | G25: 0 | H25: 1.05 | I25: 0 | J25: Fair | K25: km sta.78+150 | N25: SANVICENTE | O25: =C174+C175+C176+C177+C178+C179 -> 71.4 | Q25: =O25 -> 71.4
A26: 17 | B26: Magbabadil - Baraki Road | C26: =SUM(E26:I26) -> 4.18 | D26: ='[23]road inventory 2018'!C30 -> 4 | E26: 4.18 | F26: 0 | G26: 0 | H26: 0 | I26: 0 | J26: Fair | K26: km sta.73+400 | N26: TAYTAY | O26: =C187+C188+C189+C190+C191+C192+C193 -> 88.617 | Q26: =O26 -> 88.617
A27: 18 | B27: Tigman - Rizal - Dumangueña Road | C27: =SUM(E27:I27) -> 10.52 | D27: ='[23]road inventory 2018'!C31 -> 10.5 | E27: 4.54 | F27: 0 | G27: 0 | H27: 5.98 | I27: 0 | J27: Fair | K27: km sta.77+400 | N27: EL NIDO | O27: =C201+C202 -> 9 | Q27: =O27 -> 9
A28: 221 | B28: Hi-way Jct. Plaridel-Tigman-Caburian Rd | C28: =SUM(E28:I28) -> 4.53 | D28: ='[23]road inventory 2018'!C32 -> 5.2 | E28: 0 | F28: 0 | G28: 0 | H28: 4.53 | I28: 0 | J28: Fair | K28: km sta.76+500 | N28: DUMARAN | O28: =C210+C211+C212+C213+C214+C215+C216+C218+C219 -> 55.5 | Q28: =O28 -> 55.5
C29: =SUM(C10:C28) -> 81.36 | D29: =SUM(D10:D28) -> 81.15 | E29: =SUM(E10:E28) -> 45.32 | F29: =SUM(F10:F28) -> 0 | G29: =SUM(G10:G28) -> 0 | H29: =SUM(H10:H28) -> 36.04 | I29: =SUM(I10:I28) -> 0 | N29: CUYO | O29: =C237+C238+C239+C240+C242 -> 27.7 | Q29: =C238+C239+C240+C242 -> 15.01
A30: SUB-TOTAL | C30: =E30+F30+G30+H30+I30 -> 81.36 | E30: =SUM(E10:E28) -> 45.32 | F30: =SUM(F10:F28) -> 0 | G30: =SUM(G10:G28) -> 0 | H30: =SUM(H10:H28) -> 36.04 | I30: =SUM(I10:I28) -> 0 | N30: MAGSAYSAY | O30: =C250+C251+C252+C253+C254+C255 -> 8.82 | Q30: =C250+C251+C252+C253+C255 -> 8.02
N31: AGUTAYA | O31: =C263+C264 -> 7.25 | Q31: 0
A32: MUNICIPALITY OF NARRA | N32: CORON | O32: =C272+C273+C274+C275+C276+C277+C278+C279+C280 -> 79.6 | Q32: =C272+C273+C274+C275+C276+C278+C279+C280 -> 77.18
N33: BUSUANGA | O33: =C288+C289+C290+C291 -> 34.028 | Q33: =C288+C289 -> 13.028
A34: ROAD ID | B34: ROAD NAME | C34: LENGTH (km/s.) | E34: SURFACE TYPE | J34: ROAD CONDITION | K34: KILOMETER POST | L34: REMARKS | N34: CULION | O34: =C299+C300+C301+C302 -> 24.68 | Q34: =C299+C300+C301+C302 -> 24.68
E35: CONCRETE | F35: ASPHALT | G35: EARTH | H35: GRAVEL | I35: MIXED | N35: CAGAYAN CILLO | O35: =C310 -> 8.741 | Q35: 0
A36: 21 | B36: Sandoval Feeder Road | C36: =SUM(E36:I36) -> 4.32 | D36: ='[23]road inventory 2018'!C41 -> 4.3 | E36: 4.11 | F36: 0 | G36: 0 | H36: 0.21 | I36: 0 | J36: Good | K36: km sta.79+500 | N36: =N18 -> GOOD TO FAIR (TOTAL LENGTH) | O36: =SUM(O19:O35) -> 647.366 | P36: =C315-O36 -> 270.66 | Q36: =SUM(Q19:Q35) -> 594.465
A37: 22 | B37: Apo-Aporawan Section Road | C37: =SUM(E37:I37) -> 4.01 | D37: ='[23]road inventory 2018'!C42 -> 3.9 | E37: 0 | F37: 0 | G37: 0 | H37: 4.01 | I37: 0 | J37: Fair | K37: km sta.80+770
A38: 23 | B38: Malatgao - Babanitan Road | C38: =SUM(E38:I38) -> 4.42 | D38: ='[23]road inventory 2018'!C43 -> 4.3 | E38: 2.9 | F38: 0 | G38: 0 | H38: 1.52 | I38: 0 | J38: Fair | K38: km sta.83+580
A39: 24 | B39: Malatgao Section Road | C39: =SUM(E39:I39) -> 8.25 | D39: ='[23]road inventory 2018'!C44 -> 7.5 | E39: 8.25 | F39: 0 | G39: 0 | H39: 0 | I39: 0 | J39: Good | K39: km sta.83+580
A40: 25 | B40: Taritien Sea Road | C40: =SUM(E40:I40) -> 0.88 | D40: ='[23]road inventory 2018'!C45 -> 1.7 | E40: 0 | F40: 0 | G40: 0 | H40: 0.88 | I40: 0 | J40: Fair | K40: km sta.85+500 | L40: NOT ACCESSIBLE | N40: **NOTE: THE ROAD IS NOT ACCESSIBLE DUE TO POOR CONDITION OF BRIDGE.
A41: 26 | B41: Taritien Section Road | C41: =SUM(E41:I41) -> 6.06 | D41: ='[23]road inventory 2018'!C46 -> 5.9 | E41: 2.85 | F41: 0 | G41: 0 | H41: 3.21 | I41: 0 | J41: Fair | K41: km sta.85+500
A42: 27 | B42: Antipuluan Sea Road | C42: =SUM(E42:I42) -> 1.93 | D42: ='[23]road inventory 2018'!C47 -> 1.9 | E42: 0.28 | F42: 0 | G42: 0 | H42: 1.65 | I42: 0 | J42: Fair | K42: km sta.88+045
A43: 28 | B43: Lapu-Lapu Section Road | C43: =SUM(E43:I43) -> 5.62 | D43: ='[23]road inventory 2018'!C48 -> 5.6 | E43: 1.54 | F43: 0 | G43: 0 | H43: 4.08 | I43: 0 | J43: Good | K43: km sta.91+160
A44: 29 | B44: Narra School Road | C44: =SUM(E44:I44) -> 0.86 | D44: ='[23]road inventory 2018'!C49 -> 0.8 | E44: 0.11 | F44: 0 | G44: 0 | H44: 0.75 | I44: 0 | J44: Fair | K44: km sta.92+250
A45: 30 | B45: Rizal Avenue Section Road | C45: =SUM(E45:I45) -> 2 | D45: ='[23]road inventory 2018'!C50 -> 2 | E45: 1.5 | F45: 0 | G45: 0 | H45: 0.5 | I45: 0 | J45: Good | K45: km sta.91+670 | L45: MUNICIPAL ROAD | N45: Municipal road
A46: 106 | B46: Narra Panacan Road | C46: =SUM(E46:I46) -> 3.21 | D46: ='[23]road inventory 2018'!C51 -> 3.2 | E46: 3.21 | F46: 0 | G46: 0 | H46: 0 | I46: 0 | J46: Good | K46: km sta.92+370
A47: 31 | B47: Ipil Road / Quirino | C47: =SUM(E47:I47) -> 0.78 | D47: ='[23]road inventory 2018'!C52 -> 0.8 | E47: 0.78 | F47: 0 | G47: 0 | H47: 0 | I47: 0 | J47: Good | K47: km sta.92+700
A48: 34 | B48: Linamen Feeder Road | C48: =SUM(E48:I48) -> 4.31 | D48: ='[23]road inventory 2018'!C55 -> 4.2 | E48: 0 | F48: 0 | G48: 0 | H48: 4.31 | I48: 0 | J48: Fair | K48: km sta.100+150
A49: 35 | B49: Caguisan Feeder Road | C49: =SUM(E49:I49) -> 2.97 | D49: ='[23]road inventory 2018'!C56 -> 3 | E49: 0.4 | F49: 0 | G49: 0 | H49: 2.57 | I49: 0 | J49: Fair | K49: km sta.99+200
A50: 36 | B50: Batang-Batang Feeder Road | C50: =SUM(E50:I50) -> 6.01 | D50: ='[23]road inventory 2018'!C57 -> 6.2 | E50: 0 | F50: 0 | G50: 0 | H50: 6.01 | I50: 0 | J50: Fair | K50: km sta.101+950
A51: 37 | B51: Linamen - Batang-Batang Feeder Road | C51: =SUM(E51:I51) -> 1.6 | D51: ='[23]road inventory 2018'!C58 -> 1.6 | E51: 0 | F51: 0 | G51: 0 | H51: 1.6 | I51: 0 | J51: Fair | K51: km sta.101+960
A52: 38 | B52: Teresa - Batang-Batang Road | C52: =SUM(E52:I52) -> 3.9 | D52: ='[23]road inventory 2018'!C59 -> 4.4 | E52: 1.504 | F52: 0 | G52: 0 | H52: 2.396 | I52: 0 | J52: Fair | K52: km sta.105+550
A53: 39 | B53: Teresa Feeder Road | C53: =SUM(E53:I53) -> 4.94 | D53: ='[23]road inventory 2018'!C60 -> 4.9 | E53: 0 | F53: 0 | G53: 0 | H53: 4.94 | I53: 0 | J53: Fair | K53: km sta.104+100
A54: 105 | B54: Bato-Bato Feeder Road | C54: =SUM(E54:I54) -> 3.65 | D54: ='[23]road inventory 2018'!C61 -> 3.6 | E54: 0 | F54: 0 | G54: 0 | H54: 3.65 | I54: 0 | J54: Fair | K54: km sta.105+950
A55: 42 | B55: Aramaywan Sea Road | C55: =SUM(E55:I55) -> 1.5 | D55: ='[23]road inventory 2018'!C64 -> 1.5 | E55: 0 | F55: 0 | G55: 0 | H55: 1.5 | I55: 0 | J55: Fair | K55: km sta.120+300
A56: 104 | B56: Sandoval - Bagong Sikat Road | C56: =SUM(E56:I56) -> 3.13 | D56: ='[23]road inventory 2018'!C67 -> 3.1 | E56: 0 | F56: 0 | G56: 0 | H56: 3.13 | I56: 0 | J56: Fair | K56: km sta.81+500
C57: =SUM(C36:C56) -> 74.35 | D57: =SUM(D36:D56) -> 74.4 | E57: =SUM(E36:E56) -> 27.434 | F57: =SUM(F36:F56) -> 0 | G57: =SUM(G36:G56) -> 0 | H57: =SUM(H36:H56) -> 46.916 | I57: =SUM(I36:I56) -> 0
A58: SUB-TOTAL | C58: =SUM(E58:I58) -> 74.35 | E58: =SUM(E36:E56) -> 27.434 | F58: =SUM(F36:F56) -> 0 | G58: =SUM(G36:G56) -> 0 | H58: =SUM(H36:H56) -> 46.916 | I58: =SUM(I36:I56) -> 0
A59: MUNICIPALITY OF QUEZON
A61: ROAD ID | B61: ROAD NAME | C61: LENGTH (km/s.) | E61: SURFACE TYPE | J61: ROAD CONDITION | K61: KILOMETER POST | L61: REMARKS
E62: CONCRETE | F62: ASPHALT | G62: EARTH | H62: GRAVEL | I62: MIXED
A63: 107 | B63: Tabon - Pinaglabanan Road | C63: =SUM(E63:I63) -> 2.59 | D63: ='[23]road inventory 2018'!C73 -> 2.5 | E63: 1.07 | F63: 0 | G63: 0 | H63: 1.52 | I63: 0 | J63: Fair | K63: km sta.139+300
A64: 102 | B64: Tabon - Tagpapasi Road | C64: =SUM(E64:I64) -> 1.33 | D64: ='[23]road inventory 2018'!C74 -> 1.3 | E64: 0 | F64: 0 | G64: 0 | H64: 1.33 | I64: 0 | J64: Fair | K64: km sta.143+700
A65: 101 | B65: Magsaysay Road | C65: =SUM(E65:I65) -> 0 | D65: ='[23]road inventory 2018'!C75 -> 0.6 | E65: 0 | F65: 0 | G65: 0 | H65: 0 | I65: 0 | J65: Good | K65: km sta.146+000 | L65: MUNICIPAL ROAD | N65: Municipal Road
A66: 47 | B66: Abo-Abo - Isugod Road | C66: =SUM(E66:I66) -> 17.2 | D66: ='[23]road inventory 2018'!C76 -> 17 | E66: 0.27 | F66: 0 | G66: 0 | H66: 16.93 | I66: 0 | J66: Fair | K66: km sta.156+500
A67: 48 | B67: Maasin - Marintub Road | C67: =SUM(E67:I67) -> 2.63 | D67: ='[23]road inventory 2018'!C77 -> 2.6 | E67: 0 | F67: 0 | G67: 0 | H67: 2.63 | I67: 0 | J67: Fair | K67: km sta.157+800
A68: 90 | B68: Malatgao Road | C68: =SUM(E68:I68) -> 4.27 | D68: ='[23]road inventory 2018'!C78 -> 4.35 | E68: 0 | F68: 0 | G68: 0 | H68: 4.27 | I68: 0 | J68: Fair | K68: km sta.134+500
A69: 99 | B69: Panitian - Tabud Road | C69: =SUM(E69:I69) -> 14.14 | D69: ='[23]road inventory 2018'!C79 -> 14.1 | E69: 2.1 | F69: 0 | G69: 0 | H69: 12.04 | I69: 0 | J69: Fair | K69: km sta.151+000
C70: =SUM(C63:C69) -> 42.16 | D70: =SUM(D63:D69) -> 42.45 | E70: =SUM(E63:E69) -> 3.44 | F70: =SUM(F63:F69) -> 0 | G70: =SUM(G63:G69) -> 0 | H70: =SUM(H63:H69) -> 38.72
A71: SUB-TOTAL | C71: =SUM(E71:I71) -> 42.16 | E71: =SUM(E63:E69) -> 3.44 | F71: =SUM(F63:F69) -> 0 | G71: =SUM(G63:G69) -> 0 | H71: =SUM(H63:H69) -> 38.72 | I71: =SUM(I63:I69) -> 0
A73: MUNICIPALITY OF RIZAL
A75: ROAD ID | B75: ROAD NAME | C75: LENGTH (km/s.) | E75: SURFACE TYPE | J75: ROAD CONDITION | K75: KILOMETER POST | L75: REMARKS
E76: CONCRETE | F76: ASPHALT | G76: EARTH | H76: GRAVEL | I76: MIXED
A77: 108 | B77: Rancho - Puntabaja - Malapandeg Road | C77: =E77+F77+G77+H77+I77 -> 3.28 | D77: ='[23]road inventory 2018'!C86 -> 3.1 | E77: 0.48 | F77: 0 | G77: 0 | H77: 2.8 | I77: 0 | J77: Fair | K77: km sta.198+000
A78: SUB-TOTAL | C78: =SUM(C77:C77) -> 3.28 | E78: =SUM(E77:E77) -> 0.48 | F78: =SUM(F77:F77) -> 0 | G78: =SUM(G77:G77) -> 0 | H78: =SUM(H77:H77) -> 2.8 | I78: =SUM(I77:I77) -> 0
A80: MUNICIPALITY OF SOFRONIO ESPAÑOLA
A82: ROAD ID | B82: ROAD NAME | C82: LENGTH (km/s.) | E82: SURFACE TYPE | J82: ROAD CONDITION | K82: KILOMETER POST | L82: REMARKS
E83: CONCRETE | F83: ASPHALT | G83: EARTH | H83: GRAVEL | I83: MIXED
A84: 224 | B84: Panitian - Abokayan Road | C84: =SUM(E84:I84) -> 7.24 | D84: ='[23]road inventory 2018'!C94 -> 7.2 | E84: 1.98 | F84: 0 | G84: 0 | H84: 5.26 | I84: 0 | J84: Fair | K84: km sta.137+900
A85: 217 | B85: Punang Plain Road | C85: =SUM(E85:I85) -> 1.14 | D85: ='[23]road inventory 2018'!C96 -> 1.1 | E85: 1.14 | F85: 0 | G85: 0 | H85: 0 | I85: 0 | J85: Good | K85: km sta.149+200
A86: 225 | B86: Iraray School Road | C86: =SUM(E86:I86) -> 0.36 | D86: ='[23]road inventory 2018'!C97 -> 0.4 | E86: 0 | F86: 0 | G86: 0 | H86: 0.36 | I86: 0 | J86: Good | K86: km sta.155+700
A87: 226 | B87: Pulot Sea Road | C87: =SUM(E87:I87) -> 4.01 | D87: ='[23]road inventory 2018'!C98 -> 4.8 | E87: 0.86 | F87: 0 | G87: 0 | H87: 3.15 | I87: 0 | J87: Good | K87: km sta.162+800
A88: 116 | B88: Pulot I - Pulot III Road | C88: =SUM(E88:I88) -> 12.3 | D88: ='[23]road inventory 2018'!C99 -> 12.3 | E88: 6.67 | F88: 0 | G88: 0 | H88: 5.63 | I88: 0 | J88: Fair | K88: km sta.162+800
A89: 46 | B89: Pulot Bo. High School Road | C89: =SUM(E89:I89) -> 1.3 | D89: ='[23]road inventory 2018'!C100 -> 1.3 | E89: 1.3 | F89: 0 | G89: 0 | H89: 0 | I89: 0 | J89: Good | K89: km sta.163+800
A90: 100 | B90: Pulot III-Tabud Road | C90: =SUM(E90:I90) -> 7.8 | D90: ='[23]road inventory 2018'!C102 -> 7.8 | E90: 2 | F90: 0 | G90: 5.8 | H90: 0 | I90: 0 | J90: Fair | K90: km sta.177+000
C91: =SUM(C84:C90) -> 34.15 | D91: =SUM(D84:D90) -> 34.9 | E91: =SUM(E84:E90) -> 13.95 | F91: =SUM(F84:F90) -> 0 | G91: =SUM(G84:G90) -> 5.8 | H91: =SUM(H84:H90) -> 14.4
A92: SUB-TOTAL | C92: =SUM(E92:I92) -> 34.15 | E92: =SUM(E84:E90) -> 13.95 | F92: =SUM(F84:F90) -> 0 | G92: =SUM(G84:G90) -> 5.8 | H92: =SUM(H84:H90) -> 14.4 | I92: =SUM(I84:I90) -> 0
A94: MUNICIPALITY OF BROOKE'S POINT
A96: ROAD ID | B96: ROAD NAME | C96: LENGTH (km/s.) | E96: SURFACE TYPE | J96: ROAD CONDITION | K96: KILOMETER POST | L96: REMARKS
E97: CONCRETE | F97: ASPHALT | G97: EARTH | H97: GRAVEL | I97: MIXED
A98: 48 | B98: Maasin Airport Road | C98: =SUM(E98:I98) -> 2.19 | D98: ='[23]road inventory 2018'!C109 -> 2.1 | E98: 0 | F98: 0 | G98: 0 | H98: 2.19 | I98: 0 | J98: Fair | K98: km sta.113+100
A99: 50 | B99: Maasin Rancho Road | C99: =SUM(E99:I99) -> 7.69 | D99: ='[23]road inventory 2018'!C110 -> 7.6 | E99: 1.79 | F99: 0 | G99: 0 | H99: 5.9 | I99: 0 | J99: Fair | K99: km sta.174+800-
A100: 51 | B100: Ipilan Feeder Road | C100: =SUM(E100:I100) -> 3.96 | D100: ='[23]road inventory 2018'!C111 -> 3 | E100: 0 | F100: 0 | G100: 0 | H100: 3.96 | I100: 0 | J100: Fair | K100: km sta.182+050
A101: 52 | B101: Ipilan Rizal Road | C101: =SUM(E101:I101) -> 6.64 | D101: ='[23]road inventory 2018'!C112 -> 6.5 | E101: 0 | F101: 0 | G101: 0 | H101: 6.64 | I101: 0 | J101: Fair | K101: km sta.184+300
A102: 53 | B102: Ipilan Linao Road | C102: =SUM(E102:I102) -> 6.46 | D102: ='[23]road inventory 2018'!C113 -> 6.4 | E102: 5.64 | F102: 0 | G102: 0 | H102: 0.82 | I102: 0 | J102: Fair | K102: km sta.180+150
A103: 54 | B103: Ipilan Sea Road | C103: =SUM(E103:I103) -> 1.69 | D103: ='[23]road inventory 2018'!C114 -> 1.6 | E103: 1.18 | F103: 0 | G103: 0 | H103: 0.51 | I103: 0 | J103: Good | K103: km sta.180+700
A104: 103 | B104: Barong-Barong Feeder Road | C104: =SUM(E104:I104) -> 1.27 | D104: ='[23]road inventory 2018'!C115 -> 1.2 | E104: 0.19 | F104: 0 | G104: 0 | H104: 1.08 | I104: 0 | J104: Good | K104: km sta.182+700
A105: 55 | B105: Barong-Barong Danadio Road | C105: =SUM(E105:I105) -> 4.18 | D105: ='[23]road inventory 2018'!C116 -> 4.1 | E105: 0 | F105: 0 | G105: 0 | H105: 4.18 | I105: 0 | J105: Fair | K105: km sta.183+250
A106: 57 | B106: Tagusao Feeder Road | C106: =SUM(E106:I106) -> 1.36 | D106: ='[23]road inventory 2018'!C117 -> 1.3 | E106: 0.3 | F106: 0 | G106: 0 | H106: 1.06 | I106: 0 | J106: Fair | K106: km sta.183+500
A107: 97 | B107: Aribungos Feeder Road | C107: =SUM(E107:I107) -> 8.45 | D107: ='[23]road inventory 2018'!C120 -> 8.3 | E107: 8.45 | F107: 0 | G107: 0 | H107: 0 | I107: 0 | J107: Good | K107: km sta.186+100
A108: 56 | B108: Ipilan - Mainit Road | C108: =SUM(E108:I108) -> 5.72 | D108: ='[23]road inventory 2018'!C121 -> 5.7 | E108: 1.73 | F108: 0 | G108: 0 | H108: 3.99 | I108: 0 | J108: Fair | K108: km sta.182+050
A109: 60 | B109: Junction Mainit Road | C109: =SUM(E109:I109) -> 9.2 | D109: ='[23]road inventory 2018'!C122 -> 9.2 | E109: 7.1 | F109: 0 | G109: 0 | H109: 2.1 | I109: 0 | J109: Good | K109: km sta.189+95
...

Sheet CORE ROAD
A1: ROAD ID | B1: ROAD NAME | C1: TOTAL LENGTH | D1: SURFACE TYPE
D2: 2019 | H2: 2020 | L2: 2021 | P2: 2019 | Q2: 2020 | R2: 2021
D3: CONCRETE | E3: ASPHALT | F3: EARTH | G3: GRAVEL | H3: CONCRETE | I3: ASPHALT | J3: EARTH | K3: GRAVEL | L3: CONCRETE | M3: ASPHALT | N3: EARTH | O3: GRAVEL
A4: 132 | B4: Highway Junction Tumarbong Road | C4: 13.5 | D4: 6.58 | E4: 0 | F4: 0 | G4: =6.73+0.19 -> 6.92 | H4: 6.58 | I4: 0 | J4: 0 | K4: =6.73+0.19 -> 6.92 | L4: =H4 -> 6.58 | M4: 0 | N4: 0 | O4: =K4 -> 6.92 | P4: =SUM(D4:G4) -> 13.5 | Q4: =SUM(H4:K4) -> 13.5 | R4: =SUM(L4:O4) -> 13.5
A5: 156 | B5: Latongay - Sta. Teresita Road | C5: 20 | D5: 8.205 | E5: 0 | F5: 0 | G5: 11.795 | H5: 8.205 | I5: 0 | J5: 0 | K5: 11.795 | L5: 8.205 | M5: 0 | N5: 0 | O5: 11.795 | P5: =SUM(D5:G5) -> 20 | Q5: =SUM(H5:K5) -> 20 | R5: =SUM(L5:O5) -> 20
A6: 160 | B6: Araceli - Dumaran Road (A) | C6: 28 | D6: =L6 -> 9.744 | E6: 0 | F6: 0 | G6: =O6 -> 18.256 | H6: =D6 -> 9.744 | I6: 0 | J6: 0 | K6: =G6 -> 18.256 | L6: 9.744 | M6: 0 | N6: 0 | O6: 18.256 | P6: =SUM(D6:G6) -> 28 | Q6: =SUM(H6:K6) -> 28 | R6: =SUM(L6:O6) -> 28
A7: 158 | B7: Dumaran - Araceli Road (B) | C7: 7.2 | D7: 0 | E7: 0 | F7: 0 | G7: 7.2 | H7: 4.08 | I7: 0 | J7: 3.12 | K7: 0 | L7: 4.08 | M7: 0 | N7: 0 | O7: 3.12 | P7: =SUM(D7:G7) -> 7.2 | Q7: =SUM(H7:K7) -> 7.2 | R7: =SUM(L7:O7) -> 7.2
A8: 202 | B8: Lungsod - Igabas - Emilod Road-A | C8: 5.3 | D8: 0.9 | E8: 0 | F8: 0 | G8: 4.4 | H8: =D8 -> 0.9 | I8: 0 | J8: 0 | K8: =G8 -> 4.4 | L8: 1.37 | M8: 0 | N8: 0 | O8: 3.93 | P8: =SUM(D8:G8) -> 5.3 | Q8: =SUM(H8:K8) -> 5.3 | R8: =SUM(L8:O8) -> 5.3
A9: 215 | B9: Lungsod - Igabas - Emilod Road -B | C9: 3.8 | D9: 0 | E9: 0 | F9: 0 | G9: 3.8 | H9: 0 | I9: 0 | J9: 0 | K9: 3.8 | L9: 1 | M9: 2.8 | N9: 0 | O9: 0 | P9: =SUM(D9:G9) -> 3.8 | Q9: =SUM(H9:K9) -> 3.8 | R9: =SUM(L9:O9) -> 3.8
A10: 201 | B10: Lungsod Balaguen Road A | C10: 5.2 | D10: =L10 -> 2.7 | E10: 0 | F10: 0 | G10: =O10 -> 2.5 | H10: =L10 -> 2.7 | I10: 0 | J10: 0 | K10: =G10 -> 2.5 | L10: 2.7 | M10: 0 | N10: 0 | O10: 2.5 | P10: =SUM(D10:G10) -> 5.2 | Q10: =SUM(H10:K10) -> 5.2 | R10: =SUM(L10:O10) -> 5.2
A11: 208 | B11: Lungsod - Balaguen Road B | C11: 4.3 | D11: 0 | E11: 0 | F11: 0 | G11: 4.3 | H11: 0 | I11: 0 | J11: 0 | K11: 4.3 | L11: 1 | M11: 0.25 | N11: 0 | O11: 3.05 | P11: =SUM(D11:G11) -> 4.3 | Q11: =SUM(H11:K11) -> 4.3 | R11: =SUM(L11:O11) -> 4.3
A12: 121 | B12: Liminangcong-Cataban Road | C12: 23.2 | D12: 1.3 | E12: 0 | F12: =1.72-0.1 -> 1.62 | G12: 20.28 | H12: 3.603 | I12: 0 | J12: =F12 -> 1.62 | K12: 17.977 | L12: 3.603 | M12: 0 | N12: 1.72 | O12: 17.877 | P12: =SUM(D12:G12) -> 23.2 | Q12: =SUM(H12:K12) -> 23.2 | R12: =SUM(L12:O12) -> 23.2
A13: 17 | B13: Magbabadil - Baraki Road | C13: 4 | D13: =L13 -> 1.422 | E13: 0 | F13: 0 | G13: =O13 -> 2.578 | H13: =D13 -> 1.422 | I13: 0 | J13: 0 | K13: =G13 -> 2.578 | L13: 1.422 | M13: 0 | N13: 0 | O13: 2.578 | P13: =SUM(D13:G13) -> 4 | Q13: =SUM(H13:K13) -> 4 | R13: =SUM(L13:O13) -> 4
A14: 26 | B14: Taritien Section Road | C14: 5.9 | D14: =L14 -> 1.85 | E14: 0 | F14: 0 | G14: =O14 -> 4.05 | H14: =L14 -> 1.85 | I14: 0 | J14: 0 | K14: =O14 -> 4.05 | L14: 1.85 | M14: 0 | N14: 0 | O14: 4.05 | P14: =SUM(D14:G14) -> 5.9 | Q14: =SUM(H14:K14) -> 5.9 | R14: =SUM(L14:O14) -> 5.9
A15: 123 | B15: Tumarbong-Ilian Road | C15: 17 | D15: 12.19 | E15: 0 | F15: 0 | G15: =9.63-4.82 -> 4.81 | H15: 14 | I15: 0 | J15: 0 | K15: =7.82-4.82 -> 3 | L15: 12.19 | M15: 0 | N15: 0 | O15: 4.81 | P15: =SUM(D15:G15) -> 17 | Q15: =SUM(H15:K15) -> 17 | R15: =SUM(L15:O15) -> 17
A16: 122 | B16: Ilian - Bagong Bayan Road | C16: 3.25 | D16: 0 | E16: 0 | F16: 0 | G16: 3.25 | H16: 2.092 | I16: 0 | J16: 0 | K16: =1.348-0.19 -> 1.158 | L16: 2.092 | M16: 0 | N16: 0 | O16: 1.158 | P16: =SUM(D16:G16) -> 3.25 | Q16: =SUM(H16:K16) -> 3.25 | R16: =SUM(L16:O16) -> 3.25
A17: 130 | B17: Latongay - Bagumbayan Road | C17: 6 | D17: 0 | E17: 0 | F17: 1.19 | G17: 4.81 | H17: 0 | I17: 0 | J17: 1.19 | K17: 4.81 | L17: 1.73 | M17: 0 | N17: 4.27 | O17: 0 | P17: =SUM(D17:G17) -> 6 | Q17: =SUM(H17:K17) -> 6 | R17: =SUM(L17:O17) -> 6
A18: 151 | B18: Maranlaw - Demerawat Road | C18: 4 | D18: 0 | E18: 0 | F18: 0 | G18: 4 | H18: 0 | I18: 0 | J18: 0 | K18: 4 | L18: 0 | M18: 0 | N18: 0 | O18: 4 | P18: =SUM(D18:G18) -> 4 | Q18: =SUM(H18:K18) -> 4 | R18: =SUM(L18:O18) -> 4
A19: ** | B19: Pularaquen - Bagumbayan | C19: 13.4 | P19: =C19 -> 13.4 | Q19: =C19 -> 13.4 | R19: =C19 -> 13.4
A20: 119 | B20: Alimanguan - Sto. Niño Road | C20: 5.5 | D20: 0 | E20: 0 | F20: 0 | G20: 5.5 | H20: 0 | I20: 0 | J20: 0 | K20: 5.5 | L20: 0 | M20: 0 | N20: 0 | O20: 5.5 | P20: =SUM(D20:G20) -> 5.5 | Q20: =SUM(H20:K20) -> 5.5 | R20: =SUM(L20:O20) -> 5.5
A21: 124 | B21: Sto. Niño-New Canipo-Binga Road | C21: 17 | D21: 3.52 | E21: 0 | F21: 0 | G21: =8.98+4.5 -> 13.48 | H21: 3.52 | I21: 0 | J21: 0 | K21: =8.98+4.5 -> 13.48 | L21: 3.52 | M21: 0 | N21: 0 | O21: 13.48 | P21: =SUM(D21:G21) -> 17 | Q21: =SUM(H21:K21) -> 17 | R21: =SUM(L21:O21) -> 17
A22: 139 | B22: Tumarbong - Antonino Road | C22: 8.9 | D22: 0 | E22: 0 | F22: 0 | G22: 8.9 | H22: 0 | I22: 0 | J22: 0 | K22: 8.9 | L22: 0 | M22: 0 | N22: 0 | O22: 8.9 | P22: =SUM(D22:G22) -> 8.9 | Q22: =SUM(H22:K22) -> 8.9 | R22: =SUM(L22:O22) -> 8.9
A23: 154 | B23: Catama - Tanatanaen Road | C23: 7 | D23: 0 | E23: 0 | F23: 0 | G23: 7 | H23: 0 | I23: 0 | J23: 0 | K23: 7 | L23: 0.15 | M23: 0 | N23: 0 | O23: 6.85 | P23: =SUM(D23:G23) -> 7 | Q23: =SUM(H23:K23) -> 7 | R23: =SUM(L23:O23) -> 7
A24: 135 | B24: Tanatanaen - Maragok Road | C24: 4.4 | D24: 0 | E24: 0 | F24: 0 | G24: 4.4 | H24: 0 | I24: 0 | J24: 0 | K24: 4.4 | L24: 0 | M24: 0 | N24: 0 | O24: 4.4 | P24: =SUM(D24:G24) -> 4.4 | Q24: =SUM(H24:K24) -> 4.4 | R24: =SUM(L24:O24) -> 4.4
A25: 20 | B25: Aporawan-Daan-Cabigaan Road | C25: 7.6 | D25: 0 | E25: 0 | F25: 0 | G25: 7.6 | H25: 0 | I25: 0 | J25: 0 | K25: 7.6 | L25: 1.9 | M25: 0 | N25: 4.53 | O25: 1.17 | P25: =SUM(D25:G25) -> 7.6 | Q25: =SUM(H25:K25) -> 7.6 | R25: =SUM(L25:O25) -> 7.6
A26: 9 | B26: Magbabadil - Cabigaan Road | C26: 9 | D26: 8.65 | E26: 0 | F26: 0 | G26: 0.35 | H26: 8.65 | I26: 0 | J26: 0 | K26: 0.35 | L26: 8.646 | M26: 0 | N26: 0 | O26: 0.354 | P26: =SUM(D26:G26) -> 9 | Q26: =SUM(H26:K26) -> 9 | R26: =SUM(L26:O26) -> 9
A27: 10 | B27: Plaridel - Apis Cabigaan Road | C27: 13.6 | D27: 8.79 | E27: 0 | F27: 0 | G27: =5-0.19 -> 4.81 | H27: 8.79 | I27: 0 | J27: 0 | K27: =5-0.19 -> 4.81 | L27: 10.12 | M27: 0 | N27: 0 | O27: 3.48 | P27: =SUM(D27:G27) -> 13.6 | Q27: =SUM(H27:K27) -> 13.6 | R27: =SUM(L27:O27) -> 13.6
A28: 47 | B28: Abo-Abo - Isugod Road | C28: 17 | D28: 0.27 | E28: 0 | F28: 0 | G28: =16.93-0.2 -> 16.73 | H28: 0.27 | I28: 0 | J28: 0 | K28: =16.93-0.2 -> 16.73 | L28: 1.31 | M28: 0 | N28: 0 | O28: 15.69 | P28: =SUM(D28:G28) -> 17 | Q28: =SUM(H28:K28) -> 17 | R28: =SUM(L28:O28) -> 17
A29: 99 | B29: Panitian - Tabud Road | C29: 14.1 | D29: 0 | E29: 0 | F29: 0 | G29: 14.1 | H29: 2.1 | I29: 0 | J29: 0 | K29: 12 | L29: 2.1 | M29: 0 | N29: 0 | O29: 12 | P29: =SUM(D29:G29) -> 14.1 | Q29: =SUM(H29:K29) -> 14.1 | R29: =SUM(L29:O29) -> 14.1
A30: 100 | B30: Pulot III-Tabud Road | C30: 7.8 | D30: 0.3 | E30: 0 | F30: 0 | G30: 7.5 | H30: 2 | I30: 0 | J30: 5.8 | K30: 0 | L30: 2 | M30: 0 | N30: 0 | O30: 5.8 | P30: =SUM(D30:G30) -> 7.8 | Q30: =SUM(H30:K30) -> 7.8 | R30: =SUM(L30:O30) -> 7.8
A31: 91 | B31: Balabac-Catagupan Road | C31: 12.9 | D31: 10 | E31: 0 | F31: 0 | G31: =3.07-0.17 -> 2.9 | H31: 10 | I31: 0 | J31: 0 | K31: =3.07-0.17 -> 2.9 | L31: 12.21 | M31: 0 | N31: 0 | O31: 0.69 | P31: =SUM(D31:G31) -> 12.9 | Q31: =SUM(H31:K31) -> 12.9 | R31: =SUM(L31:O31) -> 12.9
A32: 190 | B32: Cheey - San Jose Road | C32: 17.5 | D32: 0 | E32: 0 | F32: 0 | G32: 17.5 | H32: 0 | I32: 0 | J32: 0 | K32: 17.5 | L32: 0 | M32: 0 | N32: 0 | O32: 17.5 | P32: =SUM(D32:G32) -> 17.5 | Q32: =SUM(H32:K32) -> 17.5 | R32: =SUM(L32:O32) -> 17.5
A33: 186 | B33: New Quezon - Cheey Road | C33: 10.5 | D33: 0 | E33: 0 | F33: 0 | G33: 10.5 | H33: 0 | I33: 0 | J33: 0 | K33: 10.5 | L33: 0 | M33: 0 | N33: 0 | O33: 10.5 | P33: =SUM(D33:G33) -> 10.5 | Q33: =SUM(H33:K33) -> 10.5 | R33: =SUM(L33:O33) -> 10.5
A34: 185 | B34: New Busuanga-New Quezon rd | C34: 7.6 | D34: 0 | E34: 0 | F34: 0 | G34: 7.6 | H34: 0 | I34: 0 | J34: 0 | K34: 7.6 | L34: 0 | M34: 0 | N34: 0 | O34: 7.6 | P34: =SUM(D34:G34) -> 7.6 | Q34: =SUM(H34:K34) -> 7.6 | R34: =SUM(L34:O34) -> 7.6
A35: 92 | B35: Catagupan - Agutayan Road | C35: 5.6 | D35: 3 | E35: 0 | F35: 0 | G35: 2.6 | H35: 3 | I35: 0 | J35: 0 | K35: 2.6 | L35: 5.6 | M35: 0 | N35: 0 | O35: 0 | P35: =SUM(D35:G35) -> 5.6 | Q35: =SUM(H35:K35) -> 5.6 | R35: =SUM(L35:O35) -> 5.6
A36: 195 | B36: Binudac-Botnogan-Malaking Patag Rd | C36: 3.9 | D36: 1.06 | E36: 0 | F36: 0 | G36: =3.95-1.11 -> 2.84 | H36: 1.06 | I36: 0 | J36: 0 | K36: =3.95-1.11 -> 2.84 | L36: 1.2 | M36: 0 | N36: 0 | O36: 2.7 | P36: =SUM(D36:G36) -> 3.9 | Q36: =SUM(H36:K36) -> 3.9 | R36: =SUM(L36:O36) -> 3.9
A37: 194 | B37: Cabulihan - Malaking Patag Road | C37: 5.3 | D37: 3.54 | E37: 0 | F37: 0 | G37: 1.76 | H37: 3.54 | I37: 0 | J37: 0 | K37: 1.76 | L37: 3.541 | M37: 0 | N37: 0 | O37: 1.759 | P37: =SUM(D37:G37) -> 5.3 | Q37: =SUM(H37:K37) -> 5.3 | R37: =SUM(L37:O37) -> 5.3
A38: 171 | B38: Sta. Cruz-Talaga Road | C38: 8.741 | D38: 1.18 | E38: 0 | F38: 0 | G38: 7.561 | H38: 1.18 | I38: 0 | J38: 0 | K38: 7.561 | L38: 1.18 | M38: 0 | N38: 0 | O38: 7.561 | P38: =SUM(D38:G38) -> 8.741 | Q38: =SUM(H38:K38) -> 8.741 | R38: =SUM(L38:O38) -> 8.741
A39: 214 | B39: Agutaya - Villasol Road | C39: 4.5 | D39: 0.7 | E39: 0 | F39: 0 | G39: 3.8 | H39: 0.7 | I39: 0 | J39: 0 | K39: 3.8 | L39: 0.7 | M39: 0 | N39: 0 | O39: 3.8 | P39: =SUM(D39:G39) -> 4.5 | Q39: =SUM(H39:K39) -> 4.5 | R39: =SUM(L39:O39) -> 4.5
A40: 212 | B40: Agutaya - Villa Fria Road | C40: 2.75 | D40: 2.6 | E40: 0 | F40: 0 | G40: 0.15 | H40: 2.6 | I40: 0 | J40: 0 | K40: 0.15 | L40: 2.6 | M40: 0 | N40: 0 | O40: 0.15 | P40: =SUM(D40:G40) -> 2.75 | Q40: =SUM(H40:K40) -> 2.75 | R40: =SUM(L40:O40) -> 2.75
A41: 142 | B41: Abongan-Alacalian-Kawakayan-Binga Rd. | C41: 19.3 | D41: 0.8 | E41: 0 | F41: 0 | G41: =20.89-2.39 -> 18.5 | H41: 0.8 | I41: 0 | J41: 0 | K41: =20.89-2.39 -> 18.5 | L41: 3 | M41: 0 | N41: 0 | O41: 16.3 | P41: =SUM(D41:G41) -> 19.3 | Q41: =SUM(H41:K41) -> 19.3 | R41: =SUM(L41:O41) -> 19.3
A42: ** | B42: Barake - Sagpangan | C42: 9.6 | P42: =C42 -> 9.6 | Q42: =C42 -> 9.6 | R42: =C42 -> 9.6
A43: 44 | B43: Junction Highway - Burirao Road | C43: 5.3 | D43: 1.5 | E43: 0 | F43: 0 | G43: 3.8 | H43: 1.5 | I43: 0 | J43: 0 | K43: 3.8 | L43: 1.5 | M43: 0 | N43: 0 | O43: 3.8 | P43: =SUM(D43:G43) -> 5.3 | Q43: =SUM(H43:K43) -> 5.3 | R43: =SUM(L43:O43) -> 5.3
A44: 224 | B44: Panitian - Abokayan Road | C44: 7.2 | D44: 1.02 | E44: 0 | F44: 0 | G44: =6.22-0.04 -> 6.18 | H44: 1.98 | I44: 0 | J44: 0 | K44: =5.26-0.04 -> 5.22 | L44: 3.21 | M44: 0 | N44: 0 | O44: 3.99 | P44: =SUM(D44:G44) -> 7.2 | Q44: =SUM(H44:K44) -> 7.2 | R44: =SUM(L44:O44) -> 7.2
A45: 38 | B45: Teresa - Batang-Batang Road | C45: 4.4 | D45: 0 | E45: 0 | F45: 0 | G45: 4.4 | H45: 1.504 | I45: 0 | J45: 0 | K45: 2.9 | L45: 1.58 | M45: 0 | N45: 0 | O45: 2.82 | P45: =SUM(D45:G45) -> 4.4 | Q45: =SUM(H45:K45) -> 4.404 | R45: =SUM(L45:O45) -> 4.4
A46: 25 | B46: Taritien Sea Road | C46: 1.7 | D46: 0 | E46: 0 | F46: 0 | G46: 1.7 | H46: 0 | I46: 0 | J46: 0 | K46: 1.7 | L46: 0 | M46: 0 | N46: 0 | O46: 1.7 | P46: =SUM(D46:G46) -> 1.7 | Q46: =SUM(H46:K46) -> 1.7 | R46: =SUM(L46:O46) -> 1.7
A47: 18 | B47: Tigman - Rizal - Dumangueña Road | C47: 10.5 | D47: 4.54 | E47: 0 | F47: 0 | G47: 5.96 | H47: 4.54 | I47: 0 | J47: 0 | K47: 5.96 | L47: 10.5 | M47: 0 | N47: 0 | O47: 0 | P47: =SUM(D47:G47) -> 10.5 | Q47: =SUM(H47:K47) -> 10.5 | R47: =SUM(L47:O47) -> 10.5
A48: ** | B48: Taberna - Bucana - Duli - Dagmay Road | C48: 14 | P48: =C48 -> 14 | Q48: =C48 -> 14 | R48: =C48 -> 14
A49: 96 | B49: Tub - Tub - Amas Road | C49: 5.7 | D49: 0.3 | E49: 0 | F49: 0 | G49: 5.4 | H49: 2.09 | I49: 0 | J49: 0 | K49: =3.463+0.15 -> 3.613 | L49: 2.089 | M49: 0 | N49: 0 | O49: 3.611 | P49: =SUM(D49:G49) -> 5.7 | Q49: =SUM(H49:K49) -> 5.703 | R49: =SUM(L49:O49) -> 5.7
A50: 80 | B50: Sandoval-Igang -Igang -Sarong Road | C50: 15.7 | D50: 0.7 | E50: 0 | F50: 0 | G50: 15 | H50: 0.7 | I50: 0 | J50: 0 | K50: 15 | L50: 0.7 | M50: 0 | N50: 0 | O50: 15 | P50: =SUM(D50:G50) -> 15.7 | Q50: =SUM(H50:K50) -> 15.7 | R50: =SUM(L50:O50) -> 15.7
A51: 81 | B51: Ocayan Road | C51: 3.8 | D51: 0.27 | E51: 0 | F51: 0 | G51: =3.62-0.09 -> 3.53 | H51: 0.27 | I51: 0 | J51: 0 | K51: =3.62-0.09 -> 3.53 | L51: 0.47 | M51: 0 | N51: 0 | O51: 3.33 | P51: =SUM(D51:G51) -> 3.8 | Q51: =SUM(H51:K51) -> 3.8 | R51: =SUM(L51:O51) -> 3.8
A52: ** | B52: Itangil - Magsaysay Road | C52: 8.7 | P52: =C52 -> 8.7 | Q52: =C52 -> 8.7 | R52: =C52 -> 8.7
A53: ** | B53: Salban - Culasian - Magsaysay Road | C53: 17.484 | P53: =C53 -> 17.484 | Q53: =C53 -> 17.484 | R53: =C53 -> 17.484
A54: ** | B54: Malaking Patag - Galoc Road | C54: 13.1 | P54: =C54 -> 13.1 | Q54: =C54 -> 13.1 | R54: =C54 -> 13.1
A55: ** | B55: Sandoval - Silanga Road | C55: 9.75 | P55: =C55 -> 9.75 | Q55: =C55 -> 9.75 | R55: =C55 -> 9.75
A56: ** | B56: San Juan - Bacao - Catep - Calasag Road | C56: 10 | P56: =C56 -> 10 | Q56: =C56 -> 10 | R56: =C56 -> 10
A57: ** | B57: Poblacion - Malaking Ilog - Indalawan | C57: 13.7 | P57: =C57 -> 13.7 | Q57: =C57 -> 13.7 | R57: =C57 -> 13.7
B58: GRAND TOTAL | C58: =SUM(C4:C57) -> 525.175 | D58: =SUM(D4:D57) -> 97.631 | E58: =SUM(E4:E51) -> 0 | F58: =SUM(F4:F51) -> 2.81 | G58: =SUM(G4:G51) -> 315 | H58: =SUM(H4:H51) -> 115.97 | I58: =SUM(I4:I51) -> 0 | J58: =SUM(J4:J51) -> 11.73 | K58: =SUM(K4:K51) -> 287.748 | L58: =SUM(L4:L51) -> 137.392 | ... O58: =SUM(O4:O51) -> 264.479 | P58: =SUM(P4:P57) -> 525.175 | Q58: =SUM(Q4:Q57) -> 525.182 | R58: =SUM(R4:R57) -> 525.175
B60: Please note: | C60: Roads with (**) are not in the masterlist of Provincial Roads.
C61: Based on the list from SECTION 6: ROAD SECTOR INVESTMENT PROGRAM, Indicator 5 of LRMPA, some roads here are split for other roads listed in Section 6 are considered to be just one road network. i.e. SANDOVAL - IGANG IGANG SARONG - OCAYAN ROAD, in the table above, 2 road networks were combined; SANDOVAL - IGANG IGANG - SARONG ROAD & OCAYAN ROAD.)
C66: teh, yung nakahighlight na red, in most cases, inadopt ko yung latest, 2021. kasi mas mataas yung concrete value ng mga previous. Tapos update ko nalang dun sa 2019 & 2020 inventory, para nakareflect. (pero utang ko muna ito the, pagoda nako for today's video). THANKS2!
C72: NILAGAY KO LANG YUNG 2019 & 2020 TAB DITO, PARA DI NAKO HANAP PAG MAGUPDATE AKO. BUKAS KO NAMAN GABI THE GAWIN YUNG KULANG KO SA ROAD INVENTORY. PERO ITONG CORE, I SUGGEST ITO NALANG IADOPT NATEN, SINCE YUNG PIRMADO EH YUNG LATEST AT YUNG TOTAL LENGTH AY MAY BASIS TAYO NUNG MGA SINAUNANG DATA. THANKS!

Sheet inventory2022 (FINAL)
B1: PROVINCIAL ENGINEER'S OFFICE
B2: PROVINCIAL ROAD NETWORK AND ITS STATUS / CONDITION
B3: 2022
B5: ROAD ID | C5: ROAD NAME | D5: 2022 LENGTH (KM) | E5: LENGTH (KM) | F5: SURFACE TYPE (KM) | J5: ROAD CONDITION | K5: REVISED LENGTH (km/s.) | L5: KILOMETER POST
F6: CONCRETE | G6: ASPHALT | H6: EARTH | I6: GRAVEL
B7: MUNICIPALITY OF ABORLAN
A8: 1 | B8: 219 | C8: Junction - Isaub Road | E8: ='[1]road inventory 2018'!C10 -> 0.65 | F8: 0.25 | G8: 0 | H8: 0 | I8: 0.4 | J8: Fair | K8: =SUM(F8:I8) -> 0.65 | L8: km sta.57+800
A9: 2 | B9: 1 | C9: Sagpangan Road | E9: ='[1]road inventory 2018'!C11 -> 5.5 | F9: 4.88 | G9: 0 | H9: 0 | I9: 0.62 | J9: Good | K9: =SUM(F9:I9) -> 5.5 | L9: km sta.66+400
A10: 3 | B10: 2 | C10: Isaub - Marikit -Tubig Road | E10: ='[1]road inventory 2018'!C12 -> 0.8 | F10: 0.07 | G10: 0 | H10: 0 | I10: 0.73 | J10: Fair | K10: =SUM(F10:I10) -> 0.8 | L10: km sta.58+000
A11: 4 | B11: 3 | C11: Mailigan - Sagpangan Road | E11: ='[1]road inventory 2018'!C13 -> 4.9 | F11: 0 | G11: 0 | H11: 0 | I11: 4.9 | J11: Fair | K11: =SUM(F11:I11) -> 4.9 | L11: km sta.62+400
A12: 5 | B12: 4 | C12: Iraan - Tubig Road | E12: ='[1]road inventory 2018'!C14 -> 2.7 | F12: 0 | G12: 0 | H12: 0 | I12: 2.7 | J12: Fair | K12: =SUM(F12:I12) -> 2.7 | L12: km sta.64+900
A13: 6 | B13: 93 | C13: Iraan - Baraki Road | E13: ='[1]road inventory 2018'!C15 -> 3.9 | F13: 3.79 | G13: 0 | H13: 0 | I13: 0.11 | J13: Fair | K13: =SUM(F13:I13) -> 3.9 | L13: km sta.64+900
A14: 7 | B14: 218 | C14: Isaub - Sagpangan Road | E14: ='[1]road inventory 2018'!C16 -> 5.8 | F14: 0 | G14: 0 | H14: 0 | I14: 5.8 | J14: Fair | K14: =SUM(F14:I14) -> 5.8 | L14: km sta.58+000 | P14: SOUTH | Q14: TOTAL MAINLAND
A15: 8 | B15: 5 | C15: PNAC Road | E15: ='[1]road inventory 2018'!C17 -> 2.8 | F15: 2.8 | G15: 0 | H15: 0 | I15: 0 | J15: Fair | K15: =SUM(F15:I15) -> 2.8 | L15: km sta.64+900 | P15: =E32+E37+E54+E88+E118+E128+E132+E145 -> 476.35 | Q15: =P15+O232 -> 894.2
A16: 9 | B16: 6 | C16: San Juan Road | E16: ='[1]road inventory 2018'!C18 -> 3.9 | F16: =2.6+0.9 -> 3.5 | G16: 0 | H16: 0 | I16: 0.4 | J16: Good | K16: =SUM(F16:I16) -> 3.9 | L16: km sta.66+400 | Q16: =Q15+P204 -> 1244.015
A17: 10 | B17: 7 | C17: Aborlan - River Landing | E17: ='[1]road inventory 2018'!C19 -> 1.1 | F17: 1.1 | G17: 0 | H17: 0 | I17: 0 | J17: Fair | K17: =SUM(F17:I17) -> 1.1 | L17: km sta.67+100 | M17: =E9+E16+E19+E20+E28 -> 36
A18: 11 | B18: 8 | C18: Aborlan Poblacion Road | E18: ='[1]road inventory 2018'!C20 -> 0.6 | F18: 0.6 | G18: 0 | H18: 0 | I18: 0 | J18: Fair | K18: =SUM(F18:I18) -> 0.6 | L18: km sta.66+950
A19: 12 | B19: 9 | C19: Magbabadil - Cabigaan Road | E19: ='[1]road inventory 2018'!C21 -> 9 | F19: 8.646 | G19: 0 | H19: 0 | I19: 0.354 | J19: Good | K19: =SUM(F19:I19) -> 9 | L19: km sta.66+800 | N19: 8.646
A20: 13 | B20: 10 | C20: Plaridel - Apis Cabigaan Road | E20: ='[1]road inventory 2018'!C22 -> 13.6 | F20: =8.47+1.31+0.34 -> 10.12 | G20: 0 | H20: 0 | I20: 3.48 | J20: Good | K20: =SUM(F20:I20) -> 13.6 | L20: km sta.75+650
A21: 14 | B21: 11 | C21: Tagpait Feeder Road | E21: ='[1]road inventory 2018'!C23 -> 2.2 | F21: 1.3 | G21: 0 | H21: 0 | I21: 0.9 | J21: Fair | K21: =SUM(F21:I21) -> 2.2 | L21: km sta.69+000
A22: 15 | B22: 13 | C22: New Bantayan - Apis Road | E22: ='[1]road inventory 2018'!C24 -> 1.7 | F22: 0 | G22: 0 | H22: 0 | I22: 1.7 | J22: Poor | K22: =SUM(F22:I22) -> 1.7 | L22: km sta.69+200
A23: 16 | B23: 12 | C23: Tagbariri Road | E23: ='[1]road inventory 2018'!C25 -> 1.6 | F23: 0 | G23: 0 | H23: 0 | I23: 1.6 | J23: Poor | K23: =SUM(F23:I23) -> 1.6 | L23: km sta.69+100
A24: 17 | B24: 220 | C24: Tagbariri - Magsaysay Road | E24: ='[1]road inventory 2018'!C26 -> 2.3 | F24: 0 | G24: 0 | H24: 0 | I24: 2.3 | J24: Poor | K24: =SUM(F24:I24) -> 2.3 | L24: km sta.71+150
A25: 18 | B25: 14 | C25: Junction - Tigman Road | E25: ='[1]road inventory 2018'!C27 -> 4 | F25: 4 | G25: 0 | H25: 0 | I25: 0 | J25: Fair | K25: =SUM(F25:I25) -> 4 | L25: km sta.75+650
A26: 19 | B26: 15 | C26: Tigman - Rizal Road | E26: 3.2 | F26: 0 | G26: 0 | H26: 0 | I26: 3.2 | J26: Poor | K26: =SUM(F26:I26) -> 3.2 | L26: km sta.77+400 | M26: NOT EXISTING
A27: 20 | B27: 16 | C27: Tigman - Caburian Road | E27: ='[1]road inventory 2018'!C29 -> 1 | F27: 0 | G27: 0 | H27: 0 | I27: 1 | J27: Fair | K27: =SUM(F27:I27) -> 1 | L27: km sta.78+150
A28: 21 | B28: 17 | C28: Magbabadil - Baraki Road | E28: ='[1]road inventory 2018'!C30 -> 4 | F28: 1.422 | G28: 0 | H28: 0 | I28: 2.578 | J28: Good | K28: =SUM(F28:I28) -> 4 | L28: km sta.73+400 | N28: 1.422
A29: 22 | B29: 18 | C29: Tigman - Rizal - Dumangueña Road | E29: ='[1]road inventory 2018'!C31 -> 10.5 | F29: 10.5 | G29: 0 | H29: 0 | I29: 0 | J29: Fair | K29: =SUM(F29:I29) -> 10.5 | L29: km sta.77+400 | M29: cmgp 2019, 2kms | N29: 2
A30: 23 | B30: 221 | C30: Hi-way Jct. Plaridel-Tigman-Caburian Rd | E30: ='[1]road inventory 2018'!C32 -> 5.2 | F30: 1.17 | G30: 0 | H30: 0 | I30: 4.03 | J30: Fair | K30: =SUM(F30:I30) -> 5.2 | L30: km sta.76+500
A31: 24 | B31: 20 | C31: Aporawan-Daan-Cabigaan Road | E31: ='[1]road inventory 2018'!C33 -> 7.6 | F31: 1.9 | G31: 0 | H31: 4.53 | I31: 1.17 | J31: Bad | K31: =SUM(F31:I31) -> 7.6
C32: SUB-TOTAL | E32: =SUM(E8:E31) -> 98.55 | F32: =SUM(F8:F31) -> 56.048 | G32: =SUM(G8:G31) -> 0 | H32: =SUM(H8:H31) -> 4.53 | I32: =SUM(I8:I31) -> 37.972
B34: MUNICIPALITY OF BALABAC
A35: 1 | B35: 91 | C35: Balabac-Catagupan Road | E35: ='[1]road inventory 2018'!C169 -> 12.9 | F35: =0.04+0.29+0.12+1.23+1+3+1+1.23+0.77+1+0.77+0.86 +0.9 -> 12.21 | G35: 0 | H35: 0 | I35: =0.06+0.26+0.36+0.01 -> 0.69 | J35: Good | K35: =SUM(F35:I35) -> 12.9 | L35: km sta.000 -12+900
A36: 2 | B36: 92 | C36: Catagupan - Agutayan Road | E36: ='[1]road inventory 2018'!C170 -> 5.6 | F36: 5.6 | G36: 0 | H36: 0 | I36: 0 | J36: Fair | K36: =SUM(F36:I36) -> 5.6 | L36: km sta.12+900 -18+500
C37: SUB-TOTAL | E37: =SUM(E35:E36) -> 18.5 | F37: =SUM(F35:F36) -> 17.81 | G37: =SUM(G35:G36) -> 0 | H37: =SUM(H35:H36) -> 0 | I37: =SUM(I35:I36) -> 0.69
B39: MUNICIPALITY OF BATARAZA
A40: 1 | B40: 95 | C40: a. Inogbong Sea Road | E40: ='[1]road inventory 2018'!C149 -> 3 | F40: 1.02 | G40: 0 | H40: 0 | I40: 1.98 | J40: Poor | K40: =SUM(F40:I40) -> 3 | L40: km sta.215+100
A41: 2 | B41: 77 | C41: Bataraza Poblacion Road | E41: ='[1]road inventory 2018'!C150 -> 0.7 | F41: 0 | G41: 0 | H41: 0 | I41: 0.7 | J41: Good | K41: =SUM(F41:I41) -> 0.7 | L41: km sta.216+720
A42: 3 | B42: 94 | C42: Marangas Sea Road | E42: ='[1]road inventory 2018'!C151 -> 0.6 | F42: 0 | G42: 0 | H42: 0 | I42: 0.6 | J42: Good | K42: =SUM(F42:I42) -> 0.6 | L42: km sta.217+260
A43: 4 | B43: 78 | C43: Marangas Feeder Road | E43: ='[1]road inventory 2018'!C152 -> 3.8 | F43: 0.69 | G43: 0 | H43: 0 | I43: 3.11 | J43: Poor | K43: =SUM(F43:I43) -> 3.8 | L43: km sta.218+400
A44: 5 | B44: 79 | C44: Iniam - Bono-bono Road | E44: ='[1]road inventory 2018'!C153 -> 1.9 | F44: 0.12 | G44: 0 | H44: 0 | I44: 1.78 | J44: Bad | K44: =SUM(F44:I44) -> 1.9 | L44: km sta.221+800
A45: 6 | B45: 80 | C45: Sandoval-Igang -Igang -Sarong Road | E45: ='[1]road inventory 2018'!C154 -> 15.7 | F45: =0.25+0.26+0.19 -> 0.7 | G45: 0 | H45: 0 | I45: 15 | J45: Bad | K45: =SUM(F45:I45) -> 15.7 | L45: km sta.238+500
A46: 7 | B46: 81 | C46: Ocayan Road | E46: ='[1]road inventory 2018'!C155 -> 3.8 | F46: =0.2+0.27 -> 0.47 | G46: 0 | H46: 0 | I46: 3.33 | J46: Fair | K46: =SUM(F46:I46) -> 3.8 | L46: km sta.243+580
A47: 8 | B47: 82 | C47: Taratak Sea R oad | E47: ='[1]road inventory 2018'!C156 -> 5.4 | F47: =0.42+0.8 -> 1.22 | G47: 0 | H47: 0 | I47: 4.18 | J47: Poor | K47: =SUM(F47:I47) -> 5.4 | L47: km sta.256+200
A48: 9 | B48: 83 | C48: Sandoval Barak - Barakan Road | E48: ='[1]road inventory 2018'!C157 -> 4.2 | F48: =0.12+0.22 -> 0.34 | G48: 0 | H48: 0 | I48: 3.86 | J48: Fair | K48: =SUM(F48:I48) -> 4.2 | L48: km sta.238+500
A49: 10 | B49: 84 | C49: Brooke’s Pt.- Bataraza Friendship Sea Rd | E49: ='[1]road inventory 2018'!C158 -> 1.2 | F49: 0 | G49: 0 | H49: 0 | I49: 1.2 | J49: Bad | K49: =SUM(F49:I49) -> 1.2 | L49: km sta.211+270
A50: 11 | B50: 85 | C50: San Juan - Sarong Road | E50: ='[1]road inventory 2018'!C159 -> 2.8 | F50: 0 | G50: 0 | H50: 0 | I50: 2.8 | J50: Fair | K50: =SUM(F50:I50) -> 2.8 | L50: km sta.242+020
A51: 12 | B51: 86 | C51: Culandanum - Tarusan Road | E51: ='[1]road inventory 2018'!C160 -> 2.5 | F51: 0 | G51: 0 | H51: 0 | I51: =2.5 -> 2.5 | J51: Bad | K51: =SUM(F51:I51) -> 2.5 | L51: km sta.242+770
